Workbook

Sheet CALCULADORA COSTES
A1: Calculadora | B1: PRECIO (€/KG) | C1: CONSUMO (KG/KM) | D1: €/KM (ENERGIA) | E1: COSTE RENTING | F1: €/KM (ud. TRAILER) | G1: €/DIA (trailer) | H1: Extracoste | I1: TARIFA | K1: KG C02/KM | L1: % - CO2 | M1: COSTE EMISIÓN CO2 | R1: vs DUO D
A2: DIESEL | B2: 1 | C2: 0.28 | D2: =B2*C2 -> 0.28 | E2: 2000 | F2: ='GASOIL '!E48+E27*K2 -> 1.4076342 | G2: =F2*$B$14 -> 422.29025 | H2: =F2/$F$2-1 -> 0 | I2: =G2*(1+$B$18) -> 506.74831 | K2: =C2*P2 -> 0.69804 | L2: =($K$2-K2)/$K$2 -> 0 | M2: =$E$27*K2 -> 0 | O2: FE DIESEL | P2: 2.493 | R2: =F2/$F$9-1 -> 0.55787007
A3: GAS NATURAL | B3: 1.7 | C3: =E15/100 -> 0.264 | D3: =B3*C3 -> 0.4488 | E3: 2400 | F3: ='GAS NATURAL'!E47+E27/1000*K3 -> 1.6967605 | G3: =F3*$B$14 -> 509.02815 | H3: =F3/$F$2-1 -> 0.20539875 | I3: =G3*(1+$B$18) -> 610.83377 | K3: =P3*C3 -> 0.718344 | L3: =($K$2-K3)/$K$2 -> -0.029087158 | M3: =$E$27*K3 -> 0 | O3: FE LNG | P3: 2.721 | R3: =F3/$F$9-1 -> 0.87785464
A4: H2 | B4: 7 | C4: =E16/100 -> 0.09 | D4: =B4*C4 -> 0.63 | E4: 6200 | F4: ='H2'!E47+E27/1000*K4 -> 2.4839964 | G4: =F4*$B$14 -> 745.19891 | H4: =F4/$F$2-1 -> 0.76466045 | I4: =G4*(1+$B$18) -> 894.23869 | K4: 0 | L4: =($K$2-K4)/$K$2 -> 1 | M4: =$E$27*K4 -> 0 | R4: =F4/$F$9-1 -> 1.7491117
A5: BIOMETANO | B5: 1.8 | C5: =C3 -> 0.264 | D5: =B5*C5 -> 0.4752 | E5: =E3 -> 2400 | F5: =BIOMETANO!E47+E27/1000*K5 -> 1.7242694 | G5: =F5*$B$14 -> 517.28083 | H5: =F5/$F$2-1 -> 0.22494143 | I5: =G5*(1+$B$18) -> 620.73699 | K5: =C5*P3*(1-P9*P5)+C3*(1-P9) -> 0.0718344 | L5: =($K$2-K5)/$K$2 -> 0.89709128 | M5: =$E$27*K5 -> 0 | O5: % REDUCCIÓN BIO | P5: 0.9 | R5: =F5/$F$9-1 -> 0.9082996
A6: ELECTRICO | B6: 0.23 | C6: =E18/100 -> 1.83 | D6: =B6*C6 -> 0.4209 | E6: 4000 | F6: =ELÉCTRICO!G45+E27/1000*K6 -> 1.9192354 | G6: =F6*$B$14 -> 575.77062 | H6: =F6/$F$2-1 -> 0.36344756 | I6: =G6*(1+$B$18) -> 690.92474 | K6: 0 | L6: =($K$2-K6)/$K$2 -> 1 | M6: =$E$27*K6 -> 0 | O6: % REDUCCION HVO | P6: 0.9 | R6: =F6/$F$9-1 -> 1.1240742
A7: HVO | B7: 1.35 | C7: =C2 -> 0.28 | D7: =B7*C7 -> 0.378 | E7: =E2 -> 2000 | F7: =HVO!E48+E27/1000*K7 -> 1.5095542 | G7: =F7*$B$14 -> 452.86625 | H7: =F7/$F$2-1 -> 0.072405176 | I7: =G7*(1+$B$18) -> 543.43951 | K7: =C7*P2*P8*(1-P6)+C2*P2*(1-P8) -> 0.069804 | L7: =($K$2-K7)/$K$2 -> 0.9 | M7: =$E$27*K7 -> 0 | R7: =F7/$F$9-1 -> 0.67066793
A8: DUO H2 | B8: =B4 -> 7 | C8: =C4*2*(1-E20) -> 0.126 | D8: =B8*C8 -> 0.882 | E8: =E4 -> 6200 | F8: ='DUOTRAILER H2'!E48/2+E27*K8 -> 1.4735148 | G8: =F8*$B$14 -> 442.05444 | H8: =F8/$F$2-1 -> 0.046802363 | I8: =G8*(1+$B$18) -> 530.46532 | K8: 0 | L8: =($K$2-K8)/$K$2 -> 1 | M8: =$E$27*K8 -> 0 | O8: % HVO | P8: 1 | R8: =F8/$F$9-1 -> 0.63078207
A9: DUO GASOIL | B9: =B2 -> 1 | C9: =C2*2*(1-E20) -> 0.392 | D9: =B9*C9 -> 0.392 | E9: 2200 | F9: ='DUOTRAILER GASOIL'!E48/2+E27/1000*K9 -> 0.90356327 | G9: =F9*$B$14 -> 271.06898 | H9: =F9/$F$2-1 -> -0.35809795 | I9: =G9*(1+$B$18) -> 325.28278 | K9: =C9*P2/2 -> 0.488628 | L9: =($K$2-K9)/$K$2 -> 0.3 | M9: =$E$27*K9 -> 0 | O9: % Biometano | P9: 1 | R9: =F9/$F$9-1 -> 0
A10: DUO BIOMETANO | B10: =B5 -> 1.8 | C10: =C5*2*(1-E20) -> 0.3696 | D10: =B10*C10 -> 0.66528 | E10: =E5 -> 2400 | F10: ='DUOTRAILER BIOMETANO'!E48/2+E27/1000*K10 -> 1.0614264 | G10: =F10*$B$14 -> 318.42793 | H10: =F10/$F$2-1 -> -0.24595008 | I10: =G10*(1+$B$18) -> 382.11352 | K10: =K5*0.7 -> 0.05028408 | L10: =($K$2-K10)/$K$2 -> 0.9279639 | M10: =$E$27*K10 -> 0 | O10: % H2 VERDE | P10: 1 | R10: =F10/$F$9-1 -> 0.17471181
A11: DUO HVO | B11: =B7 -> 1.35 | C11: 0.41 | D11: =B11*C11 -> 0.5535 | E11: =E9 -> 2200 | F11: ='DUOTRAILER HVO'!E48/2+E27/1000*K11 -> 0.98754327 | G11: =F11*$B$14 -> 296.26298 | H11: =F11/$F$2-1 -> -0.29843756 | I11: =G11*(1+$B$18) -> 355.51558 | K11: =C11*0.174 -> 0.07134 | L11: =($K$2-K11)/$K$2 -> 0.89779955 | M11: =$E$27*K11 -> 0 | R11: =F11/$F$9-1 -> 0.092943131
A12: DUO ELECTRICO | B12: =B6 -> 0.23 | C12: =C6*(1-E20) -> 1.281 | D12: =B12*C12 -> 0.29463 | E12: =E6 -> 4000 | F12: ='DUOTRAILER ELECTRICO'!E48/2+E27/1000*K12 -> 0.99474905 | G12: =B14*F12 -> 298.42472 | H12: =F12/$F$2-1 -> -0.29331849 | I12: =G12*(1+$B$18) -> 358.10966 | K12: =K6 -> 0 | L12: =L6 -> 1 | M12: =M6 -> 0 | R12: =F12/$F$9-1 -> 0.10091798
A14: KMS VEHICULO /DIA | B14: 300 | C14: (Modificable) | D14: Consumo Diesel /100 km | E14: 31
A15: DIAS MES | B15: 22 | C15: (Vinculado) | D15: Consumo GNL/100 km | E15: 26.4
A16: Conductores * | B16: {=_xlfn.IFS(B14<700,1,B14=700,1,B14>700,2)} -> 1 | C16: > 700 kms ---> 2 Cond | D16: Consumo H2/100 km | E16: 9
A17: SALARIO CONDUCTOR (Tabla R) | B17: 3048 | C17: < --Solo tabla roja | D17: Consumo BioGNC / 100 km | E17: 26.4
A18: MARGEN | B18: 0.2 | D18: Consumo KWH /100 km | E18: =183 -> 183
A19: Tipo de trailer | B19: Trailer | C19: Dolly | D19: Consumo HVO / 100 km | E19: =E14*1.02 -> 31.62
A20: PRECIO SEMIRREMOLQUE | B20: 450 | C20: 200 | D20: % Ahorro consumo Duo | E20: 0.3
A21: OPERATIVA CORREDOR | D21: TIPO H2 | E21: Verde | F21: Gris
A22: COSTE TRAILER YARD/ | B22: 50 | D22: PRECIO H2 | E22: 6 | F22: 1
A23: COSTE TRANSPORTE PLAZA | B23: 500 | D23: VEHICULO | E23: SIMPLE | F23: DUO
A24: Nº DESCARGAS PLAZA | B24: 10 | D24: KMS AUTOPISTA | E24: 0 | F24: 0
A25: KMS CORREDOR DUO | B25: 600 | D25: PRECIO AUTOPISTA | E25: 0.26 | F25: =E25*1.5 -> 0.39
A26: Nº ACARREOS VIAJE | B26: 1 | D26: EXTRA CONDUCTOR | E26: 0.05 | F26: (Vehículo especial)
A27: FACTOR CORRECTOR TARIFA | B27: 0.12 | D27: PRECIO t CO2 | E27: 0
A28: Se aplica corrector al coste dia simple Se considera que el duotrailer puede tener más productividad en corredor, No así el simple.
A29: DIESEL | B29: KMS | C29: COSTE ACARREO +YARD | D29: COSTE DUO DIESEL | E29: COSTE DUO+ ACARREO | F29: COSTE SIMPLE | G29: EXTRACOSTE | H29: DUO VS SIMPLE | I29: TARIFA NORMAL
A30: RUTA A | B30: =B25 -> 600 | C30: =(B23/B24+B22)*B26 -> 100 | D30: =B30*F9 -> 542.13796 | E30: =C30+D30 -> 642.13796 | F30: =B30*F2 -> 844.58051 | G30: =E30/I30-1 -> -0.32115712 | H30: =E30/F30-1 -> -0.23969597 | I30: =F2*B25*(1+B27) -> 945.93017
A31: HVO | B31: KMS | C31: COSTE ACARREO+YARD | D31: COSTE DUO HVO | E31: COSTE DUO+ ACARREO | F31: COSTE SIMPLE | G31: EXTRACOSTE | H31: DUO VS SIMPLE | I31: TARIFA NORMAL
A32: RUTA A | B32: =B25 -> 600 | C32: =(B23/B24+B22)*B26 -> 100 | D32: =F11*B32 -> 592.52596 | E32: =C32+D32 -> 692.52596 | F32: =F30 -> 844.58051 | G32: =E32/I32-1 -> -0.26788891 | H32: =E32/F32-1 -> -0.18003558 | I32: =F2*B25*(1+B27) -> 945.93017
A33: H2 | B33: KMS | C33: COSTE ACARREO +YARD | D33: COSTE DUO H2 | E33: COSTE DUO+ ACARREO | F33: COSTE SIMPLE | G33: EXTRACOSTE | H33: DUO VS SIMPLE | I33: TARIFA NORMAL
A34: RUTA A | B34: =B25 -> 600 | C34: =(B23/B24+B22)*B26 -> 100 | D34: =F8*B34 -> 884.10887 | E34: =C34+D34 -> 984.10887 | F34: =F30 -> 844.58051 | G34: =E34/I34-1 -> 0.040361016 | H34: =E34/F34-1 -> 0.16520434 | I34: =B25*F2*(1+B27) -> 945.93017
A35: Falta aplicar el margen
A36: DIFERENCIA | B36: 100 | C36: 200 | D36: 300 | E36: 400 | F36: 500 | G36: 600 | H36: 700 | I36: 800 | J36: 900 | K36: 1000 | L36: 1100 | M36: 1200
A37: GASOIL | B37: =B61/B61-1 -> 0 | C37: =C61/C61-1 -> 0 | D37: =D61/D61-1 -> 0 | E37: =E61/E61-1 -> 0 | F37: =F61/F61-1 -> 0 | G37: =G61/G61-1 -> 0 | H37: =H61/H61-1 -> 0 | I37: =I61/I61-1 -> 0 | ... M37: =M61/M61-1 -> 0
A38: HVO | B38: =B62/B61-1 -> 0.028321381 | C38: =C62/C61-1 -> 0.052109875 | D38: =D62/D61-1 -> 0.072373093 | E38: =E62/E61-1 -> 0.089840604 | F38: =F62/F61-1 -> 0.10505366 | G38: =G62/G61-1 -> 0.11842225 | H38: =H62/H61-1 -> 0.13026265 | I38: =I62/I61-1 -> 0.11276134 | ... M38: =M62/M61-1 -> 0.14417529
A39: H2 | B39: =B63/B61-1 -> 0.6753257 | C39: =C63/C61-1 -> 0.71433551 | D39: =D63/D61-1 -> 0.74756437 | E39: =E63/E61-1 -> 0.77620865 | F39: =F63/F61-1 -> 0.80115594 | G39: =G63/G61-1 -> 0.82307856 | H39: =H63/H61-1 -> 0.84249517 | I39: =I63/I61-1 -> 0.68847961 | ... M39: =M63/M61-1 -> 0.75849174
A40: ELÉCTRICO | B40: =B64/B61-1 -> 0.32537799 | C40: =C64/C61-1 -> 0.33679995 | D40: =D64/D61-1 -> 0.34652926 | E40: =E64/E61-1 -> 0.35491622 | F40: =F64/F61-1 -> 0.36222071 | G40: =G64/G61-1 -> 0.3686396 | H40: =H64/H61-1 -> 0.37432472 | I40: =I64/I61-1 -> 0.303794 | ... M40: =M64/M61-1 -> 0.32804781
A41: GAS NATURAL | B41: =B65/B61-1 -> 0.12378913 | C41: =C65/C61-1 -> 0.1587611 | D41: =D65/D61-1 -> 0.18855048 | E41: =E65/E61-1 -> 0.21422984 | F41: =F65/F61-1 -> 0.23659486 | G41: =G65/G61-1 -> 0.25624831 | H41: =H65/H61-1 -> 0.27365514 | I41: =I65/I61-1 -> 0.23155561 | ... M41: =M65/M61-1 -> 0.28015434
A42: BIOMETANO | B42: =B66/B61-1 -> 0.13141856 | C42: =C66/C61-1 -> 0.17279886 | D42: =D66/D61-1 -> 0.20804691 | E42: =E66/E61-1 -> 0.2384318 | F42: =F66/F61-1 -> 0.26489503 | G42: =G66/G61-1 -> 0.28814982 | H42: =H66/H61-1 -> 0.3087463 | I42: =I66/I61-1 -> 0.26193214 | ... M42: =M66/M61-1 -> 0.31899339
A44: COSTES FIJOS | B44: 100 | C44: 200 | D44: 300 | E44: 400 | F44: 500 | G44: 600 | H44: 700 | I44: 800 | J44: 900 | K44: 1000 | L44: 1100 | M44: 1200
A45: GASOIL | B45: ='GASOIL '!$E$6/B44/$B$15 -> 1.6081818 | C45: ='GASOIL '!$E$6/C44/$B$15 -> 0.80409091 | D45: ='GASOIL '!$E$6/D44/$B$15 -> 0.53606061 | E45: ='GASOIL '!$E$6/E44/$B$15 -> 0.40204545 | F45: ='GASOIL '!$E$6/F44/$B$15 -> 0.32163636 | G45: ='GASOIL '!$E$6/G44/$B$15 -> 0.2680303 | H45: ='GASOIL '!$E$6/H44/$B$15 -> 0.22974026 | I45: ='GASOIL '!$E$6/I44/$B$15 -> 0.20102273 | ... M45: ='GASOIL '!$E$6/M44/$B$15 -> 0.13401515
A46: HVO | B46: =HVO!$E$6/B$44/$B$15 -> 1.6081818 | C46: =HVO!$E$6/C$44/$B$15 -> 0.80409091 | D46: =HVO!$E$6/D$44/$B$15 -> 0.53606061 | E46: =HVO!$E$6/E$44/$B$15 -> 0.40204545 | F46: =HVO!$E$6/F$44/$B$15 -> 0.32163636 | G46: =HVO!$E$6/G$44/$B$15 -> 0.2680303 | H46: =HVO!$E$6/H$44/$B$15 -> 0.22974026 | I46: =HVO!$E$6/I$44/$B$15 -> 0.20102273 | ... M46: =HVO!$E$6/M$44/$B$15 -> 0.13401515
A47: H2 | B47: ='H2'!$E$6/B$44/$B$15 -> 3.595 | C47: ='H2'!$E$6/C$44/$B$15 -> 1.7975 | D47: ='H2'!$E$6/D$44/$B$15 -> 1.1983333 | E47: ='H2'!$E$6/E$44/$B$15 -> 0.89875 | F47: ='H2'!$E$6/F$44/$B$15 -> 0.719 | G47: ='H2'!$E$6/G$44/$B$15 -> 0.59916667 | H47: ='H2'!$E$6/H$44/$B$15 -> 0.51357143 | I47: ='H2'!$E$6/I$44/$B$15 -> 0.449375 | ... M47: ='H2'!$E$6/M$44/$B$15 -> 0.29958333
A48: ELÉCTRICO | B48: =ELÉCTRICO!$E$6/B$44/$B$15 -> 2.5931818 | C48: =ELÉCTRICO!$E$6/C$44/$B$15 -> 1.2965909 | D48: =ELÉCTRICO!$E$6/D$44/$B$15 -> 0.86439394 | E48: =ELÉCTRICO!$E$6/E$44/$B$15 -> 0.64829545 | F48: =ELÉCTRICO!$E$6/F$44/$B$15 -> 0.51863636 | G48: =ELÉCTRICO!$E$6/G$44/$B$15 -> 0.43219697 | H48: =ELÉCTRICO!$E$6/H$44/$B$15 -> 0.37045455 | I48: =ELÉCTRICO!$E$6/I$44/$B$15 -> 0.32414773 | ... M48: =ELÉCTRICO!$E$6/M$44/$B$15 -> 0.21609848
A49: GAS NATURAL | B49: ='GAS NATURAL'!$E$6/B$44/$B$15 -> 1.8677273 | C49: ='GAS NATURAL'!$E$6/C$44/$B$15 -> 0.93386364 | D49: ='GAS NATURAL'!$E$6/D$44/$B$15 -> 0.62257576 | E49: ='GAS NATURAL'!$E$6/E$44/$B$15 -> 0.46693182 | F49: ='GAS NATURAL'!$E$6/F$44/$B$15 -> 0.37354545 | G49: ='GAS NATURAL'!$E$6/G$44/$B$15 -> 0.31128788 | H49: ='GAS NATURAL'!$E$6/H$44/$B$15 -> 0.26681818 | I49: ='GAS NATURAL'!$E$6/I$44/$B$15 -> 0.23346591 | ... M49: ='GAS NATURAL'!$E$6/M$44/$B$15 -> 0.15564394
A50: BIOMETANO | B50: =BIOMETANO!$E$6/B$44/$B$15 -> 1.8677273 | C50: =BIOMETANO!$E$6/C$44/$B$15 -> 0.93386364 | D50: =BIOMETANO!$E$6/D$44/$B$15 -> 0.62257576 | E50: =BIOMETANO!$E$6/E$44/$B$15 -> 0.46693182 | F50: =BIOMETANO!$E$6/F$44/$B$15 -> 0.37354545 | G50: =BIOMETANO!$E$6/G$44/$B$15 -> 0.31128788 | H50: =BIOMETANO!$E$6/H$44/$B$15 -> 0.26681818 | I50: =BIOMETANO!$E$6/I$44/$B$15 -> 0.23346591 | ... M50: =BIOMETANO!$E$6/M$44/$B$15 -> 0.15564394
A52: COSTES VARIABLES | B52: 100 | C52: 200 | D52: 300 | E52: 400 | F52: 500 | G52: 600 | H52: 700 | I52: 800 | J52: 900 | K52: 1000 | L52: 1100 | M52: 1200
A53: GASOIL | B53: =($B$17/$B$15+0.0105*2*'CALCULADORA COSTES'!B$52+'GASOIL '!$E$37/$B$15+'GASOIL '!$D$33*'CALCULADORA COSTES'!B$52)/'CALCULADORA COSTES'!B$52 -> 1.7319091 | C53: =($B$17/$B$15+0.0105*2*'CALCULADORA COSTES'!C$52+'GASOIL '!$E$37/$B$15+'GASOIL '!$D$33*'CALCULADORA COSTES'!C$52)/'CALCULADORA COSTES'!C$52 -> 1.0164545 | D53: =($B$17/$B$15+0.0105*2*'CALCULADORA COSTES'!D$52+'GASOIL '!$E$37/$B$15+'GASOIL '!$D$33*'CALCULADORA COSTES'!D$52)/'CALCULADORA COSTES'!D$52 -> 0.7779697 | E53: =($B$17/$B$15+0.0105*2*'CALCULADORA COSTES'!E$52+'GASOIL '!$E$37/$B$15+'GASOIL '!$D$33*'CALCULADORA COSTES'!E$52)/'CALCULADORA COSTES'!E$52 -> 0.65872727 | F53: =($B$17/$B$15+0.0105*2*'CALCULADORA COSTES'!F$52+'GASOIL '!$E$37/$B$15+'GASOIL '!$D$33*'CALCULADORA COSTES'!F$52)/'CALCULADORA COSTES'!F$52 -> 0.58718182 | G53: =($B$17/$B$15+0.0105*2*'CALCULADORA COSTES'!G$52+'GASOIL '!$E$37/$B$15+'GASOIL '!$D$33*'CALCULADORA COSTES'!G$52)/'CALCULADORA COSTES'!G$52 -> 0.53948485 | H53: =($B$17/$B$15+0.0105*2*'CALCULADORA COSTES'!H$52+'GASOIL '!$E$37/$B$15+'GASOIL '!$D$33*'CALCULADORA COSTES'!H$52)/'CALCULADORA COSTES'!H$52 -> 0.50541558 | I53: =($B$17*2/$B$15+0.0105*2*'CALCULADORA COSTES'!I$52+'GASOIL '!$E$37/$B$15+'GASOIL '!$D$33*'CALCULADORA COSTES'!I$52)/'CALCULADORA COSTES'!I$52 -> 0.65304545 | J53: =($B$17*2/$B$15+0.0105*2*'CALCULADORA COSTES'!J$52+'GASOIL '!$E$37/$B$15+'GASOIL '!$D$33*'CALCULADORA COSTES'!J$52)/'CALCULADORA COSTES'!J$52 -> 0.61392929 | K53: =($B$17*2/$B$15+0.0105*2*'CALCULADORA COSTES'!K$52+'GASOIL '!$E$37/$B$15+'GASOIL '!$D$33*'CALCULADORA COSTES'!K$52)/'CALCULADORA COSTES'!K$52 -> 0.58263636 | L53: =($B$17*2/$B$15+0.0105*2*'CALCULADORA COSTES'!L$52+'GASOIL '!$E$37/$B$15+'GASOIL '!$D$33*'CALCULADORA COSTES'!L$52)/'CALCULADORA COSTES'!L$52 -> 0.55703306 | M53: =($B$17*2/$B$15+0.0105*2*'CALCULADORA COSTES'!M$52+'GASOIL '!$E$37/$B$15+'GASOIL '!$D$33*'CALCULADORA COSTES'!M$52)/'CALCULADORA COSTES'!M$52 -> 0.53569697
A54: HVO | B54: =($B$17/$B$15+0.0105*2*'CALCULADORA COSTES'!B$52+HVO!$E$37/$B$15+HVO!$D$33*'CALCULADORA COSTES'!B$52)/'CALCULADORA COSTES'!B$52 -> 1.8299091 | C54: =($B$17/$B$15+0.0105*2*'CALCULADORA COSTES'!C$52+HVO!$E$37/$B$15+HVO!$D$33*'CALCULADORA COSTES'!C$52)/'CALCULADORA COSTES'!C$52 -> 1.1144545 | D54: =($B$17/$B$15+0.0105*2*'CALCULADORA COSTES'!D$52+HVO!$E$37/$B$15+HVO!$D$33*'CALCULADORA COSTES'!D$52)/'CALCULADORA COSTES'!D$52 -> 0.8759697 | E54: =($B$17/$B$15+0.0105*2*'CALCULADORA COSTES'!E$52+HVO!$E$37/$B$15+HVO!$D$33*'CALCULADORA COSTES'!E$52)/'CALCULADORA COSTES'!E$52 -> 0.75672727 | F54: =($B$17/$B$15+0.0105*2*'CALCULADORA COSTES'!F$52+HVO!$E$37/$B$15+HVO!$D$33*'CALCULADORA COSTES'!F$52)/'CALCULADORA COSTES'!F$52 -> 0.68518182 | G54: =($B$17/$B$15+0.0105*2*'CALCULADORA COSTES'!G$52+HVO!$E$37/$B$15+HVO!$D$33*'CALCULADORA COSTES'!G$52)/'CALCULADORA COSTES'!G$52 -> 0.63748485 | H54: =($B$17/$B$15+0.0105*2*'CALCULADORA COSTES'!H$52+HVO!$E$37/$B$15+HVO!$D$33*'CALCULADORA COSTES'!H$52)/'CALCULADORA COSTES'!H$52 -> 0.60341558 | I54: =($B$17*2/$B$15+0.0105*2*'CALCULADORA COSTES'!I$52+HVO!$E$37/$B$15+HVO!$D$33*'CALCULADORA COSTES'!I$52)/'CALCULADORA COSTES'!I$52 -> 0.75104545 | J54: =($B$17*2/$B$15+0.0105*2*'CALCULADORA COSTES'!J$52+HVO!$E$37/$B$15+HVO!$D$33*'CALCULADORA COSTES'!J$52)/'CALCULADORA COSTES'!J$52 -> 0.71192929 | K54: =($B$17*2/$B$15+0.0105*2*'CALCULADORA COSTES'!K$52+HVO!$E$37/$B$15+HVO!$D$33*'CALCULADORA COSTES'!K$52)/'CALCULADORA COSTES'!K$52 -> 0.68063636 | L54: =($B$17*2/$B$15+0.0105*2*'CALCULADORA COSTES'!L$52+HVO!$E$37/$B$15+HVO!$D$33*'CALCULADORA COSTES'!L$52)/'CALCULADORA COSTES'!L$52 -> 0.65503306 | M54: =($B$17*2/$B$15+0.0105*2*'CALCULADORA COSTES'!M$52+HVO!$E$37/$B$15+HVO!$D$33*'CALCULADORA COSTES'!M$52)/'CALCULADORA COSTES'!M$52 -> 0.63369697
A55: H2 | B55: =($B$17/$B$15+0.0105*2*'CALCULADORA COSTES'!B$52+'H2'!$E$36/$B$15+'H2'!$D$32*'CALCULADORA COSTES'!B$52)/'CALCULADORA COSTES'!B$52 -> 2.0819091 | C55: =($B$17/$B$15+0.0105*2*'CALCULADORA COSTES'!C$52+'H2'!$E$36/$B$15+'H2'!$D$32*'CALCULADORA COSTES'!C$52)/'CALCULADORA COSTES'!C$52 -> 1.3664545 | D55: =($B$17/$B$15+0.0105*2*'CALCULADORA COSTES'!D$52+'H2'!$E$36/$B$15+'H2'!$D$32*'CALCULADORA COSTES'!D$52)/'CALCULADORA COSTES'!D$52 -> 1.1279697 | E55: =($B$17/$B$15+0.0105*2*'CALCULADORA COSTES'!E$52+'H2'!$E$36/$B$15+'H2'!$D$32*'CALCULADORA COSTES'!E$52)/'CALCULADORA COSTES'!E$52 -> 1.0087273 | F55: =($B$17/$B$15+0.0105*2*'CALCULADORA COSTES'!F$52+'H2'!$E$36/$B$15+'H2'!$D$32*'CALCULADORA COSTES'!F$52)/'CALCULADORA COSTES'!F$52 -> 0.93718182 | G55: =($B$17/$B$15+0.0105*2*'CALCULADORA COSTES'!G$52+'H2'!$E$36/$B$15+'H2'!$D$32*'CALCULADORA COSTES'!G$52)/'CALCULADORA COSTES'!G$52 -> 0.88948485 | H55: =($B$17/$B$15+0.0105*2*'CALCULADORA COSTES'!H$52+'H2'!$E$36/$B$15+'H2'!$D$32*'CALCULADORA COSTES'!H$52)/'CALCULADORA COSTES'!H$52 -> 0.85541558 | I55: =($B$17*2/$B$15+0.0105*2*'CALCULADORA COSTES'!I$52+'H2'!$E$36/$B$15+'H2'!$D$32*'CALCULADORA COSTES'!I$52)/'CALCULADORA COSTES'!I$52 -> 1.0030455 | J55: =($B$17*2/$B$15+0.0105*2*'CALCULADORA COSTES'!J$52+'H2'!$E$36/$B$15+'H2'!$D$32*'CALCULADORA COSTES'!J$52)/'CALCULADORA COSTES'!J$52 -> 0.96392929 | K55: =($B$17*2/$B$15+0.0105*2*'CALCULADORA COSTES'!K$52+'H2'!$E$36/$B$15+'H2'!$D$32*'CALCULADORA COSTES'!K$52)/'CALCULADORA COSTES'!K$52 -> 0.93263636 | L55: =($B$17*2/$B$15+0.0105*2*'CALCULADORA COSTES'!L$52+'H2'!$E$36/$B$15+'H2'!$D$32*'CALCULADORA COSTES'!L$52)/'CALCULADORA COSTES'!L$52 -> 0.90703306 | M55: =($B$17*2/$B$15+0.0105*2*'CALCULADORA COSTES'!M$52+'H2'!$E$36/$B$15+'H2'!$D$32*'CALCULADORA COSTES'!M$52)/'CALCULADORA COSTES'!M$52 -> 0.88569697
A56: ELÉCTRICO | B56: =($B$17/$B$15+0.0105*2*'CALCULADORA COSTES'!B$52+ELÉCTRICO!$E$36/$B$15+ELÉCTRICO!$D$32*'CALCULADORA COSTES'!B$52)/'CALCULADORA COSTES'!B$52 -> 1.8728091 | C56: =($B$17/$B$15+0.0105*2*'CALCULADORA COSTES'!C$52+ELÉCTRICO!$E$36/$B$15+ELÉCTRICO!$D$32*'CALCULADORA COSTES'!C$52)/'CALCULADORA COSTES'!C$52 -> 1.1573545 | D56: =($B$17/$B$15+0.0105*2*'CALCULADORA COSTES'!D$52+ELÉCTRICO!$E$36/$B$15+ELÉCTRICO!$D$32*'CALCULADORA COSTES'!D$52)/'CALCULADORA COSTES'!D$52 -> 0.9188697 | E56: =($B$17/$B$15+0.0105*2*'CALCULADORA COSTES'!E$52+ELÉCTRICO!$E$36/$B$15+ELÉCTRICO!$D$32*'CALCULADORA COSTES'!E$52)/'CALCULADORA COSTES'!E$52 -> 0.79962727 | F56: =($B$17/$B$15+0.0105*2*'CALCULADORA COSTES'!F$52+ELÉCTRICO!$E$36/$B$15+ELÉCTRICO!$D$32*'CALCULADORA COSTES'!F$52)/'CALCULADORA COSTES'!F$52 -> 0.72808182 | G56: =($B$17/$B$15+0.0105*2*'CALCULADORA COSTES'!G$52+ELÉCTRICO!$E$36/$B$15+ELÉCTRICO!$D$32*'CALCULADORA COSTES'!G$52)/'CALCULADORA COSTES'!G$52 -> 0.68038485 | H56: =($B$17/$B$15+0.0105*2*'CALCULADORA COSTES'!H$52+ELÉCTRICO!$E$36/$B$15+ELÉCTRICO!$D$32*'CALCULADORA COSTES'!H$52)/'CALCULADORA COSTES'!H$52 -> 0.64631558 | I56: =($B$17*2/$B$15+0.0105*2*'CALCULADORA COSTES'!I$52+ELÉCTRICO!$E$36/$B$15+ELÉCTRICO!$D$32*'CALCULADORA COSTES'!I$52)/'CALCULADORA COSTES'!I$52 -> 0.79394545 | J56: =($B$17*2/$B$15+0.0105*2*'CALCULADORA COSTES'!J$52+ELÉCTRICO!$E$36/$B$15+ELÉCTRICO!$D$32*'CALCULADORA COSTES'!J$52)/'CALCULADORA COSTES'!J$52 -> 0.75482929 | K56: =($B$17*2/$B$15+0.0105*2*'CALCULADORA COSTES'!K$52+ELÉCTRICO!$E$36/$B$15+ELÉCTRICO!$D$32*'CALCULADORA COSTES'!K$52)/'CALCULADORA COSTES'!K$52 -> 0.72353636 | L56: =($B$17*2/$B$15+0.0105*2*'CALCULADORA COSTES'!L$52+ELÉCTRICO!$E$36/$B$15+ELÉCTRICO!$D$32*'CALCULADORA COSTES'!L$52)/'CALCULADORA COSTES'!L$52 -> 0.69793306 | M56: =($B$17*2/$B$15+0.0105*2*'CALCULADORA COSTES'!M$52+ELÉCTRICO!$E$36/$B$15+ELÉCTRICO!$D$32*'CALCULADORA COSTES'!M$52)/'CALCULADORA COSTES'!M$52 -> 0.67659697
A57: GAS NATURAL | B57: =($B$17/$B$15+0.0105*2*'CALCULADORA COSTES'!B$52+'GAS NATURAL'!$E$36/$B$15+'GAS NATURAL'!$D$32*'CALCULADORA COSTES'!B$52)/'CALCULADORA COSTES'!B$52 -> 1.9007091 | C57: =($B$17/$B$15+0.0105*2*'CALCULADORA COSTES'!C$52+'GAS NATURAL'!$E$36/$B$15+'GAS NATURAL'!$D$32*'CALCULADORA COSTES'!C$52)/'CALCULADORA COSTES'!C$52 -> 1.1852545 | D57: =($B$17/$B$15+0.0105*2*'CALCULADORA COSTES'!D$52+'GAS NATURAL'!$E$36/$B$15+'GAS NATURAL'!$D$32*'CALCULADORA COSTES'!D$52)/'CALCULADORA COSTES'!D$52 -> 0.9467697 | E57: =($B$17/$B$15+0.0105*2*'CALCULADORA COSTES'!E$52+'GAS NATURAL'!$E$36/$B$15+'GAS NATURAL'!$D$32*'CALCULADORA COSTES'!E$52)/'CALCULADORA COSTES'!E$52 -> 0.82752727 | F57: =($B$17/$B$15+0.0105*2*'CALCULADORA COSTES'!F$52+'GAS NATURAL'!$E$36/$B$15+'GAS NATURAL'!$D$32*'CALCULADORA COSTES'!F$52)/'CALCULADORA COSTES'!F$52 -> 0.75598182 | G57: =($B$17/$B$15+0.0105*2*'CALCULADORA COSTES'!G$52+'GAS NATURAL'!$E$36/$B$15+'GAS NATURAL'!$D$32*'CALCULADORA COSTES'!G$52)/'CALCULADORA COSTES'!G$52 -> 0.70828485 | H57: =($B$17/$B$15+0.0105*2*'CALCULADORA COSTES'!H$52+'GAS NATURAL'!$E$36/$B$15+'GAS NATURAL'!$D$32*'CALCULADORA COSTES'!H$52)/'CALCULADORA COSTES'!H$52 -> 0.67421558 | I57: =($B$17*2/$B$15+0.0105*2*'CALCULADORA COSTES'!I$52+'GAS NATURAL'!$E$36/$B$15+'GAS NATURAL'!$D$32*'CALCULADORA COSTES'!I$52)/'CALCULADORA COSTES'!I$52 -> 0.82184545 | J57: =($B$17*2/$B$15+0.0105*2*'CALCULADORA COSTES'!J$52+'GAS NATURAL'!$E$36/$B$15+'GAS NATURAL'!$D$32*'CALCULADORA COSTES'!J$52)/'CALCULADORA COSTES'!J$52 -> 0.78272929 | K57: =($B$17*2/$B$15+0.0105*2*'CALCULADORA COSTES'!K$52+'GAS NATURAL'!$E$36/$B$15+'GAS NATURAL'!$D$32*'CALCULADORA COSTES'!K$52)/'CALCULADORA COSTES'!K$52 -> 0.75143636 | L57: =($B$17*2/$B$15+0.0105*2*'CALCULADORA COSTES'!L$52+'GAS NATURAL'!$E$36/$B$15+'GAS NATURAL'!$D$32*'CALCULADORA COSTES'!L$52)/'CALCULADORA COSTES'!L$52 -> 0.72583306 | M57: =($B$17*2/$B$15+0.0105*2*'CALCULADORA COSTES'!M$52+'GAS NATURAL'!$E$36/$B$15+'GAS NATURAL'!$D$32*'CALCULADORA COSTES'!M$52)/'CALCULADORA COSTES'!M$52 -> 0.70449697
A58: BIOMETANO | B58: =($B$17/$B$15+0.0105*2*'CALCULADORA COSTES'!B$52+BIOMETANO!$E$36/$B$15+BIOMETANO!$D$32*'CALCULADORA COSTES'!B$52)/'CALCULADORA COSTES'!B$52 -> 1.9271091 | C58: =($B$17/$B$15+0.0105*2*'CALCULADORA COSTES'!C$52+BIOMETANO!$E$36/$B$15+BIOMETANO!$D$32*'CALCULADORA COSTES'!C$52)/'CALCULADORA COSTES'!C$52 -> 1.2116545 | D58: =($B$17/$B$15+0.0105*2*'CALCULADORA COSTES'!D$52+BIOMETANO!$E$36/$B$15+BIOMETANO!$D$32*'CALCULADORA COSTES'!D$52)/'CALCULADORA COSTES'!D$52 -> 0.9731697 | E58: =($B$17/$B$15+0.0105*2*'CALCULADORA COSTES'!E$52+BIOMETANO!$E$36/$B$15+BIOMETANO!$D$32*'CALCULADORA COSTES'!E$52)/'CALCULADORA COSTES'!E$52 -> 0.85392727 | F58: =($B$17/$B$15+0.0105*2*'CALCULADORA COSTES'!F$52+BIOMETANO!$E$36/$B$15+BIOMETANO!$D$32*'CALCULADORA COSTES'!F$52)/'CALCULADORA COSTES'!F$52 -> 0.78238182 | G58: =($B$17/$B$15+0.0105*2*'CALCULADORA COSTES'!G$52+BIOMETANO!$E$36/$B$15+BIOMETANO!$D$32*'CALCULADORA COSTES'!G$52)/'CALCULADORA COSTES'!G$52 -> 0.73468485 | H58: =($B$17/$B$15+0.0105*2*'CALCULADORA COSTES'!H$52+BIOMETANO!$E$36/$B$15+BIOMETANO!$D$32*'CALCULADORA COSTES'!H$52)/'CALCULADORA COSTES'!H$52 -> 0.70061558 | I58: =($B$17*2/$B$15+0.0105*2*'CALCULADORA COSTES'!I$52+BIOMETANO!$E$36/$B$15+BIOMETANO!$D$32*'CALCULADORA COSTES'!I$52)/'CALCULADORA COSTES'!I$52 -> 0.84824545 | J58: =($B$17*2/$B$15+0.0105*2*'CALCULADORA COSTES'!J$52+BIOMETANO!$E$36/$B$15+BIOMETANO!$D$32*'CALCULADORA COSTES'!J$52)/'CALCULADORA COSTES'!J$52 -> 0.80912929 | K58: =($B$17*2/$B$15+0.0105*2*'CALCULADORA COSTES'!K$52+BIOMETANO!$E$36/$B$15+BIOMETANO!$D$32*'CALCULADORA COSTES'!K$52)/'CALCULADORA COSTES'!K$52 -> 0.77783636 | L58: =($B$17*2/$B$15+0.0105*2*'CALCULADORA COSTES'!L$52+BIOMETANO!$E$36/$B$15+BIOMETANO!$D$32*'CALCULADORA COSTES'!L$52)/'CALCULADORA COSTES'!L$52 -> 0.75223306 | M58: =($B$17*2/$B$15+0.0105*2*'CALCULADORA COSTES'!M$52+BIOMETANO!$E$36/$B$15+BIOMETANO!$D$32*'CALCULADORA COSTES'!M$52)/'CALCULADORA COSTES'!M$52 -> 0.73089697
A60: TOTAL | B60: 100 | C60: 200 | D60: 300 | E60: 400 | F60: 500 | G60: 600 | H60: 700 | I60: 800 | J60: 900 | K60: 1000 | L60: 1100 | M60: 1200
A61: GASOIL | B61: =(B45+B53)+(B45+B53)*0.04+275/Tabla25[[#Headers],[100]]/'CALCULADORA COSTES'!$B$15 -> 3.5986945 | C61: =(C45+C53)+(C45+C53)*0.04+275/Tabla25[[#Headers],[200]]/'CALCULADORA COSTES'!$B$15 -> 1.9558673 | D61: =(D45+D53)+(D45+D53)*0.04+275/Tabla25[[#Headers],[300]]/'CALCULADORA COSTES'!$B$15 -> 1.4082582 | E61: =(E45+E53)+(E45+E53)*0.04+275/Tabla25[[#Headers],[400]]/'CALCULADORA COSTES'!$B$15 -> 1.1344536 | F61: =(F45+F53)+(F45+F53)*0.04+275/Tabla25[[#Headers],[500]]/'CALCULADORA COSTES'!$B$15 -> 0.97017091 | G61: =(G45+G53)+(G45+G53)*0.04+275/Tabla25[[#Headers],[600]]/'CALCULADORA COSTES'!$B$15 -> 0.86064909 | H61: =(H45+H53)+(H45+H53)*0.04+275/Tabla25[[#Headers],[700]]/'CALCULADORA COSTES'!$B$15 -> 0.78241922 | I61: =(I45+I53)+(I45+I53)*0.04+275/Tabla25[[#Headers],[800]]/'CALCULADORA COSTES'!$B$15 -> 0.90385591 | J61: =(J45+J53)+(J45+J53)*0.04+275/Tabla25[[#Headers],[900]]/'CALCULADORA COSTES'!$B$15 -> 0.8382097 | K61: =(K45+K53)+(K45+K53)*0.04+275/Tabla25[[#Headers],[1000]]/'CALCULADORA COSTES'!$B$15 -> 0.78569273 | L61: =(L45+L53)+(L45+L53)*0.04+275/Tabla25[[#Headers],[1100]]/'CALCULADORA COSTES'!$B$15 -> 0.7427243 | M61: =(M45+M53)+(M45+M53)*0.04+275/Tabla25[[#Headers],[1200]]/'CALCULADORA COSTES'!$B$15 -> 0.70691727
A62: HVO | B62: =(B46+B54)+(B46+B54)*0.04+275/Tabla25[[#Headers],[100]]/'CALCULADORA COSTES'!$B$15 -> 3.7006145 | C62: =(C46+C54)+(C46+C54)*0.04+275/Tabla25[[#Headers],[200]]/'CALCULADORA COSTES'!$B$15 -> 2.0577873 | D62: =(D46+D54)+(D46+D54)*0.04+275/Tabla25[[#Headers],[300]]/'CALCULADORA COSTES'!$B$15 -> 1.5101782 | E62: =(E46+E54)+(E46+E54)*0.04+275/Tabla25[[#Headers],[400]]/'CALCULADORA COSTES'!$B$15 -> 1.2363736 | F62: =(F46+F54)+(F46+F54)*0.04+275/Tabla25[[#Headers],[500]]/'CALCULADORA COSTES'!$B$15 -> 1.0720909 | G62: =(G46+G54)+(G46+G54)*0.04+275/Tabla25[[#Headers],[600]]/'CALCULADORA COSTES'!$B$15 -> 0.96256909 | H62: =(H46+H54)+(H46+H54)*0.04+275/Tabla25[[#Headers],[700]]/'CALCULADORA COSTES'!$B$15 -> 0.88433922 | I62: =(I46+I54)+(I46+I54)*0.04+275/Tabla25[[#Headers],[800]]/'CALCULADORA COSTES'!$B$15 -> 1.0057759 | J62: =(J46+J54)+(J46+J54)*0.04+275/Tabla25[[#Headers],[900]]/'CALCULADORA COSTES'!$B$15 -> 0.9401297 | K62: =(K46+K54)+(K46+K54)*0.04+275/Tabla25[[#Headers],[1000]]/'CALCULADORA COSTES'!$B$15 -> 0.88761273 | L62: =(L46+L54)+(L46+L54)*0.04+275/Tabla25[[#Headers],[1100]]/'CALCULADORA COSTES'!$B$15 -> 0.8446443 | M62: =(M46+M54)+(M46+M54)*0.04+275/Tabla25[[#Headers],[1200]]/'CALCULADORA COSTES'!$B$15 -> 0.80883727
A63: H2 | B63: =(B47+B55)+(B47+B55)*0.04+275/Tabla25[[#Headers],[100]]/'CALCULADORA COSTES'!$B$15 -> 6.0289855 | C63: =(C47+C55)+(C47+C55)*0.04+275/Tabla25[[#Headers],[200]]/'CALCULADORA COSTES'!$B$15 -> 3.3530127 | D63: =(D47+D55)+(D47+D55)*0.04+275/Tabla25[[#Headers],[300]]/'CALCULADORA COSTES'!$B$15 -> 2.4610218 | E63: =(E47+E55)+(E47+E55)*0.04+275/Tabla25[[#Headers],[400]]/'CALCULADORA COSTES'!$B$15 -> 2.0150264 | F63: =(F47+F55)+(F47+F55)*0.04+275/Tabla25[[#Headers],[500]]/'CALCULADORA COSTES'!$B$15 -> 1.7474291 | G63: =(G47+G55)+(G47+G55)*0.04+275/Tabla25[[#Headers],[600]]/'CALCULADORA COSTES'!$B$15 -> 1.5690309 | H63: =(H47+H55)+(H47+H55)*0.04+275/Tabla25[[#Headers],[700]]/'CALCULADORA COSTES'!$B$15 -> 1.4416036 | I63: =(I47+I55)+(I47+I55)*0.04+275/Tabla25[[#Headers],[800]]/'CALCULADORA COSTES'!$B$15 -> 1.5261423 | J63: =(J47+J55)+(J47+J55)*0.04+275/Tabla25[[#Headers],[900]]/'CALCULADORA COSTES'!$B$15 -> 1.4317976 | K63: =(K47+K55)+(K47+K55)*0.04+275/Tabla25[[#Headers],[1000]]/'CALCULADORA COSTES'!$B$15 -> 1.3563218 | L63: =(L47+L55)+(L47+L55)*0.04+275/Tabla25[[#Headers],[1100]]/'CALCULADORA COSTES'!$B$15 -> 1.2945689 | M63: =(M47+M55)+(M47+M55)*0.04+275/Tabla25[[#Headers],[1200]]/'CALCULADORA COSTES'!$B$15 -> 1.2431082
A64: ELÉCTRICO | B64: =(B48+B56)+(B48+B56)*0.04+275/Tabla25[[#Headers],[100]]/'CALCULADORA COSTES'!$B$15 -> 4.7696305 | C64: =(C48+C56)+(C48+C56)*0.04+275/Tabla25[[#Headers],[200]]/'CALCULADORA COSTES'!$B$15 -> 2.6146033 | D64: =(D48+D56)+(D48+D56)*0.04+275/Tabla25[[#Headers],[300]]/'CALCULADORA COSTES'!$B$15 -> 1.8962608 | E64: =(E48+E56)+(E48+E56)*0.04+275/Tabla25[[#Headers],[400]]/'CALCULADORA COSTES'!$B$15 -> 1.5370896 | F64: =(F48+F56)+(F48+F56)*0.04+275/Tabla25[[#Headers],[500]]/'CALCULADORA COSTES'!$B$15 -> 1.3215869 | G64: =(G48+G56)+(G48+G56)*0.04+275/Tabla25[[#Headers],[600]]/'CALCULADORA COSTES'!$B$15 -> 1.1779184 | H64: =(H48+H56)+(H48+H56)*0.04+275/Tabla25[[#Headers],[700]]/'CALCULADORA COSTES'!$B$15 -> 1.0752981 | I64: =(I48+I56)+(I48+I56)*0.04+275/Tabla25[[#Headers],[800]]/'CALCULADORA COSTES'!$B$15 -> 1.1784419 | J64: =(J48+J56)+(J48+J56)*0.04+275/Tabla25[[#Headers],[900]]/'CALCULADORA COSTES'!$B$15 -> 1.0985679 | K64: =(K48+K56)+(K48+K56)*0.04+275/Tabla25[[#Headers],[1000]]/'CALCULADORA COSTES'!$B$15 -> 1.0346687 | L64: =(L48+L56)+(L48+L56)*0.04+275/Tabla25[[#Headers],[1100]]/'CALCULADORA COSTES'!$B$15 -> 0.98238757 | M64: =(M48+M56)+(M48+M56)*0.04+275/Tabla25[[#Headers],[1200]]/'CALCULADORA COSTES'!$B$15 -> 0.93881994
A65: GAS NATURAL | B65: =(B49+B57)+(B49+B57)*0.04+275/Tabla25[[#Headers],[100]]/'CALCULADORA COSTES'!$B$15 -> 4.0441738 | C65: =(C49+C57)+(C49+C57)*0.04+275/Tabla25[[#Headers],[200]]/'CALCULADORA COSTES'!$B$15 -> 2.2663829 | D65: =(D49+D57)+(D49+D57)*0.04+275/Tabla25[[#Headers],[300]]/'CALCULADORA COSTES'!$B$15 -> 1.6737859 | E65: =(E49+E57)+(E49+E57)*0.04+275/Tabla25[[#Headers],[400]]/'CALCULADORA COSTES'!$B$15 -> 1.3774875 | F65: =(F49+F57)+(F49+F57)*0.04+275/Tabla25[[#Headers],[500]]/'CALCULADORA COSTES'!$B$15 -> 1.1997084 | G65: =(G49+G57)+(G49+G57)*0.04+275/Tabla25[[#Headers],[600]]/'CALCULADORA COSTES'!$B$15 -> 1.081189 | H65: =(H49+H57)+(H49+H57)*0.04+275/Tabla25[[#Headers],[700]]/'CALCULADORA COSTES'!$B$15 -> 0.99653226 | I65: =(I49+I57)+(I49+I57)*0.04+275/Tabla25[[#Headers],[800]]/'CALCULADORA COSTES'!$B$15 -> 1.1131488 | J65: =(J49+J57)+(J49+J57)*0.04+275/Tabla25[[#Headers],[900]]/'CALCULADORA COSTES'!$B$15 -> 1.0437536 | K65: =(K49+K57)+(K49+K57)*0.04+275/Tabla25[[#Headers],[1000]]/'CALCULADORA COSTES'!$B$15 -> 0.98823745 | L65: =(L49+L57)+(L49+L57)*0.04+275/Tabla25[[#Headers],[1100]]/'CALCULADORA COSTES'!$B$15 -> 0.94281514 | M65: =(M49+M57)+(M49+M57)*0.04+275/Tabla25[[#Headers],[1200]]/'CALCULADORA COSTES'!$B$15 -> 0.90496321
A66: BIOMETANO | B66: =(B50+B58)+(B50+B58)*0.04+275/Tabla25[[#Headers],[100]]/'CALCULADORA COSTES'!$B$15 -> 4.0716298 | C66: =(C50+C58)+(C50+C58)*0.04+275/Tabla25[[#Headers],[200]]/'CALCULADORA COSTES'!$B$15 -> 2.2938389 | D66: =(D50+D58)+(D50+D58)*0.04+275/Tabla25[[#Headers],[300]]/'CALCULADORA COSTES'!$B$15 -> 1.7012419 | E66: =(E50+E58)+(E50+E58)*0.04+275/Tabla25[[#Headers],[400]]/'CALCULADORA COSTES'!$B$15 -> 1.4049435 | F66: =(F50+F58)+(F50+F58)*0.04+275/Tabla25[[#Headers],[500]]/'CALCULADORA COSTES'!$B$15 -> 1.2271644 | G66: =(G50+G58)+(G50+G58)*0.04+275/Tabla25[[#Headers],[600]]/'CALCULADORA COSTES'!$B$15 -> 1.108645 | H66: =(H50+H58)+(H50+H58)*0.04+275/Tabla25[[#Headers],[700]]/'CALCULADORA COSTES'!$B$15 -> 1.0239883 | I66: =(I50+I58)+(I50+I58)*0.04+275/Tabla25[[#Headers],[800]]/'CALCULADORA COSTES'!$B$15 -> 1.1406048 | J66: =(J50+J58)+(J50+J58)*0.04+275/Tabla25[[#Headers],[900]]/'CALCULADORA COSTES'!$B$15 -> 1.0712096 | K66: =(K50+K58)+(K50+K58)*0.04+275/Tabla25[[#Headers],[1000]]/'CALCULADORA COSTES'!$B$15 -> 1.0156935 | L66: =(L50+L58)+(L50+L58)*0.04+275/Tabla25[[#Headers],[1100]]/'CALCULADORA COSTES'!$B$15 -> 0.97027114 | M66: =(M50+M58)+(M50+M58)*0.04+275/Tabla25[[#Headers],[1200]]/'CALCULADORA COSTES'!$B$15 -> 0.93241921

Sheet TABLAS 
A1: SIMPLE H2 / 4 € | N1: SIMPLE GNL | AA1: EXTRA COSTE
A2: KMS / % VERDE | B2: 0 | C2: 10 | D2: 20 | E2: 30 | F2: 40 | G2: 50 | H2: 60 | I2: 70 | J2: 80 | K2: 90 | L2: 100 | N2: KMS / % BIO | O2: 0 | P2: 10 | Q2: 20 | R2: 30 | S2: 40 | T2: 50 | U2: 60 | V2: 70 | W2: 80 | X2: 90 | Y2: 100 | AA2: KMS / % HVO | AB2: 0 | AC2: 10 | AD2: 20 | AE2: 30 | AF2: 40 | AG2: 50 | AH2: 60 | AI2: 70 | AJ2: 80 | AK2: 90 | AL2: 100
A3: 100 | B3: 0.77 | C3: 0.78 | D3: 0.78 | E3: 0.79 | F3: 0.8 | G3: 0.8 | H3: 0.81 | I3: 0.82 | J3: 0.82 | K3: 0.83 | L3: 0.84 | N3: 100 | O3: 0.15 | P3: 0.15 | Q3: 0.15 | R3: 0.16 | S3: 0.16 | T3: 0.17 | U3: 0.17 | V3: 0.17 | W3: 0.18 | X3: 0.18 | Y3: 0.19 | AA3: 100 | AB3: 0 | AC3: 0.01 | AD3: 0.03 | AE3: 0.04 | AF3: 0.05 | AG3: 0.06 | AH3: 0.08 | AI3: 0.09 | AJ3: 0.1 | AK3: 0.11 | AL3: 0.13
A4: 200 | B4: 0.67 | C4: 0.68 | D4: 0.69 | E4: 0.7 | F4: 0.71 | G4: 0.73 | H4: 0.74 | I4: 0.75 | J4: 0.76 | K4: 0.78 | L4: 0.79 | N4: 200 | O4: 0.11 | P4: 0.11 | Q4: 0.12 | R4: 0.13 | S4: 0.13 | T4: 0.14 | U4: 0.15 | V4: 0.16 | W4: 0.16 | X4: 0.17 | Y4: 0.18 | AA4: 200 | AB4: 0 | AC4: 0.02 | AD4: 0.05 | AE4: 0.07 | AF4: 0.09 | AG4: 0.12 | AH4: 0.14 | AI4: 0.16 | AJ4: 0.18 | AK4: 0.21 | AL4: 0.23
A5: 300 | B5: 0.58 | C5: 0.59 | D5: 0.61 | E5: 0.63 | F5: 0.64 | G5: 0.66 | H5: 0.68 | I5: 0.7 | J5: 0.71 | K5: 0.73 | L5: 0.75 | N5: 300 | O5: 0.07 | P5: 0.08 | Q5: 0.09 | R5: 0.1 | S5: 0.11 | T5: 0.12 | U5: 0.13 | V5: 0.14 | W5: 0.15 | X5: 0.16 | Y5: 0.17 | AA5: 300 | AB5: 0 | AC5: 0.03 | AD5: 0.06 | AE5: 0.1 | AF5: 0.13 | AG5: 0.16 | AH5: 0.19 | AI5: 0.22 | AJ5: 0.26 | AK5: 0.29 | AL5: 0.32
A6: 400 | B6: 0.5 | C6: 0.52 | D6: 0.54 | E6: 0.56 | F6: 0.59 | G6: 0.61 | H6: 0.63 | I6: 0.65 | J6: 0.67 | K6: 0.69 | L6: 0.71 | N6: 400 | O6: 0.04 | P6: 0.05 | Q6: 0.07 | R6: 0.08 | S6: 0.09 | T6: 0.1 | U6: 0.12 | V6: 0.13 | W6: 0.14 | X6: 0.15 | Y6: 0.17 | AA6: 400 | AB6: 0 | AC6: 0.04 | AD6: 0.08 | AE6: 0.12 | AF6: 0.16 | AG6: 0.2 | AH6: 0.24 | AI6: 0.28 | AJ6: 0.32 | AK6: 0.36 | AL6: 0.4
A7: 500 | B7: 0.44 | C7: 0.46 | D7: 0.48 | E7: 0.51 | F7: 0.53 | G7: 0.56 | H7: 0.58 | I7: 0.61 | J7: 0.63 | K7: 0.66 | L7: 0.68 | N7: 500 | O7: 0.02 | P7: 0.03 | Q7: 0.04 | R7: 0.06 | S7: 0.07 | T7: 0.09 | U7: 0.1 | V7: 0.12 | W7: 0.13 | X7: 0.15 | Y7: 0.16 | AA7: 500 | AB7: 0 | AC7: 0.05 | AD7: 0.09 | AE7: 0.14 | AF7: 0.18 | AG7: 0.23 | AH7: 0.28 | AI7: 0.32 | AJ7: 0.37 | AK7: 0.42 | AL7: 0.46
A8: 600 | B8: 0.38 | C8: 0.41 | D8: 0.43 | E8: 0.46 | F8: 0.49 | G8: 0.52 | H8: 0.54 | I8: 0.57 | J8: 0.6 | K8: 0.63 | L8: 0.65 | N8: 600 | O8: -0.01 | P8: 0.01 | Q8: 0.03 | R8: 0.04 | S8: 0.06 | T8: 0.07 | U8: 0.09 | V8: 0.11 | W8: 0.12 | X8: 0.14 | Y8: 0.16 | AA8: 600 | AB8: 0 | AC8: 0.05 | AD8: 0.1 | AE8: 0.16 | AF8: 0.21 | AG8: 0.26 | AH8: 0.31 | AI8: 0.36 | AJ8: 0.42 | AK8: 0.47 | AL8: 0.52
A9: 700 | B9: 0.33 | C9: 0.36 | D9: 0.39 | E9: 0.42 | F9: 0.45 | G9: 0.48 | H9: 0.51 | I9: 0.54 | J9: 0.57 | K9: 0.6 | L9: 0.63 | N9: 700 | O9: -0.03 | P9: -0.01 | Q9: 0.01 | R9: 0.03 | S9: 0.05 | T9: 0.06 | U9: 0.08 | V9: 0.1 | W9: 0.12 | X9: 0.13 | Y9: 0.15 | AA9: 700 | AB9: 0 | AC9: 0.06 | AD9: 0.11 | AE9: 0.17 | AF9: 0.23 | AG9: 0.29 | AH9: 0.34 | AI9: 0.4 | AJ9: 0.46 | AK9: 0.51 | AL9: 0.57
A10: 800 | B10: 0.24 | C10: 0.27 | D10: 0.29 | E10: 0.32 | F10: 0.34 | G10: 0.37 | H10: 0.39 | I10: 0.42 | J10: 0.45 | K10: 0.47 | L10: 0.5 | N10: 800 | O10: -0.01 | P10: 0 | Q10: 0.02 | R10: 0.03 | S10: 0.05 | T10: 0.06 | U10: 0.08 | V10: 0.09 | W10: 0.11 | X10: 0.12 | Y10: 0.14 | AA10: 800 | AB10: 0 | AC10: 0.05 | AD10: 0.1 | AE10: 0.14 | AF10: 0.19 | AG10: 0.24 | AH10: 0.29 | AI10: 0.34 | AJ10: 0.38 | AK10: 0.43 | AL10: 0.48
A11: 900 | B11: 0.21 | C11: 0.24 | D11: 0.27 | E11: 0.29 | F11: 0.32 | G11: 0.35 | H11: 0.38 | I11: 0.4 | J11: 0.43 | K11: 0.46 | L11: 0.49 | N11: 900 | O11: -0.03 | P11: -0.01 | Q11: 0.01 | R11: 0.02 | S11: 0.04 | T11: 0.06 | U11: 0.07 | V11: 0.09 | W11: 0.1 | X11: 0.12 | Y11: 0.14 | AA11: 900 | AB11: 0 | AC11: 0.05 | AD11: 0.1 | AE11: 0.16 | AF11: 0.21 | AG11: 0.26 | AH11: 0.31 | AI11: 0.36 | AJ11: 0.41 | AK11: 0.47 | AL11: 0.52
A12: 1000 | B12: 0.18 | C12: 0.21 | D12: 0.24 | E12: 0.27 | F12: 0.3 | G12: 0.33 | H12: 0.36 | I12: 0.39 | J12: 0.42 | K12: 0.45 | L12: 0.48 | N12: 1000 | O12: -0.02 | P12: -0.02 | Q12: 0 | R12: 0.01 | S12: 0.03 | T12: 0.05 | U12: 0.07 | V12: 0.08 | W12: 0.1 | X12: 0.12 | Y12: 0.13 | AA12: 1000 | AB12: 0 | AC12: 0.06 | AD12: 0.11 | AE12: 0.17 | AF12: 0.22 | AG12: 0.28 | AH12: 0.33 | AI12: 0.39 | AJ12: 0.44 | AK12: 0.5 | AL12: 0.55
A13: 1100 | B13: 0.16 | C13: 0.19 | D13: 0.22 | E13: 0.25 | F13: 0.28 | G13: 0.31 | H13: 0.34 | I13: 0.37 | J13: 0.41 | K13: 0.44 | L13: 0.47 | N13: 1100 | O13: -0.03 | P13: -0.03 | Q13: -0.01 | R13: 0 | S13: 0.02 | T13: 0.04 | U13: 0.06 | V13: 0.08 | W13: 0.1 | X13: 0.11 | Y13: 0.13 | AA13: 1100 | AB13: 0 | AC13: 0.06 | AD13: 0.12 | AE13: 0.18 | AF13: 0.23 | AG13: 0.29 | AH13: 0.35 | AI13: 0.41 | AJ13: 0.47 | AK13: 0.53 | AL13: 0.58
A14: 1200 | B14: 0.13 | C14: 0.17 | D14: 0.2 | E14: 0.23 | F14: 0.26 | G14: 0.3 | H14: 0.33 | I14: 0.36 | J14: 0.39 | K14: 0.43 | L14: 0.45 | N14: 1200 | O14: -0.06 | P14: -0.04 | Q14: -0.02 | R14: 0 | S14: 0.02 | T14: 0.03 | U14: 0.05 | V14: 0.07 | W14: 0.09 | X14: 0.11 | Y14: 0.13 | AA14: 1200 | AB14: 0 | AC14: 0.06 | AD14: 0.12 | AE14: 0.18 | AF14: 0.25 | AG14: 0.31 | AH14: 0.37 | AI14: 0.43 | AJ14: 0.49 | AK14: 0.55 | AL14: 0.61
... A16: 1400 | B16: 0.09 | C16: 0.13 | D16: 0.16 | E16: 0.2 | F16: 0.23 | G16: 0.27 | H16: 0.3 | I16: 0.34 | J16: 0.37 | K16: 0.41 | L16: 0.45 | N16: 1400 | O16: -0.08 | P16: -0.06 | Q16: -0.04 | R16: -0.02 | S16: 0 | T16: 0.02 | U16: 0.04 | V16: 0.07 | W16: 0.09 | X16: 0.11 | Y16: 0.13 | AA16: 1400 | AB16: 0 | AC16: 0.07 | AD16: 0.13 | AE16: 0.2 | AF16: 0.27 | AG16: 0.33 | AH16: 0.4 | AI16: 0.47 | AJ16: 0.53 | AK16: 0.6 | AL16: 0.67
A18: DUO H2 / 4 € | N18: DUO GNL | AA18: DUO DIESEL
A19: KMS / % VERDE | B19: 0 | C19: 10 | D19: 20 | E19: 30 | F19: 40 | G19: 50 | H19: 60 | I19: 70 | J19: 80 | K19: 90 | L19: 100 | N19: KMS / % BIO | O19: 0 | P19: 10 | Q19: 20 | R19: 30 | S19: 40 | T19: 50 | U19: 60 | V19: 70 | W19: 80 | X19: 90 | Y19: 100 | AA19: KMS / % HVO | AB19: 0 | AC19: 10 | AD19: 20 | AE19: 30 | AF19: 40 | AG19: 50 | AH19: 60 | AI19: 70 | AJ19: 80 | AK19: 90 | AL19: 100
A20: 100 | B20: -0.02 | C20: -0.02 | D20: -0.01 | E20: -0.01 | F20: 0 | G20: 0 | H20: 0.01 | I20: 0.01 | J20: 0.02 | K20: 0.02 | L20: 0.03 | N20: 100 | O20: -0.31 | P20: -0.31 | Q20: -0.31 | R20: -0.31 | S20: -0.3 | T20: -0.3 | U20: -0.3 | V20: -0.3 | W20: -0.29 | X20: -0.29 | Y20: -0.29 | AA20: 100 | AB20: -0.33 | AC20: -0.33 | AD20: -0.31 | AE20: -0.3 | AF20: -0.3 | AG20: -0.29 | AH20: -0.28 | AI20: -0.27 | AJ20: -0.26 | AK20: -0.25 | AL20: -0.24
A21: 200 | B21: -0.07 | C21: -0.06 | D21: -0.05 | E21: -0.04 | F21: -0.04 | G21: -0.03 | H21: -0.02 | I21: -0.01 | J21: 0 | K21: 0.01 | L21: 0.02 | N21: 200 | O21: -0.33 | P21: -0.33 | Q21: -0.32 | R21: -0.32 | S21: -0.31 | T21: -0.31 | U21: -0.3 | V21: -0.3 | W21: -0.29 | X21: -0.29 | Y21: -0.28 | AA21: 200 | AB21: -0.33 | AC21: -0.33 | AD21: -0.29 | AE21: -0.28 | AF21: -0.26 | AG21: -0.25 | AH21: -0.23 | AI21: -0.21 | AJ21: -0.2 | AK21: -0.18 | AL21: -0.16
A22: 300 | B22: -0.11 | C22: -0.1 | D22: -0.09 | E22: -0.08 | F22: -0.07 | G22: -0.05 | H22: -0.04 | I22: -0.03 | J22: -0.02 | K22: -0.01 | L22: 0.01 | N22: 300 | O22: -0.35 | P22: -0.34 | Q22: -0.33 | R22: -0.33 | S22: -0.32 | T22: -0.31 | U22: -0.3 | V22: -0.3 | W22: -0.29 | X22: -0.28 | Y22: -0.28 | AA22: 300 | AB22: -0.32 | AC22: -0.3 | AD22: -0.28 | AE22: -0.26 | AF22: -0.23 | AG22: -0.21 | AH22: -0.19 | AI22: -0.17 | AJ22: -0.14 | AK22: -0.12 | AL22: -0.1
A23: 400 | B23: -0.15 | C23: -0.13 | D23: -0.12 | E23: -0.1 | F23: -0.09 | G23: -0.08 | H23: -0.06 | I23: -0.05 | J23: -0.03 | K23: -0.02 | L23: 0 | N23: 400 | O23: -0.36 | P23: -0.35 | Q23: -0.34 | R23: -0.33 | S23: -0.32 | T23: -0.31 | U23: -0.31 | V23: -0.3 | W23: -0.29 | X23: -0.28 | Y23: -0.27 | AA23: 400 | AB23: -0.32 | AC23: -0.29 | AD23: -0.26 | AE23: -0.24 | AF23: -0.21 | AG23: -0.18 | AH23: -0.15 | AI23: -0.13 | AJ23: -0.1 | AK23: -0.07 | AL23: -0.04
A24: 500 | B24: -0.18 | C24: -0.16 | D24: -0.15 | E24: -0.13 | F24: -0.11 | G24: -0.09 | H24: -0.08 | I24: -0.06 | J24: -0.04 | K24: -0.03 | L24: -0.01 | N24: 500 | O24: -0.37 | P24: -0.36 | Q24: -0.35 | R24: -0.34 | S24: -0.33 | T24: -0.32 | U24: -0.31 | V24: -0.3 | W24: -0.29 | X24: -0.28 | Y24: -0.27 | AA24: 500 | AB24: -0.32 | AC24: -0.28 | AD24: -0.25 | AE24: -0.22 | AF24: -0.19 | AG24: -0.16 | AH24: -0.12 | AI24: -0.09 | AJ24: -0.06 | AK24: -0.03 | AL24: 0.01
A25: 600 | B25: -0.21 | C25: -0.19 | D25: -0.17 | E25: -0.15 | F25: -0.13 | G25: -0.11 | H25: -0.09 | I25: -0.07 | J25: -0.05 | K25: -0.03 | L25: -0.01 | N25: 600 | O25: -0.38 | P25: -0.37 | Q25: -0.36 | R25: -0.34 | S25: -0.33 | T25: -0.32 | U25: -0.31 | V25: -0.3 | W25: -0.29 | X25: -0.28 | Y25: -0.26 | AA25: 600 | AB25: -0.31 | AC25: -0.28 | AD25: -0.24 | AE25: -0.21 | AF25: -0.17 | AG25: -0.13 | AH25: -0.1 | AI25: -0.06 | AJ25: -0.02 | AK25: 0.01 | AL25: 0.05
A26: 700 | B26: -0.23 | C26: -0.21 | D26: -0.19 | E26: -0.17 | F26: -0.15 | G26: -0.13 | H26: -0.1 | I26: -0.08 | J26: -0.06 | K26: -0.04 | L26: -0.02 | N26: 700 | O26: -0.39 | P26: -0.37 | Q26: -0.36 | R26: -0.35 | S26: -0.34 | T26: -0.32 | U26: -0.31 | V26: -0.3 | W26: -0.29 | X26: -0.27 | Y26: -0.26 | AA26: 700 | AB26: -0.31 | AC26: -0.27 | AD26: -0.23 | AE26: -0.19 | AF26: -0.15 | AG26: -0.11 | AH26: -0.07 | AI26: -0.03 | AJ26: 0.01 | AK26: 0.05 | AL26: 0.09
A27: 800 | B27: -0.3 | C27: -0.28 | D27: -0.26 | E27: -0.24 | F27: -0.22 | G27: -0.21 | H27: -0.19 | I27: -0.17 | J27: -0.15 | K27: -0.14 | L27: -0.12 | N27: 800 | O27: -0.41 | P27: -0.4 | Q27: -0.39 | R27: -0.37 | S27: -0.36 | T27: -0.35 | U27: -0.34 | V27: -0.33 | W27: -0.32 | X27: -0.31 | Y27: -0.3 | AA27: 800 | AB27: -0.34 | AC27: -0.31 | AD27: -0.27 | AE27: -0.24 | AF27: -0.21 | AG27: -0.17 | AH27: -0.14 | AI27: -0.11 | AJ27: -0.07 | AK27: -0.04 | AL27: 0
A28: 900 | B28: -0.31 | C28: -0.29 | D28: -0.27 | E28: -0.25 | F28: -0.23 | G28: -0.21 | H28: -0.19 | I28: -0.17 | J28: -0.16 | K28: -0.14 | L28: -0.12 | N28: 900 | O28: -0.41 | P28: -0.4 | Q28: -0.39 | R28: -0.38 | S28: -0.37 | T28: -0.35 | U28: -0.34 | V28: -0.33 | W28: -0.32 | X28: -0.31 | Y28: -0.3 | AA28: 900 | AB28: -0.34 | AC28: -0.3 | AD28: -0.27 | AE28: -0.23 | AF28: -0.19 | AG28: -0.16 | AH28: -0.12 | AI28: -0.08 | AJ28: -0.05 | AK28: -0.01 | AL28: 0.02
A29: 1000 | B29: -0.32 | C29: -0.3 | D29: -0.28 | E29: -0.26 | F29: -0.24 | G29: -0.22 | H29: -0.2 | I29: -0.18 | J29: -0.16 | K29: -0.14 | L29: -0.12 | N29: 1000 | O29: -0.42 | P29: -0.4 | Q29: -0.39 | R29: -0.38 | S29: -0.37 | T29: -0.35 | U29: -0.34 | V29: -0.33 | W29: -0.32 | X29: -0.31 | Y29: -0.29 | AA29: 1000 | AB29: -0.34 | AC29: -0.3 | AD29: -0.26 | AE29: -0.22 | AF29: -0.18 | AG29: -0.14 | AH29: -0.1 | AI29: -0.07 | AJ29: -0.03 | AK29: 0.01 | AL29: 0.05
A30: 1100 | B30: -0.33 | C30: -0.31 | D30: -0.29 | E30: -0.27 | F30: -0.25 | G30: -0.22 | H30: -0.2 | I30: -0.18 | J30: -0.16 | K30: -0.14 | L30: -0.12 | N30: 1100 | O30: -0.42 | P30: -0.41 | Q30: -0.39 | R30: -0.38 | S30: -0.37 | T30: -0.35 | U30: -0.34 | V30: -0.33 | W30: -0.32 | X30: -0.3 | Y30: -0.29 | AA30: 1100 | AB30: -0.33 | AC30: -0.29 | AD30: -0.25 | AE30: -0.21 | AF30: -0.17 | AG30: -0.13 | AH30: -0.09 | AI30: -0.05 | AJ30: -0.01 | AK30: 0.03 | AL30: 0.08
A31: 1200 | B31: -0.34 | C31: -0.32 | D31: -0.3 | E31: -0.28 | F31: -0.25 | G31: -0.23 | H31: -0.21 | I31: -0.18 | J31: -0.16 | K31: -0.14 | L31: -0.12 | N31: 1200 | O31: -0.42 | P31: -0.41 | Q31: -0.4 | R31: -0.38 | S31: -0.37 | T31: -0.36 | U31: -0.34 | V31: -0.33 | W31: -0.31 | X31: -0.3 | Y31: -0.29 | AA31: 1200 | AB31: -0.33 | AC31: -0.29 | AD31: -0.25 | AE31: -0.2 | AF31: -0.16 | AG31: -0.12 | AH31: -0.07 | AI31: -0.03 | AJ31: 0.01 | AK31: 0.06 | AL31: 0.1
... A33: 1400 | B33: -0.36 | C33: -0.34 | D33: -0.31 | E33: -0.29 | F33: -0.26 | G33: -0.24 | H33: -0.21 | I33: -0.19 | J33: -0.16 | K33: -0.14 | L33: -0.11 | N33: 1400 | O33: -0.43 | P33: -0.41 | Q33: -0.4 | R33: -0.39 | S33: -0.37 | T33: -0.36 | U33: -0.34 | V33: -0.33 | W33: -0.31 | X33: -0.3 | Y33: -0.28 | AA33: 1400 | AB33: -0.33 | AC33: -0.28 | AD33: -0.24 | AE33: -0.19 | AF33: -0.14 | AG33: -0.09 | AH33: -0.05 | AI33: 0 | AJ33: 0.05 | AK33: 0.09 | AL33: 0.14
A37: TABLAS NO DINÁMICAS
A38: SIN SUBVENCIÓN | B38: 100 KMS/DIA | C38: 200 KMS/DIA | D38: 300 KMS/DIA | E38: 400 KMS/DIA | F38: 500 KMS/DIA | G38: 600 KMS/DIA | H38: 700 KMS/DIA | I38: 800 KMS/DIA | J38: 900 KMS/DIA | K38: 1000 KMS/DIA | L38: 1100 KMS/DIA | M38: 1200 KMS/DIA | N38: 1300 KMS/DIA | O38: 1400 KMS/DIA | T38: =1.5/0.9 -> 1.6666667
A39: H2 (5 €) | B39: =5.93 -> 5.93 | C39: 3.18 | D39: 2.27 | E39: 1.81 | F39: 1.54 | G39: 1.35 | H39: 1.22 | I39: 1.32 | J39: 1.22 | K39: 1.14 | L39: 1.08 | M39: 1.03 | N39: 0.98 | O39: 0.94 | T39: =T38*0.3 -> 0.5
A40: H2 (4 €) | B40: 5.85 | C40: 3.1 | D40: 2.19 | E40: 1.73 | F40: 1.45 | G40: 1.27 | H40: 1.14 | I40: 1.24 | J40: 1.14 | K40: 1.06 | L40: 1 | M40: 0.94 | N40: 0.9 | O40: 0.86
A41: H2 (3 €) | B41: 5.76 | C41: 3.02 | D41: 2.1 | E41: 1.64 | F41: 1.37 | G41: 1.19 | H41: 1.06 | I41: 1.16 | J41: 1.06 | K41: 0.98 | L41: 0.91 | M41: 0.86 | N41: 0.81 | O41: 0.78
A42: H2 (2 €) | B42: 5.68 | C42: 2.93 | D42: 2.02 | E42: 1.56 | F42: 1.29 | G42: 1.1 | H42: 0.97 | I42: 1.07 | J42: 0.97 | K42: 0.9 | L42: 0.83 | M42: 0.78 | N42: 0.73 | O42: 0.69
A43: H2 (1 €) | B43: 5.6 | C43: 2.85 | D43: 1.94 | E43: 1.48 | F43: 1.2 | G43: 1.02 | H43: 0.89 | I43: 0.99 | J43: 0.89 | K43: 0.81 | L43: 0.75 | M43: 0.69 | N43: 0.65 | O43: 0.61 | Q43: =50/1000 -> 0.05
A44: Diesel (0,8 €) | B44: 3.12 | C44: 1.7 | D44: 1.23 | E44: 0.99 | F44: 0.85 | G44: 0.76 | H44: 0.69 | I44: 0.82 | J44: 0.76 | K44: 0.71 | L44: 0.67 | M44: 0.64 | N44: 0.61 | O44: 0.59 | Q44: =1000/0.77 -> 1298.7013
A45: GNL (0,6 €) | B45: 3.67 | C45: 1.93 | D45: 1.35 | E45: 1.06 | F45: 0.88 | G45: 0.77 | H45: 0.68 | I45: 0.82 | J45: 0.75 | K45: 0.69 | L45: 0.65 | M45: 0.61 | N45: 0.58 | O45: 0.55 | Q45: =50/Q44 -> 0.0385
A46: BIOMETANO (1,05 €) | B46: 3.79 | C46: 2.05 | D46: 1.47 | E46: 1.18 | F46: 1.01 | G46: 0.89 | H46: 0.81 | I46: 0.94 | J46: 0.87 | K46: 0.82 | L46: 0.77 | M46: 0.73 | N46: 0.7 | O46: 0.67 | Q46: =Q45/0.9 -> 0.042777778
A47: ELÉCTRICO (0,14 € KWH) | B47: 5.18 | C47: 2.73 | D47: 1.91 | E47: 1.5 | F47: 1.26 | G47: 1.1 | H47: 0.98 | I47: 1.09 | J47: 1 | K47: 0.93 | L47: 0.87 | M47: 0.82 | N47: 0.78 | O47: 0.74
A48: HVO | B48: 3.51 | C48: 2.09 | D48: 1.62 | E48: 1.39 | F48: 1.24 | G48: 1.15 | H48: 1.08 | I48: 1.21 | J48: 1.15 | K48: 1.1 | L48: 1.07 | M48: 1.03 | N48: 1.01 | O48: 0.98 | Q48: =0.08*3.5 -> 0.28 | S48: 3.5
Q49: =0.95*0.3 -> 0.285
A50: SIN SUBVENCIÓN | B50: 100 KMS/DIA | C50: 200 KMS/DIA | D50: 300 KMS/DIA | E50: 400 KMS/DIA | F50: 500 KMS/DIA | G50: 600 KMS/DIA | H50: 700 KMS/DIA | I50: 800 KMS/DIA | J50: 900 KMS/DIA | K50: 1000 KMS/DIA | L50: 1100 KMS/DIA | M50: 1200 KMS/DIA | N50: 1300 KMS/DIA | O50: 1400 KMS/DIA
A51: H2 (5 €) | B51: =B39/B$44-1 -> 0.90064103 | C51: =C39/C$44-1 -> 0.87058824 | D51: =D39/D$44-1 -> 0.84552846 | E51: =E39/E$44-1 -> 0.82828283 | F51: =F39/F$44-1 -> 0.81176471 | G51: =G39/G$44-1 -> 0.77631579 | H51: =H39/H$44-1 -> 0.76811594 | I51: =I39/I$44-1 -> 0.6097561 | ... O51: =O39/O$44-1 -> 0.59322034
A52: H2 (4 €) | B52: =B40/B$44-1 -> 0.875 | C52: =C40/C$44-1 -> 0.82352941 | D52: =D40/D$44-1 -> 0.7804878 | E52: =E40/E$44-1 -> 0.74747475 | F52: =F40/F$44-1 -> 0.70588235 | G52: =G40/G$44-1 -> 0.67105263 | H52: =H40/H$44-1 -> 0.65217391 | I52: =I40/I$44-1 -> 0.51219512 | ... O52: =O40/O$44-1 -> 0.45762712
A53: H2 (3 €) | B53: =B41/B$44-1 -> 0.84615385 | C53: =C41/C$44-1 -> 0.77647059 | D53: =D41/D$44-1 -> 0.70731707 | E53: =E41/E$44-1 -> 0.65656566 | F53: =F41/F$44-1 -> 0.61176471 | G53: =G41/G$44-1 -> 0.56578947 | H53: =H41/H$44-1 -> 0.53623188 | I53: =I41/I$44-1 -> 0.41463415 | ... O53: =O41/O$44-1 -> 0.3220339
A54: H2 (2 €) | B54: =B42/B$44-1 -> 0.82051282 | C54: =C42/C$44-1 -> 0.72352941 | D54: =D42/D$44-1 -> 0.64227642 | E54: =E42/E$44-1 -> 0.57575758 | F54: =F42/F$44-1 -> 0.51764706 | G54: =G42/G$44-1 -> 0.44736842 | H54: =H42/H$44-1 -> 0.4057971 | I54: =I42/I$44-1 -> 0.30487805 | ... O54: =O42/O$44-1 -> 0.16949153
A55: H2 (1 €) | B55: =B43/B$44-1 -> 0.79487179 | C55: =C43/C$44-1 -> 0.67647059 | D55: =D43/D$44-1 -> 0.57723577 | E55: =E43/E$44-1 -> 0.49494949 | F55: =F43/F$44-1 -> 0.41176471 | G55: =G43/G$44-1 -> 0.34210526 | H55: =H43/H$44-1 -> 0.28985507 | I55: =I43/I$44-1 -> 0.20731707 | ... O55: =O43/O$44-1 -> 0.033898305
A56: Diesel (0,8 €) | B56: =B44/B$44-1 -> 0 | C56: =C44/C$44-1 -> 0 | D56: =D44/D$44-1 -> 0 | E56: =E44/E$44-1 -> 0 | F56: =F44/F$44-1 -> 0 | G56: =G44/G$44-1 -> 0 | H56: =H44/H$44-1 -> 0 | I56: =I44/I$44-1 -> 0 | ... O56: =O44/O$44-1 -> 0
A57: GNL (0,6 €) | B57: =B45/B$44-1 -> 0.17628205 | C57: =C45/C$44-1 -> 0.13529412 | D57: =D45/D$44-1 -> 0.097560976 | E57: =E45/E$44-1 -> 0.070707071 | F57: =F45/F$44-1 -> 0.035294118 | G57: =G45/G$44-1 -> 0.013157895 | H57: =H45/H$44-1 -> -0.014492754 | I57: =I45/I$44-1 -> 0 | ... O57: =O45/O$44-1 -> -0.06779661
A58: BIOMETANO (1,05 €) | B58: =B46/B$44-1 -> 0.21474359 | C58: =C46/C$44-1 -> 0.20588235 | D58: =D46/D$44-1 -> 0.19512195 | E58: =E46/E$44-1 -> 0.19191919 | F58: =F46/F$44-1 -> 0.18823529 | G58: =G46/G$44-1 -> 0.17105263 | H58: =H46/H$44-1 -> 0.17391304 | I58: =I46/I$44-1 -> 0.14634146 | ... O58: =O46/O$44-1 -> 0.13559322
A59: ELÉCTRICO (0,14 € KWH) | B59: =B47/B$44-1 -> 0.66025641 | C59: =C47/C$44-1 -> 0.60588235 | D59: =D47/D$44-1 -> 0.55284553 | E59: =E47/E$44-1 -> 0.51515152 | F59: =F47/F$44-1 -> 0.48235294 | G59: =G47/G$44-1 -> 0.44736842 | H59: =H47/H$44-1 -> 0.42028986 | I59: =I47/I$44-1 -> 0.32926829 | ... O59: =O47/O$44-1 -> 0.25423729
A60: HVO | B60: =B48/B$44-1 -> 0.125 | C60: =C48/C$44-1 -> 0.22941176 | D60: =D48/D$44-1 -> 0.31707317 | E60: =E48/E$44-1 -> 0.4040404 | F60: =F48/F$44-1 -> 0.45882353 | G60: =G48/G$44-1 -> 0.51315789 | H60: =H48/H$44-1 -> 0.56521739 | I60: =I48/I$44-1 -> 0.47560976 | ... O60: =O48/O$44-1 -> 0.66101695
A62: GNL /BIO CON SUBV | B62: 100 KMS/DIA | C62: 200 KMS/DIA | D62: 300 KMS/DIA | E62: 400 KMS/DIA | F62: 500 KMS/DIA | G62: 600 KMS/DIA | H62: 700 KMS/DIA | I62: 800 KMS/DIA | J62: 900 KMS/DIA | K62: 1000 KMS/DIA | L62: 1100 KMS/DIA | M62: 1200 KMS/DIA | N62: 1300 KMS/DIA | O62: 1400 KMS/DIA
A63: GNL (0,6 €) | B63: 3.53 | C63: 1.86 | D63: 1.3 | E63: 1.02 | F63: 0.85 | G63: 0.74 | H63: 0.66 | I63: 0.8 | J63: 0.73 | K63: 0.68 | L63: 0.63 | M63: 0.6 | N63: 0.56 | O63: =0.54 -> 0.54
A64: BIOMETANO (1,05 €) | B64: 3.65 | C64: 1.98 | D64: 1.42 | E64: 1.14 | F64: 0.98 | G64: 0.87 | H64: 0.79 | I64: 0.93 | J64: 0.86 | K64: 0.8 | L64: 0.76 | M64: 0.72 | N64: 0.69 | O64: 0.66
A66: GNL /BIO CON SUBV | B66: 100 KMS/DIA | C66: 200 KMS/DIA | D66: 300 KMS/DIA | E66: 400 KMS/DIA | F66: 500 KMS/DIA | G66: 600 KMS/DIA | H66: 700 KMS/DIA | I66: 800 KMS/DIA | J66: 900 KMS/DIA | K66: 1000 KMS/DIA | L66: 1100 KMS/DIA | M66: 1200 KMS/DIA | N66: 1300 KMS/DIA | O66: 1400 KMS/DIA
A67: GNL (0,6 €) | B67: =B63/B$44-1 -> 0.13141026 | C67: =C63/C$44-1 -> 0.094117647 | D67: =D63/D$44-1 -> 0.056910569 | E67: =E63/E$44-1 -> 0.03030303 | F67: =F63/F$44-1 -> 0 | G67: =G63/G$44-1 -> -0.026315789 | H67: =H63/H$44-1 -> -0.043478261 | I67: =I63/I$44-1 -> -0.024390244 | ... O67: =O63/O$44-1 -> -0.084745763
A68: BIOMETANO (1,05 €) | B68: =B64/B$44-1 -> 0.16987179 | C68: =C64/C$44-1 -> 0.16470588 | D68: =D64/D$44-1 -> 0.15447154 | E68: =E64/E$44-1 -> 0.15151515 | F68: =F64/F$44-1 -> 0.15294118 | G68: =G64/G$44-1 -> 0.14473684 | H68: =H64/H$44-1 -> 0.14492754 | I68: =I64/I$44-1 -> 0.13414634 | ... O68: =O64/O$44-1 -> 0.11864407
G80: =100000*1000 -> 100000000
G81: =G80/0.75 -> 1.3333333e+08
G82: =G81/150000 -> 888.88889

Sheet GASOIL 
E2: € | F2: % | G2: €/KM
C3: KMS DIARIOS
C4: KMS ANUALES
C5: KMS mensuales | E5: ='CALCULADORA COSTES'!B14*'CALCULADORA COSTES'!B15 -> 6600
C6: GASTOS FIJOS | E6: =SUM(E7:E29) -> 3538 | F6: =E6/E$5 -> 0.53606061 | G6: =E6/E$5 -> 0.53606061
C7: Cuota TRACTORA | E7: ='CALCULADORA COSTES'!E2 -> 2000 | F7: =E7/E$5 -> 0.3030303 | G7: =E7/E$5 -> 0.3030303
C8: Seguro tract. ( a 3os + Propios+seguro mercancias) | E8: 300 | F8: =E8/E$5 -> 0.045454545 | G8: =E8/E$5 -> 0.045454545
C9: Impto circulación Tract. | E9: 18 | F9: =E9/E$5 -> 0.0027272727 | G9: =E9/E$5 -> 0.0027272727
C10: Mantenimiento Tract. | E10: 162 | F10: =E10/E$5 -> 0.024545455 | G10: =E10/E$5 -> 0.024545455
C11: Reparación Tract.+ Equipo | E11: 100 | F11: =E11/E$5 -> 0.015151515 | G11: =E11/E$5 -> 0.015151515
C12: Equipo Tract. | E12: 50 | F12: =E12/E$5 -> 0.0075757576 | G12: =E12/E$5 -> 0.0075757576
C13: Siniestro Tract. | E13: 100 | F13: =E13/E$5 -> 0.015151515 | G13: =E13/E$5 -> 0.015151515
C14: Cuota PLATAFORMA | E14: ='CALCULADORA COSTES'!B20 -> 450 | F14: =E14/E$5 -> 0.068181818 | G14: =E14/E$5 -> 0.068181818
C15: Seguro Plat | E15: 25 | F15: =E15/E$5 -> 0.0037878788 | G15: =E15/E$5 -> 0.0037878788
C16: Impto circulación Plat | E16: 18 | F16: =E16/E$5 -> 0.0027272727 | G16: =E16/E$5 -> 0.0027272727
C17: Mantenimiento Plataforma + reparación | E17: 100 | F17: =E17/E$5 -> 0.015151515 | G17: =E17/E$5 -> 0.015151515
C18: Equipo Plat | E18: 50 | F18: =E18/E$5 -> 0.0075757576 | G18: =E18/E$5 -> 0.0075757576
C19: Siniestro Plat | E19: 150 | F19: =E19/E$5 -> 0.022727273 | G19: =E19/E$5 -> 0.022727273
C20: TELÉFONO | E20: 15 | F20: =E20/E$5 -> 0.0022727273 | G20: =E20/E$5 -> 0.0022727273
C21: Camb Cont (gtos fros) | F21: =E21/E$5 -> 0 | G21: =E21/E$5 -> 0
C22: Relaciones Públicas | F22: =E22/E$5 -> 0 | G22: =E22/E$5 -> 0
C23: Gastos Var. | F23: =E23/E$5 -> 0 | G23: =E23/E$5 -> 0
C24: Amortización Cont. | F24: =E24/E$5 -> 0 | G24: =E24/E$5 -> 0
C25: Mantenimiento (Gruas) | F25: =E25/E$5 -> 0 | G25: =E25/E$5 -> 0
C26: Suministros | F26: =E26/E$5 -> 0 | G26: =E26/E$5 -> 0
C27: Compras | F27: =E27/E$5 -> 0 | G27: =E27/E$5 -> 0
C28: PARKING | F28: =E28/E$5 -> 0 | G28: =E28/E$5 -> 0
C29: Reg. Cierre | F29: =E29/E$5 -> 0 | G29: =E29/E$5 -> 0
C30: GASTOS VARIABLES | E30: =SUM(E31:E37) -> 5130.64 | F30: =E30/E5 -> 0.7773697 | G30: =SUM(G31:G37) -> 0.7773697
C31: GASTO PERSONAL | D31: ='CALCULADORA COSTES'!B17*'CALCULADORA COSTES'!B16 -> 3048 | E31: =D31 -> 3048 | F31: =E31/E5 -> 0.46181818 | G31: =E31/E5 -> 0.46181818
D32: º | F32: =E32/E5 -> 0 | G32: =E32/E5 -> 0
C33: GASOIL (0,8 €/ltr) (31,5 L/100) | D33: ='CALCULADORA COSTES'!B2*'CALCULADORA COSTES'!C2 -> 0.28 | E33: =+D33*E5 -> 1848 | F33: =E33/E5 -> 0.28 | G33: =E33/E5 -> 0.28
C34: AUTOPISTA | E34: ='CALCULADORA COSTES'!E24*'CALCULADORA COSTES'!E25 -> 0 | F34: =E34/E5 -> 0 | G34: =E34/E5 -> 0
C35: NEUMÁTICOS TRACT.(0,0105€/km) | D35: 0.0102 | E35: =+D35*E5 -> 67.32 | F35: =E35/E5 -> 0.0102 | G35: =E35/E5 -> 0.0102
C36: NEUMÁTICOS PLAT. (0,0105€/km) | D36: 0.0102 | E36: =+D36*E5 -> 67.32 | F36: =E36/E5 -> 0.0102 | G36: =E36/E5 -> 0.0102
C37: OTROS GASTOS | E37: 100 | F37: =E37/E5 -> 0.015151515 | G37: =E37/E5 -> 0.015151515
C40: COSTE TOTAL | E40: =E30+E6 -> 8668.64 | F40: 1 | G40: =SUM(G30+G6) -> 1.3134303
F41: 0 | G41: 0
C42: Planificación Flota | E42: 275 | F42: =E42/E5 -> 0.041666667 | G42: =E42/E5 -> 0.041666667
C43: margen | D43: 0.04 | E43: =+E40*0.04 -> 346.7456 | F43: =E43/E5 -> 0.052537212 | G43: =E43/E5 -> 0.052537212
C44: Estructura Indirecta | F44: 0 | G44: 0
C45: Estructura General | F45: 0 | G45: 0
C46: COSTE PRODUCTIVO | E46: =E40+SUM(E42:E45) -> 9290.3856 | F46: 1 | G46: =SUM(G40:G45) -> 1.4076342
C47: PRECIO INTRAGRUPO TOTAL
C48: PRECIO COSTE €/KM | E48: =G46+E47 -> 1.4076342

Sheet GAS NATURAL
C1: CAMIONES DE GAS
E2: € | F2: % | G2: €/KM
C3: KMS DIARIOS
C4: KMS ANUALES
C5: KMS mensuales | E5: ='CALCULADORA COSTES'!B14*'CALCULADORA COSTES'!B15 -> 6600
C6: GASTOS FIJOS | E6: =SUM(E7:E29) -> 4109 | F6: =E6/E$5 -> 0.62257576 | G6: =E6/E$5 -> 0.62257576
C7: Cuota TRACTORA | E7: ='CALCULADORA COSTES'!E3 -> 2400 | F7: =E7/E$5 -> 0.36363636 | G7: =E7/E$5 -> 0.36363636
C8: Seguro tract. ( a 3os + Propios+seguro mercancias) | E8: 300 | F8: =E8/E$5 -> 0.045454545 | G8: =E8/E$5 -> 0.045454545
C9: Impto circulación Tract. | E9: 18 | F9: =E9/E$5 -> 0.0027272727 | G9: =E9/E$5 -> 0.0027272727
C10: Mantenimiento Tract. | E10: 348 | F10: =E10/E$5 -> 0.052727273 | G10: =E10/E$5 -> 0.052727273
C11: Reparación Tract.+ Equipo | E11: 100 | F11: =E11/E$5 -> 0.015151515 | G11: =E11/E$5 -> 0.015151515
C12: Equipo Tract. | E12: 50 | F12: =E12/E$5 -> 0.0075757576 | G12: =E12/E$5 -> 0.0075757576
C13: Siniestro Tract. | E13: 100 | F13: =E13/E$5 -> 0.015151515 | G13: =E13/E$5 -> 0.015151515
C14: Cuota PLATAFORMA | E14: ='CALCULADORA COSTES'!B20 -> 450 | F14: =E14/E$5 -> 0.068181818 | G14: =E14/E$5 -> 0.068181818
C15: Seguro Plat | E15: 25 | F15: =E15/E$5 -> 0.0037878788 | G15: =E15/E$5 -> 0.0037878788
C16: Impto circulación Plat | E16: 18 | F16: =E16/E$5 -> 0.0027272727 | G16: =E16/E$5 -> 0.0027272727
C17: Mantenimiento Plataforma + reparación | E17: 150 | F17: =E17/E$5 -> 0.022727273 | G17: =E17/E$5 -> 0.022727273
C18: Equipo Plat | E18: 50 | F18: =E18/E$5 -> 0.0075757576 | G18: =E18/E$5 -> 0.0075757576
C19: Siniestro Plat | E19: 85 | F19: =E19/E$5 -> 0.012878788 | G19: =E19/E$5 -> 0.012878788
C20: TELÉFONO | E20: 15 | F20: =E20/E$5 -> 0.0022727273 | G20: =E20/E$5 -> 0.0022727273
C21: Camb Cont (gtos fros) | F21: =E21/E$5 -> 0 | G21: =E21/E$5 -> 0
C22: Relaciones Públicas | F22: =E22/E$5 -> 0 | G22: =E22/E$5 -> 0
C23: Gastos Var. | F23: =E23/E$5 -> 0 | G23: =E23/E$5 -> 0
C24: Amortización Cont. | F24: =E24/E$5 -> 0 | G24: =E24/E$5 -> 0
C25: Mantenimiento (Gruas) | F25: =E25/E$5 -> 0 | G25: =E25/E$5 -> 0
C26: Suministros | F26: =E26/E$5 -> 0 | G26: =E26/E$5 -> 0
C27: Compras | F27: =E27/E$5 -> 0 | G27: =E27/E$5 -> 0
C28: PARKING | E28: 0 | F28: =E28/E$5 -> 0 | G28: =E28/E$5 -> 0
C29: Reg. Cierre | F29: =E29/E$5 -> 0 | G29: =E29/E$5 -> 0
C30: GASTOS VARIABLES | E30: =SUM(E31:E36) -> 6394.48 | F30: =E30/E5 -> 0.96886061 | G30: =SUM(G31:G36) -> 0.96886061
C31: GASTO PERSONAL | D31: ='CALCULADORA COSTES'!B17*'CALCULADORA COSTES'!B16 -> 3048 | E31: =D31*(1+'CALCULADORA COSTES'!E26) -> 3200.4 | F31: =E31/E5 -> 0.48490909 | G31: =E31/E5 -> 0.48490909
C32: GAS | D32: ='CALCULADORA COSTES'!B3*'CALCULADORA COSTES'!C3 -> 0.4488 | E32: =+D32*E5 -> 2962.08 | F32: =E32/E5 -> 0.4488 | G32: =E32/E5 -> 0.4488
C33: AUTOPISTA | D33: =0 -> 0 | E33: ='CALCULADORA COSTES'!E24*'CALCULADORA COSTES'!E25 -> 0 | F33: =E33/E5 -> 0 | G33: =E33/E5 -> 0
C34: NEUMÁTICOS TRACT.(0,0105€/km) | D34: 0.01 | E34: =+D34*E5 -> 66 | F34: =E34/E5 -> 0.01 | G34: =E34/E5 -> 0.01
C35: NEUMÁTICOS PLAT. (0,0105€/km) | D35: 0.01 | E35: =+D35*E5 -> 66 | F35: =E35/E5 -> 0.01 | G35: =E35/E5 -> 0.01
C36: OTROS GASTOS | E36: 100 | F36: =E36/E5 -> 0.015151515 | G36: =E36/E5 -> 0.015151515
C39: COSTE TOTAL | E39: =E30+E6 -> 10503.48 | F39: 1 | G39: =SUM(G30+G6) -> 1.5914364
F40: 0 | G40: 0
C41: Planificación Flota | E41: 275 | F41: =E41/E5 -> 0.041666667 | G41: =E41/E5 -> 0.041666667
C42: margen | D42: 0.04 | E42: =+E39*0.04 -> 420.1392 | F42: =E42/E5 -> 0.063657455 | G42: =E42/E5 -> 0.063657455
C43: Estructura Indirecta | F43: 0 | G43: 0
C44: Estructura General | F44: 0 | G44: 0
C45: COSTE PRODUCTIVO | E45: =E39+SUM(E41:E44) -> 11198.619 | F45: 1 | G45: =SUM(G39:G44) -> 1.6967605
C46: PRECIO INTRAGRUPO TOTAL
C47: PRECIO COSTE €/KM | E47: =G45+E46 -> 1.6967605

Sheet H2
C1: CAMIONES DE GAS
E2: € | F2: % | G2: €/KM
C3: KMS DIARIOS
C4: KMS ANUALES
C5: KMS mensuales | E5: ='CALCULADORA COSTES'!B14*'CALCULADORA COSTES'!B15 -> 6600
C6: GASTOS FIJOS | E6: =SUM(E7:E29) -> 7909 | F6: =E6/E$5 -> 1.1983333 | G6: =E6/E$5 -> 1.1983333
C7: Cuota TRACTORA | E7: ='CALCULADORA COSTES'!E4 -> 6200 | F7: =E7/E$5 -> 0.93939394 | G7: =E7/E$5 -> 0.93939394
C8: Seguro tract. ( a 3os + Propios+seguro mercancias) | E8: 300 | F8: =E8/E$5 -> 0.045454545 | G8: =E8/E$5 -> 0.045454545
C9: Impto circulación Tract. | E9: 18 | F9: =E9/E$5 -> 0.0027272727 | G9: =E9/E$5 -> 0.0027272727
C10: Mantenimiento Tract. | E10: 348 | F10: =E10/E$5 -> 0.052727273 | G10: =E10/E$5 -> 0.052727273
C11: Reparación Tract.+ Equipo | E11: 100 | F11: =E11/E$5 -> 0.015151515 | G11: =E11/E$5 -> 0.015151515
C12: Equipo Tract. | E12: 50 | F12: =E12/E$5 -> 0.0075757576 | G12: =E12/E$5 -> 0.0075757576
C13: Siniestro Tract. | E13: 100 | F13: =E13/E$5 -> 0.015151515 | G13: =E13/E$5 -> 0.015151515
C14: Cuota PLATAFORMA | E14: ='CALCULADORA COSTES'!B20 -> 450 | F14: =E14/E$5 -> 0.068181818 | G14: =E14/E$5 -> 0.068181818
C15: Seguro Plat | E15: 25 | F15: =E15/E$5 -> 0.0037878788 | G15: =E15/E$5 -> 0.0037878788
C16: Impto circulación Plat | E16: 18 | F16: =E16/E$5 -> 0.0027272727 | G16: =E16/E$5 -> 0.0027272727
C17: Mantenimiento Plataforma + reparación | E17: 150 | F17: =E17/E$5 -> 0.022727273 | G17: =E17/E$5 -> 0.022727273
C18: Equipo Plat | E18: 50 | F18: =E18/E$5 -> 0.0075757576 | G18: =E18/E$5 -> 0.0075757576
C19: Siniestro Plat | E19: 85 | F19: =E19/E$5 -> 0.012878788 | G19: =E19/E$5 -> 0.012878788
C20: TELÉFONO | E20: 15 | F20: =E20/E$5 -> 0.0022727273 | G20: =E20/E$5 -> 0.0022727273
C21: Camb Cont (gtos fros) | F21: =E21/E$5 -> 0 | G21: =E21/E$5 -> 0
C22: Relaciones Públicas | F22: =E22/E$5 -> 0 | G22: =E22/E$5 -> 0
C23: Gastos Var. | F23: =E23/E$5 -> 0 | G23: =E23/E$5 -> 0
C24: Amortización Cont. | F24: =E24/E$5 -> 0 | G24: =E24/E$5 -> 0
C25: Mantenimiento (Gruas) | F25: =E25/E$5 -> 0 | G25: =E25/E$5 -> 0
C26: Suministros | F26: =E26/E$5 -> 0 | G26: =E26/E$5 -> 0
C27: Compras | F27: =E27/E$5 -> 0 | G27: =E27/E$5 -> 0
C28: PARKING | E28: 0 | F28: =E28/E$5 -> 0 | G28: =E28/E$5 -> 0
C29: Reg. Cierre | F29: =E29/E$5 -> 0 | G29: =E29/E$5 -> 0
C30: GASTOS VARIABLES | E30: =SUM(E31:E36) -> 7590.4 | F30: =E30/E5 -> 1.1500606 | G30: =SUM(G31:G36) -> 1.1500606
C31: GASTO PERSONAL | D31: ='CALCULADORA COSTES'!B17*'CALCULADORA COSTES'!B16 -> 3048 | E31: =D31*('CALCULADORA COSTES'!E26+1) -> 3200.4 | F31: =E31/E5 -> 0.48490909 | G31: =E31/E5 -> 0.48490909
C32: H2 | D32: ='CALCULADORA COSTES'!B4*'CALCULADORA COSTES'!C4 -> 0.63 | E32: =+D32*E5 -> 4158 | F32: =E32/E5 -> 0.63 | G32: =E32/E5 -> 0.63
C33: AUTOPISTA | E33: ='CALCULADORA COSTES'!E24*'CALCULADORA COSTES'!E25 -> 0 | F33: =E33/E5 -> 0 | G33: =E33/E5 -> 0
C34: NEUMÁTICOS TRACT.(0,0105€/km) | D34: 0.01 | E34: =+D34*E5 -> 66 | F34: =E34/E5 -> 0.01 | G34: =E34/E5 -> 0.01
C35: NEUMÁTICOS PLAT. (0,0105€/km) | D35: 0.01 | E35: =+D35*E5 -> 66 | F35: =E35/E5 -> 0.01 | G35: =E35/E5 -> 0.01
C36: OTROS GASTOS | E36: 100 | F36: =E36/E5 -> 0.015151515 | G36: =E36/E5 -> 0.015151515
C39: COSTE TOTAL | E39: =E30+E6 -> 15499.4 | F39: 1 | G39: =SUM(G30+G6) -> 2.3483939
F40: 0 | G40: 0
C41: Planificación Flota | E41: 275 | F41: =E41/E5 -> 0.041666667 | G41: =E41/E5 -> 0.041666667
C42: margen | D42: 0.04 | E42: =+E39*0.04 -> 619.976 | F42: =E42/E5 -> 0.093935758 | G42: =E42/E5 -> 0.093935758
C43: Estructura Indirecta | F43: 0 | G43: 0
C44: Estructura General | F44: 0 | G44: 0
C45: COSTE PRODUCTIVO | E45: =E39+SUM(E41:E44) -> 16394.376 | F45: 1 | G45: =SUM(G39:G44) -> 2.4839964
C46: PRECIO INTRAGRUPO TOTAL
C47: PRECIO COSTE €/KM | E47: =G45+E46 -> 2.4839964

Sheet HVO
E2: € | F2: % | G2: €/KM
C3: KMS DIARIOS
C4: KMS ANUALES
C5: KMS mensuales | E5: ='CALCULADORA COSTES'!B14*'CALCULADORA COSTES'!B15 -> 6600
C6: GASTOS FIJOS | E6: =SUM(E7:E29) -> 3538 | F6: =E6/E$5 -> 0.53606061 | G6: =E6/E$5 -> 0.53606061
C7: Cuota TRACTORA | E7: ='CALCULADORA COSTES'!E2 -> 2000 | F7: =E7/E$5 -> 0.3030303 | G7: =E7/E$5 -> 0.3030303
C8: Seguro tract. ( a 3os + Propios+seguro mercancias) | E8: 300 | F8: =E8/E$5 -> 0.045454545 | G8: =E8/E$5 -> 0.045454545
C9: Impto circulación Tract. | E9: 18 | F9: =E9/E$5 -> 0.0027272727 | G9: =E9/E$5 -> 0.0027272727
C10: Mantenimiento Tract. | E10: 162 | F10: =E10/E$5 -> 0.024545455 | G10: =E10/E$5 -> 0.024545455
C11: Reparación Tract.+ Equipo | E11: 100 | F11: =E11/E$5 -> 0.015151515 | G11: =E11/E$5 -> 0.015151515
C12: Equipo Tract. | E12: 50 | F12: =E12/E$5 -> 0.0075757576 | G12: =E12/E$5 -> 0.0075757576
C13: Siniestro Tract. | E13: 100 | F13: =E13/E$5 -> 0.015151515 | G13: =E13/E$5 -> 0.015151515
C14: Cuota PLATAFORMA | E14: ='CALCULADORA COSTES'!B20 -> 450 | F14: =E14/E$5 -> 0.068181818 | G14: =E14/E$5 -> 0.068181818
C15: Seguro Plat | E15: 25 | F15: =E15/E$5 -> 0.0037878788 | G15: =E15/E$5 -> 0.0037878788
C16: Impto circulación Plat | E16: 18 | F16: =E16/E$5 -> 0.0027272727 | G16: =E16/E$5 -> 0.0027272727
C17: Mantenimiento Plataforma + reparación | E17: 100 | F17: =E17/E$5 -> 0.015151515 | G17: =E17/E$5 -> 0.015151515
C18: Equipo Plat | E18: 50 | F18: =E18/E$5 -> 0.0075757576 | G18: =E18/E$5 -> 0.0075757576
C19: Siniestro Plat | E19: 150 | F19: =E19/E$5 -> 0.022727273 | G19: =E19/E$5 -> 0.022727273
C20: TELÉFONO | E20: 15 | F20: =E20/E$5 -> 0.0022727273 | G20: =E20/E$5 -> 0.0022727273
C21: Camb Cont (gtos fros) | F21: =E21/E$5 -> 0 | G21: =E21/E$5 -> 0
C22: Relaciones Públicas | F22: =E22/E$5 -> 0 | G22: =E22/E$5 -> 0
C23: Gastos Var. | F23: =E23/E$5 -> 0 | G23: =E23/E$5 -> 0
C24: Amortización Cont. | F24: =E24/E$5 -> 0 | G24: =E24/E$5 -> 0
C25: Mantenimiento (Gruas) | F25: =E25/E$5 -> 0 | G25: =E25/E$5 -> 0
C26: Suministros | F26: =E26/E$5 -> 0 | G26: =E26/E$5 -> 0
C27: Compras | F27: =E27/E$5 -> 0 | G27: =E27/E$5 -> 0
C28: PARKING | F28: =E28/E$5 -> 0 | G28: =E28/E$5 -> 0
C29: Reg. Cierre | F29: =E29/E$5 -> 0 | G29: =E29/E$5 -> 0
C30: GASTOS VARIABLES | E30: =SUM(E31:E37) -> 5777.44 | F30: =E30/E5 -> 0.8753697 | G30: =SUM(G31:G37) -> 0.8753697
C31: GASTO PERSONAL | D31: ='CALCULADORA COSTES'!B17*'CALCULADORA COSTES'!B16 -> 3048 | E31: =D31 -> 3048 | F31: =E31/E5 -> 0.46181818 | G31: =E31/E5 -> 0.46181818
F32: =E32/E5 -> 0 | G32: =E32/E5 -> 0
C33: HVO | D33: ='CALCULADORA COSTES'!D7 -> 0.378 | E33: =+D33*E5 -> 2494.8 | F33: =E33/E5 -> 0.378 | G33: =E33/E5 -> 0.378
C34: AUTOPISTA | E34: ='CALCULADORA COSTES'!E24*'CALCULADORA COSTES'!E25 -> 0 | F34: =E34/E5 -> 0 | G34: =E34/E5 -> 0
C35: NEUMÁTICOS TRACT.(0,0105€/km) | D35: 0.0102 | E35: =+D35*E5 -> 67.32 | F35: =E35/E5 -> 0.0102 | G35: =E35/E5 -> 0.0102
C36: NEUMÁTICOS PLAT. (0,0105€/km) | D36: 0.0102 | E36: =+D36*E5 -> 67.32 | F36: =E36/E5 -> 0.0102 | G36: =E36/E5 -> 0.0102
C37: OTROS GASTOS | E37: 100 | F37: =E37/E5 -> 0.015151515 | G37: =E37/E5 -> 0.015151515
C40: COSTE TOTAL | E40: =E30+E6 -> 9315.44 | F40: 1 | G40: =SUM(G30+G6) -> 1.4114303
F41: 0 | G41: 0
C42: Planificación Flota | E42: 275 | F42: =E42/E5 -> 0.041666667 | G42: =E42/E5 -> 0.041666667
C43: margen | D43: 0.04 | E43: =+E40*0.04 -> 372.6176 | F43: =E43/E5 -> 0.056457212 | G43: =E43/E5 -> 0.056457212
C44: Estructura Indirecta | F44: 0 | G44: 0
C45: Estructura General | F45: 0 | G45: 0
C46: COSTE PRODUCTIVO | E46: =E40+SUM(E42:E45) -> 9963.0576 | F46: 1 | G46: =SUM(G40:G45) -> 1.5095542
C47: PRECIO INTRAGRUPO TOTAL
C48: PRECIO COSTE €/KM | E48: =G46+E47 -> 1.5095542

Sheet BIOMETANO
C1: CAMION BIOMETANO
E2: € | F2: % | G2: €/KM
C3: KMS DIARIOS
C4: KMS ANUALES
C5: KMS mensuales | E5: ='CALCULADORA COSTES'!B14*'CALCULADORA COSTES'!B15 -> 6600
C6: GASTOS FIJOS | E6: =SUM(E7:E29) -> 4109 | F6: =E6/E$5 -> 0.62257576 | G6: =E6/E$5 -> 0.62257576
C7: Cuota TRACTORA | E7: ='CALCULADORA COSTES'!E3 -> 2400 | F7: =E7/E$5 -> 0.36363636 | G7: =E7/E$5 -> 0.36363636
C8: Seguro tract. ( a 3os + Propios+seguro mercancias) | E8: 300 | F8: =E8/E$5 -> 0.045454545 | G8: =E8/E$5 -> 0.045454545
C9: Impto circulación Tract. | E9: 18 | F9: =E9/E$5 -> 0.0027272727 | G9: =E9/E$5 -> 0.0027272727
C10: Mantenimiento Tract. | E10: 348 | F10: =E10/E$5 -> 0.052727273 | G10: =E10/E$5 -> 0.052727273
C11: Reparación Tract.+ Equipo | E11: 100 | F11: =E11/E$5 -> 0.015151515 | G11: =E11/E$5 -> 0.015151515
C12: Equipo Tract. | E12: 50 | F12: =E12/E$5 -> 0.0075757576 | G12: =E12/E$5 -> 0.0075757576
C13: Siniestro Tract. | E13: 100 | F13: =E13/E$5 -> 0.015151515 | G13: =E13/E$5 -> 0.015151515
C14: Cuota PLATAFORMA | E14: ='CALCULADORA COSTES'!B20 -> 450 | F14: =E14/E$5 -> 0.068181818 | G14: =E14/E$5 -> 0.068181818
C15: Seguro Plat | E15: 25 | F15: =E15/E$5 -> 0.0037878788 | G15: =E15/E$5 -> 0.0037878788
C16: Impto circulación Plat | E16: 18 | F16: =E16/E$5 -> 0.0027272727 | G16: =E16/E$5 -> 0.0027272727
C17: Mantenimiento Plataforma + reparación | E17: 150 | F17: =E17/E$5 -> 0.022727273 | G17: =E17/E$5 -> 0.022727273
C18: Equipo Plat | E18: 50 | F18: =E18/E$5 -> 0.0075757576 | G18: =E18/E$5 -> 0.0075757576
C19: Siniestro Plat | E19: 85 | F19: =E19/E$5 -> 0.012878788 | G19: =E19/E$5 -> 0.012878788
C20: TELÉFONO | E20: 15 | F20: =E20/E$5 -> 0.0022727273 | G20: =E20/E$5 -> 0.0022727273
C21: Camb Cont (gtos fros) | F21: =E21/E$5 -> 0 | G21: =E21/E$5 -> 0
C22: Relaciones Públicas | F22: =E22/E$5 -> 0 | G22: =E22/E$5 -> 0
C23: Gastos Var. | F23: =E23/E$5 -> 0 | G23: =E23/E$5 -> 0
C24: Amortización Cont. | F24: =E24/E$5 -> 0 | G24: =E24/E$5 -> 0
C25: Mantenimiento (Gruas) | F25: =E25/E$5 -> 0 | G25: =E25/E$5 -> 0
C26: Suministros | F26: =E26/E$5 -> 0 | G26: =E26/E$5 -> 0
C27: Compras | F27: =E27/E$5 -> 0 | G27: =E27/E$5 -> 0
C28: PARKING | E28: 0 | F28: =E28/E$5 -> 0 | G28: =E28/E$5 -> 0
C29: Reg. Cierre | F29: =E29/E$5 -> 0 | G29: =E29/E$5 -> 0
C30: GASTOS VARIABLES | E30: =SUM(E31:E36) -> 6569.056 | F30: =E30/E5 -> 0.99531152 | G30: =SUM(G31:G36) -> 0.99531152
C31: GASTO PERSONAL | D31: =(2000+85+22*36.06+20+150)*'CALCULADORA COSTES'!B16 -> 3048.32 | E31: =D31*(1+'CALCULADORA COSTES'!E26) -> 3200.736 | F31: =E31/E5 -> 0.48496 | G31: =E31/E5 -> 0.48496
C32: GAS (0,6 €/KG) (26,40 K/100) | D32: ='CALCULADORA COSTES'!B5*'CALCULADORA COSTES'!C5 -> 0.4752 | E32: =+D32*E5 -> 3136.32 | F32: =E32/E5 -> 0.4752 | G32: =E32/E5 -> 0.4752
C33: AUTOPISTA | D33: =0 -> 0 | E33: ='CALCULADORA COSTES'!E24*'CALCULADORA COSTES'!E25 -> 0 | F33: =E33/E5 -> 0 | G33: =E33/E5 -> 0
C34: NEUMÁTICOS TRACT.(0,0105€/km) | D34: 0.01 | E34: =+D34*E5 -> 66 | F34: =E34/E5 -> 0.01 | G34: =E34/E5 -> 0.01
C35: NEUMÁTICOS PLAT. (0,0105€/km) | D35: 0.01 | E35: =+D35*E5 -> 66 | F35: =E35/E5 -> 0.01 | G35: =E35/E5 -> 0.01
C36: OTROS GASTOS | E36: 100 | F36: =E36/E5 -> 0.015151515 | G36: =E36/E5 -> 0.015151515
C39: COSTE TOTAL | E39: =E30+E6 -> 10678.056 | F39: 1 | G39: =SUM(G30+G6) -> 1.6178873
F40: 0 | G40: 0
C41: Planificación Flota | E41: 275 | F41: =E41/E5 -> 0.041666667 | G41: =E41/E5 -> 0.041666667
C42: margen | D42: 0.04 | E42: =+E39*0.04 -> 427.12224 | F42: =E42/E5 -> 0.064715491 | G42: =E42/E5 -> 0.064715491
C43: Estructura Indirecta | F43: 0 | G43: 0
C44: Estructura General | F44: 0 | G44: 0
C45: COSTE PRODUCTIVO | E45: =E39+SUM(E41:E44) -> 11380.178 | F45: 1 | G45: =SUM(G39:G44) -> 1.7242694
C46: PRECIO INTRAGRUPO TOTAL
C47: PRECIO COSTE €/KM | E47: =G45+E46 -> 1.7242694

Sheet ELÉCTRICO
C1: CAMIONES DE GAS
E2: € | F2: % | G2: €/KM
C3: KMS DIARIOS
C4: KMS ANUALES
C5: KMS mensuales | E5: ='CALCULADORA COSTES'!B14*'CALCULADORA COSTES'!B15 -> 6600
C6: GASTOS FIJOS | E6: =SUM(E7:E29) -> 5705 | F6: =E6/E$5 -> 0.86439394 | G6: =E6/E$5 -> 0.86439394
C7: Cuota TRACTORA | E7: ='CALCULADORA COSTES'!$E6 -> 4000 | F7: =E7/E$5 -> 0.60606061 | G7: =E7/E$5 -> 0.60606061
C8: Seguro tract. ( a 3os + Propios+seguro mercancias) | E8: 300 | F8: =E8/E$5 -> 0.045454545 | G8: =E8/E$5 -> 0.045454545
C9: Impto circulación Tract. | E9: 18 | F9: =E9/E$5 -> 0.0027272727 | G9: =E9/E$5 -> 0.0027272727
C10: Mantenimiento Tract. | E10: 348 | F10: =E10/E$5 -> 0.052727273 | G10: =E10/E$5 -> 0.052727273
C11: Reparación Tract.+ Equipo | E11: 100 | F11: =E11/E$5 -> 0.015151515 | G11: =E11/E$5 -> 0.015151515
C12: Equipo Tract. | E12: 50 | F12: =E12/E$5 -> 0.0075757576 | G12: =E12/E$5 -> 0.0075757576
C13: Siniestro Tract. | E13: 100 | F13: =E13/E$5 -> 0.015151515 | G13: =E13/E$5 -> 0.015151515
C14: Cuota PLATAFORMA | E14: ='CALCULADORA COSTES'!B20 -> 450 | F14: =E14/E$5 -> 0.068181818 | G14: =E14/E$5 -> 0.068181818
C15: Seguro Plat | E15: 25 | F15: =E15/E$5 -> 0.0037878788 | G15: =E15/E$5 -> 0.0037878788
C16: Impto circulación Plat | E16: 18 | F16: =E16/E$5 -> 0.0027272727 | G16: =E16/E$5 -> 0.0027272727
C17: Mantenimiento Plataforma + reparación | E17: 150 | F17: =E17/E$5 -> 0.022727273 | G17: =E17/E$5 -> 0.022727273
C18: Equipo Plat | E18: 50 | F18: =E18/E$5 -> 0.0075757576 | G18: =E18/E$5 -> 0.0075757576
C19: Siniestro Plat | E19: 85 | F19: =E19/E$5 -> 0.012878788 | G19: =E19/E$5 -> 0.012878788
C20: TELÉFONO | E20: 11 | F20: =E20/E$5 -> 0.0016666667 | G20: =E20/E$5 -> 0.0016666667
C21: Camb Cont (gtos fros) | F21: =E21/E$5 -> 0 | G21: =E21/E$5 -> 0
C22: Relaciones Públicas | F22: =E22/E$5 -> 0 | G22: =E22/E$5 -> 0
C23: Gastos Var. | F23: =E23/E$5 -> 0 | G23: =E23/E$5 -> 0
C24: Amortización Cont. | F24: =E24/E$5 -> 0 | G24: =E24/E$5 -> 0
C25: Mantenimiento (Gruas) | F25: =E25/E$5 -> 0 | G25: =E25/E$5 -> 0
C26: Suministros | F26: =E26/E$5 -> 0 | G26: =E26/E$5 -> 0
C27: Compras | F27: =E27/E$5 -> 0 | G27: =E27/E$5 -> 0
C28: PARKING | E28: 0 | F28: =E28/E$5 -> 0 | G28: =E28/E$5 -> 0
C29: Reg. Cierre | F29: =E29/E$5 -> 0 | G29: =E29/E$5 -> 0
C30: GASTOS VARIABLES | E30: =SUM(E31:E36) -> 6210.34 | F30: =E30/E5 -> 0.94096061 | G30: =SUM(G31:G36) -> 0.94096061
C31: GASTO PERSONAL | D31: ='CALCULADORA COSTES'!B17*'CALCULADORA COSTES'!B16 -> 3048 | E31: =D31*(1+'CALCULADORA COSTES'!E26) -> 3200.4 | F31: =E31/E5 -> 0.48490909 | G31: =E31/E5 -> 0.48490909
C32: Eléctrico | D32: ='CALCULADORA COSTES'!B6*'CALCULADORA COSTES'!C6 -> 0.4209 | E32: =D32*E5 -> 2777.94 | F32: =E32/E5 -> 0.4209 | G32: =E32/E5 -> 0.4209
C33: AUTOPISTA | E33: ='CALCULADORA COSTES'!E24*'CALCULADORA COSTES'!E25 -> 0 | F33: =E33/E5 -> 0 | G33: =E33/E5 -> 0
C34: NEUMÁTICOS TRACT.(0,0105€/km) | D34: 0.01 | E34: =+D34*E5 -> 66 | F34: =E34/E5 -> 0.01 | G34: =E34/E5 -> 0.01
C35: NEUMÁTICOS PLAT. (0,0105€/km) | D35: 0.01 | E35: =+D35*E5 -> 66 | F35: =E35/E5 -> 0.01 | G35: =E35/E5 -> 0.01
C36: OTROS GASTOS | E36: 100 | F36: =E36/E5 -> 0.015151515 | G36: =E36/E5 -> 0.015151515
C39: COSTE TOTAL | E39: =E30+E6 -> 11915.34 | F39: 1 | G39: =SUM(G30+G6) -> 1.8053545
F40: 0 | G40: 0
C41: Planificación Flota | E41: 275 | F41: =E41/E5 -> 0.041666667 | G41: =E41/E5 -> 0.041666667
C42: margen | D42: 0.04 | E42: =+E39*0.04 -> 476.6136 | F42: =E42/E5 -> 0.072214182 | G42: =E42/E5 -> 0.072214182
C43: Estructura Indirecta | F43: 0 | G43: 0
C44: Estructura General | F44: 0 | G44: 0
C45: COSTE PRODUCTIVO | E45: =E39+SUM(E41:E44) -> 12666.954 | F45: 1 | G45: =SUM(G39:G44) -> 1.9192354
C46: PRECIO INTRAGRUPO TOTAL
C47: PRECIO COSTE €/KM | E47: =G45+E45 -> 12668.873

Sheet DUOTRAILER GASOIL
E2: € | F2: % | G2: €/KM
C3: KMS DIARIOS
C4: KMS ANUALES
C5: KMS mensuales | E5: ='CALCULADORA COSTES'!B14*'CALCULADORA COSTES'!B15 -> 6600
C6: GASTOS FIJOS | E6: =SUM(E7:E29) -> 5047 | F6: =E6/E$5 -> 0.76469697 | G6: =E6/E$5 -> 0.76469697
C7: Cuota TRACTORA | E7: ='CALCULADORA COSTES'!E9 -> 2200 | F7: =E7/E$5 -> 0.33333333 | G7: =E7/E$5 -> 0.33333333
C8: Seguro tract. ( a 3os + Propios+seguro mercancias) | E8: 300 | F8: =E8/E$5 -> 0.045454545 | G8: =E8/E$5 -> 0.045454545
C9: Impto circulación Tract. | E9: 18 | F9: =E9/E$5 -> 0.0027272727 | G9: =E9/E$5 -> 0.0027272727
C10: Mantenimiento Tract. | E10: 400 | F10: =E10/E$5 -> 0.060606061 | G10: =E10/E$5 -> 0.060606061
C11: Reparación Tract.+ Equipo | E11: 100 | F11: =E11/E$5 -> 0.015151515 | G11: =E11/E$5 -> 0.015151515
C12: Equipo Tract. | E12: 50 | F12: =E12/E$5 -> 0.0075757576 | G12: =E12/E$5 -> 0.0075757576
C13: Siniestro Tract. | E13: 150 | F13: =E13/E$5 -> 0.022727273 | G13: =E13/E$5 -> 0.022727273
C14: Cuota PLATAFORMA Enganche | E14: =115+'CALCULADORA COSTES'!B20 -> 565 | F14: =E14/E$5 -> 0.085606061 | G14: =E14/E$5 -> 0.085606061
C15: Seguro Plat | E15: 25 | F15: =E15/E$5 -> 0.0037878788 | G15: =E15/E$5 -> 0.0037878788
C16: Impto circulación Plat | E16: 18 | F16: =E16/E$5 -> 0.0027272727 | G16: =E16/E$5 -> 0.0027272727
C17: Mantenimiento Plataforma + reparación | E17: 125 | F17: =E17/E$5 -> 0.018939394 | G17: =E17/E$5 -> 0.018939394
C18: CUOTA DOLLY | E18: ='CALCULADORA COSTES'!C20 -> 200 | F18: =E18/E$5 -> 0.03030303 | G18: =E18/E$5 -> 0.03030303
C19: Seguro Dolly | E19: 25 | F19: =E19/E$5 -> 0.0037878788 | G19: =E19/E$5 -> 0.0037878788
C20: Impuesto Dolly | E20: 18 | F20: =E20/E$5 -> 0.0027272727 | G20: =E20/E$5 -> 0.0027272727
C21: Mantenimiento | E21: 50 | F21: =E21/E$5 -> 0.0075757576 | G21: =E21/E$5 -> 0.0075757576
C22: Cuota PLATAFORMA 2 | E22: ='CALCULADORA COSTES'!B20 -> 450 | F22: =E22/E$5 -> 0.068181818 | G22: =E22/E$5 -> 0.068181818
C23: Seguro Plat | E23: 25 | F23: =E23/E$5 -> 0.0037878788 | G23: =E23/E$5 -> 0.0037878788
C24: Impto circulación Plat | E24: 18 | F24: =E24/E$5 -> 0.0027272727 | G24: =E24/E$5 -> 0.0027272727
C25: Mantenimiento Plataforma + reparación | E25: 125 | F25: =E25/E$5 -> 0.018939394 | G25: =E25/E$5 -> 0.018939394
C26: Siniestros | E26: 170 | F26: =E26/E$5 -> 0.025757576 | G26: =E26/E$5 -> 0.025757576
C27: Teléfono | E27: 15 | F27: =E27/E$5 -> 0.0022727273 | G27: =E27/E$5 -> 0.0022727273
C28: PARKING | F28: =E28/E$5 -> 0 | G28: =E28/E$5 -> 0
C29: Reg. Cierre | F29: =E29/E$5 -> 0 | G29: =E29/E$5 -> 0
C30: GASTOS VARIABLES | E30: =SUM(E31:E37) -> 6156.88 | F30: =E30/E5 -> 0.93286061 | G30: =SUM(G31:G37) -> 0.93286061
C31: GASTO PERSONAL | D31: ='CALCULADORA COSTES'!B17*'CALCULADORA COSTES'!B16 -> 3048 | E31: ='H2'!E31 -> 3200.4 | F31: =E31/E5 -> 0.48490909 | G31: =E31/E5 -> 0.48490909
F32: =E32/E5 -> 0 | G32: =E32/E5 -> 0
C33: GASOIL (0,8 €/L) | D33: ='CALCULADORA COSTES'!B9*'CALCULADORA COSTES'!C9 -> 0.392 | E33: =+D33*E5 -> 2587.2 | F33: =E33/E5 -> 0.392 | G33: =E33/E5 -> 0.392
C34: AUTOPISTA | E34: ='CALCULADORA COSTES'!F24*'CALCULADORA COSTES'!F25 -> 0 | F34: =E34/E5 -> 0 | G34: =E34/E5 -> 0
C35: NEUMÁTICOS TRACT.(0,0105€/km) | D35: 0.0102 | E35: =+D35*E5*2 -> 134.64 | F35: =E35/E5 -> 0.0204 | G35: =E35/E5 -> 0.0204
C36: NEUMÁTICOS PLAT. (0,0105€/km) | D36: 0.0102 | E36: =+D36*E5*2 -> 134.64 | F36: =E36/E5 -> 0.0204 | G36: =E36/E5 -> 0.0204
C37: OTROS GASTOS | E37: 100 | F37: =E37/E5 -> 0.015151515 | G37: =E37/E5 -> 0.015151515
C40: COSTE TOTAL | E40: =E30+E6 -> 11203.88 | F40: 1 | G40: =SUM(G30+G6) -> 1.6975576
F41: 0 | G41: 0
C42: Planificación Flota | E42: 275 | F42: =E42/E5 -> 0.041666667 | G42: =E42/E5 -> 0.041666667
C43: margen | D43: 0.04 | E43: =+E40*0.04 -> 448.1552 | F43: =E43/E5 -> 0.067902303 | G43: =E43/E5 -> 0.067902303
C44: Estructura Indirecta | F44: 0 | G44: 0
C45: Estructura General | F45: 0 | G45: 0
C46: COSTE PRODUCTIVO | E46: =E40+SUM(E42:E45) -> 11927.035 | F46: 1 | G46: =SUM(G40:G45) -> 1.8071265
C47: PRECIO INTRAGRUPO TOTAL
C48: PRECIO COSTE €/KM | E48: =G46+E47 -> 1.8071265

Sheet DUOTRAILER HVO
E2: € | F2: % | G2: €/KM
C3: KMS DIARIOS
C4: KMS ANUALES
C5: KMS mensuales | E5: ='CALCULADORA COSTES'!B14*'CALCULADORA COSTES'!B15 -> 6600
C6: GASTOS FIJOS | E6: =SUM(E7:E29) -> 5047 | F6: =E6/E$5 -> 0.76469697 | G6: =E6/E$5 -> 0.76469697
C7: Cuota TRACTORA | E7: ='CALCULADORA COSTES'!E9 -> 2200 | F7: =E7/E$5 -> 0.33333333 | G7: =E7/E$5 -> 0.33333333
C8: Seguro tract. ( a 3os + Propios+seguro mercancias) | E8: 300 | F8: =E8/E$5 -> 0.045454545 | G8: =E8/E$5 -> 0.045454545
C9: Impto circulación Tract. | E9: 18 | F9: =E9/E$5 -> 0.0027272727 | G9: =E9/E$5 -> 0.0027272727
C10: Mantenimiento Tract. | E10: 400 | F10: =E10/E$5 -> 0.060606061 | G10: =E10/E$5 -> 0.060606061
C11: Reparación Tract.+ Equipo | E11: 100 | F11: =E11/E$5 -> 0.015151515 | G11: =E11/E$5 -> 0.015151515
C12: Equipo Tract. | E12: 50 | F12: =E12/E$5 -> 0.0075757576 | G12: =E12/E$5 -> 0.0075757576
C13: Siniestro Tract. | E13: 150 | F13: =E13/E$5 -> 0.022727273 | G13: =E13/E$5 -> 0.022727273
C14: Cuota PLATAFORMA Enganche | E14: ='DUOTRAILER GASOIL'!E14 -> 565 | F14: =E14/E$5 -> 0.085606061 | G14: =E14/E$5 -> 0.085606061
C15: Seguro Plat | E15: 25 | F15: =E15/E$5 -> 0.0037878788 | G15: =E15/E$5 -> 0.0037878788
C16: Impto circulación Plat | E16: 18 | F16: =E16/E$5 -> 0.0027272727 | G16: =E16/E$5 -> 0.0027272727
C17: Mantenimiento Plataforma + reparación | E17: 125 | F17: =E17/E$5 -> 0.018939394 | G17: =E17/E$5 -> 0.018939394
C18: CUOTA DOLLY | E18: ='DUOTRAILER GASOIL'!E18 -> 200 | F18: =E18/E$5 -> 0.03030303 | G18: =E18/E$5 -> 0.03030303
C19: Seguro Dolly | E19: 25 | F19: =E19/E$5 -> 0.0037878788 | G19: =E19/E$5 -> 0.0037878788
C20: Impuesto Dolly | E20: 18 | F20: =E20/E$5 -> 0.0027272727 | G20: =E20/E$5 -> 0.0027272727
C21: Mantenimiento | E21: 50 | F21: =E21/E$5 -> 0.0075757576 | G21: =E21/E$5 -> 0.0075757576
C22: Cuota PLATAFORMA 2 | E22: ='DUOTRAILER GASOIL'!E22 -> 450 | F22: =E22/E$5 -> 0.068181818 | G22: =E22/E$5 -> 0.068181818
C23: Seguro Plat | E23: 25 | F23: =E23/E$5 -> 0.0037878788 | G23: =E23/E$5 -> 0.0037878788
C24: Impto circulación Plat | E24: 18 | F24: =E24/E$5 -> 0.0027272727 | G24: =E24/E$5 -> 0.0027272727
C25: Mantenimiento Plataforma + reparación | E25: 125 | F25: =E25/E$5 -> 0.018939394 | G25: =E25/E$5 -> 0.018939394
C26: Siniestros | E26: 170 | F26: =E26/E$5 -> 0.025757576 | G26: =E26/E$5 -> 0.025757576
C27: Teléfono | E27: 15 | F27: =E27/E$5 -> 0.0022727273 | G27: =E27/E$5 -> 0.0022727273
C28: PARKING | F28: =E28/E$5 -> 0 | G28: =E28/E$5 -> 0
C29: Reg. Cierre | F29: =E29/E$5 -> 0 | G29: =E29/E$5 -> 0
C30: GASTOS VARIABLES | E30: =SUM(E31:E37) -> 7222.78 | F30: =E30/E5 -> 1.0943606 | G30: =SUM(G31:G37) -> 1.0943606
C31: GASTO PERSONAL | D31: ='CALCULADORA COSTES'!B17*'CALCULADORA COSTES'!B16 -> 3048 | E31: ='H2'!E31 -> 3200.4 | F31: =E31/E5 -> 0.48490909 | G31: =E31/E5 -> 0.48490909
F32: =E32/E5 -> 0 | G32: =E32/E5 -> 0
C33: GASOIL (0,8 €/L) | D33: ='CALCULADORA COSTES'!D11 -> 0.5535 | E33: =+D33*E5 -> 3653.1 | F33: =E33/E5 -> 0.5535 | G33: =E33/E5 -> 0.5535
C34: AUTOPISTA | E34: ='CALCULADORA COSTES'!F24*'CALCULADORA COSTES'!F25 -> 0 | F34: =E34/E5 -> 0 | G34: =E34/E5 -> 0
C35: NEUMÁTICOS TRACT.(0,0105€/km) | D35: 0.0102 | E35: =+D35*E5*2 -> 134.64 | F35: =E35/E5 -> 0.0204 | G35: =E35/E5 -> 0.0204
C36: NEUMÁTICOS PLAT. (0,0105€/km) | D36: 0.0102 | E36: =+D36*E5*2 -> 134.64 | F36: =E36/E5 -> 0.0204 | G36: =E36/E5 -> 0.0204
C37: OTROS GASTOS | E37: 100 | F37: =E37/E5 -> 0.015151515 | G37: =E37/E5 -> 0.015151515
C40: COSTE TOTAL | E40: =E30+E6 -> 12269.78 | F40: 1 | G40: =SUM(G30+G6) -> 1.8590576
F41: 0 | G41: 0
C42: Planificación Flota | E42: 275 | F42: =E42/E5 -> 0.041666667 | G42: =E42/E5 -> 0.041666667
C43: margen | D43: 0.04 | E43: =+E40*0.04 -> 490.7912 | F43: =E43/E5 -> 0.074362303 | G43: =E43/E5 -> 0.074362303
C44: Estructura Indirecta | F44: 0 | G44: 0
C45: Estructura General | F45: 0 | G45: 0
C46: COSTE PRODUCTIVO | E46: =E40+SUM(E42:E45) -> 13035.571 | F46: 1 | G46: =SUM(G40:G45) -> 1.9750865
C47: PRECIO INTRAGRUPO TOTAL
C48: PRECIO COSTE €/KM | E48: =G46+E47 -> 1.9750865

Sheet DUOTRAILER H2
E2: € | F2: % | G2: €/KM
C3: KMS DIARIOS
C4: KMS ANUALES
C5: KMS mensuales | E5: ='CALCULADORA COSTES'!B14*'CALCULADORA COSTES'!B15 -> 6600
C6: GASTOS FIJOS | E6: =SUM(E7:E29) -> 9047 | F6: =E6/E$5 -> 1.3707576 | G6: =E6/E$5 -> 1.3707576
C7: Cuota TRACTORA | E7: ='CALCULADORA COSTES'!E8 -> 6200 | F7: =E7/E$5 -> 0.93939394 | G7: =E7/E$5 -> 0.93939394
C8: Seguro tract. ( a 3os + Propios+seguro mercancias) | E8: 300 | F8: =E8/E$5 -> 0.045454545 | G8: =E8/E$5 -> 0.045454545
C9: Impto circulación Tract. | E9: 18 | F9: =E9/E$5 -> 0.0027272727 | G9: =E9/E$5 -> 0.0027272727
C10: Mantenimiento Tract. | E10: 400 | F10: =E10/E$5 -> 0.060606061 | G10: =E10/E$5 -> 0.060606061
C11: Reparación Tract.+ Equipo | E11: 100 | F11: =E11/E$5 -> 0.015151515 | G11: =E11/E$5 -> 0.015151515
C12: Equipo Tract. | E12: 50 | F12: =E12/E$5 -> 0.0075757576 | G12: =E12/E$5 -> 0.0075757576
C13: Siniestro Tract. | E13: 150 | F13: =E13/E$5 -> 0.022727273 | G13: =E13/E$5 -> 0.022727273
C14: Cuota PLATAFORMA Enganche | E14: ='DUOTRAILER GASOIL'!E14 -> 565 | F14: =E14/E$5 -> 0.085606061 | G14: =E14/E$5 -> 0.085606061
C15: Seguro Plat | E15: 25 | F15: =E15/E$5 -> 0.0037878788 | G15: =E15/E$5 -> 0.0037878788
C16: Impto circulación Plat | E16: 18 | F16: =E16/E$5 -> 0.0027272727 | G16: =E16/E$5 -> 0.0027272727
C17: Mantenimiento Plataforma + reparación | E17: 125 | F17: =E17/E$5 -> 0.018939394 | G17: =E17/E$5 -> 0.018939394
C18: CUOTA DOLLY | E18: ='DUOTRAILER GASOIL'!E18 -> 200 | F18: =E18/E$5 -> 0.03030303 | G18: =E18/E$5 -> 0.03030303
C19: Seguro Dolly | E19: 25 | F19: =E19/E$5 -> 0.0037878788 | G19: =E19/E$5 -> 0.0037878788
C20: Impuesto Dolly | E20: 18 | F20: =E20/E$5 -> 0.0027272727 | G20: =E20/E$5 -> 0.0027272727
C21: Mantenimiento | E21: 50 | F21: =E21/E$5 -> 0.0075757576 | G21: =E21/E$5 -> 0.0075757576
C22: Cuota PLATAFORMA 2 | E22: ='DUOTRAILER GASOIL'!E22 -> 450 | F22: =E22/E$5 -> 0.068181818 | G22: =E22/E$5 -> 0.068181818
C23: Seguro Plat | E23: 25 | F23: =E23/E$5 -> 0.0037878788 | G23: =E23/E$5 -> 0.0037878788
C24: Impto circulación Plat | E24: 18 | F24: =E24/E$5 -> 0.0027272727 | G24: =E24/E$5 -> 0.0027272727
C25: Mantenimiento Plataforma + reparación | E25: 125 | F25: =E25/E$5 -> 0.018939394 | G25: =E25/E$5 -> 0.018939394
C26: Siniestros | E26: 170 | F26: =E26/E$5 -> 0.025757576 | G26: =E26/E$5 -> 0.025757576
C27: Teléfono | E27: 15 | F27: =E27/E$5 -> 0.0022727273 | G27: =E27/E$5 -> 0.0022727273
C28: PARKING | F28: =E28/E$5 -> 0 | G28: =E28/E$5 -> 0
C29: Reg. Cierre | F29: =E29/E$5 -> 0 | G29: =E29/E$5 -> 0
C30: GASTOS VARIABLES | E30: =SUM(E31:E37) -> 9390.88 | F30: =E30/E5 -> 1.4228606 | G30: =SUM(G31:G37) -> 1.4228606
C31: GASTO PERSONAL | D31: ='CALCULADORA COSTES'!B17*'CALCULADORA COSTES'!B16 -> 3048 | E31: ='H2'!E31 -> 3200.4 | F31: =E31/E5 -> 0.48490909 | G31: =E31/E5 -> 0.48490909
F32: =E32/E5 -> 0 | G32: =E32/E5 -> 0
C33: Hidrógeno | D33: ='CALCULADORA COSTES'!B8*'CALCULADORA COSTES'!C8 -> 0.882 | E33: =+D33*E5 -> 5821.2 | F33: =E33/E5 -> 0.882 | G33: =E33/E5 -> 0.882
C34: AUTOPISTA | E34: ='CALCULADORA COSTES'!F24*'CALCULADORA COSTES'!F25 -> 0 | F34: =E34/E5 -> 0 | G34: =E34/E5 -> 0
C35: NEUMÁTICOS TRACT.(0,0105€/km) | D35: 0.0102 | E35: =+D35*E5*2 -> 134.64 | F35: =E35/E5 -> 0.0204 | G35: =E35/E5 -> 0.0204
C36: NEUMÁTICOS PLAT. (0,0105€/km) | D36: 0.0102 | E36: =+D36*E5*2 -> 134.64 | F36: =E36/E5 -> 0.0204 | G36: =E36/E5 -> 0.0204
C37: OTROS GASTOS | E37: 100 | F37: =E37/E5 -> 0.015151515 | G37: =E37/E5 -> 0.015151515
C40: COSTE TOTAL | E40: =E30+E6 -> 18437.88 | F40: 1 | G40: =SUM(G30+G6) -> 2.7936182
F41: 0 | G41: 0
C42: Planificación Flota | E42: 275 | F42: =E42/E5 -> 0.041666667 | G42: =E42/E5 -> 0.041666667
C43: margen | D43: 0.04 | E43: =+E40*0.04 -> 737.5152 | F43: =E43/E5 -> 0.11174473 | G43: =E43/E5 -> 0.11174473
C44: Estructura Indirecta | F44: 0 | G44: 0
C45: Estructura General | F45: 0 | G45: 0
C46: COSTE PRODUCTIVO | E46: =E40+SUM(E42:E45) -> 19450.395 | F46: 1 | G46: =SUM(G40:G45) -> 2.9470296
C47: PRECIO INTRAGRUPO TOTAL
C48: PRECIO COSTE €/KM | E48: =G46+E47 -> 2.9470296

Sheet DUOTRAILER ELECTRICO
E2: € | F2: % | G2: €/KM
C3: KMS DIARIOS
C4: KMS ANUALES
C5: KMS mensuales | E5: ='CALCULADORA COSTES'!B14*'CALCULADORA COSTES'!B15 -> 6600
C6: GASTOS FIJOS | E6: =SUM(E7:E29) -> 6847 | F6: =E6/E$5 -> 1.0374242 | G6: =E6/E$5 -> 1.0374242
C7: Cuota TRACTORA | E7: ='CALCULADORA COSTES'!E12 -> 4000 | F7: =E7/E$5 -> 0.60606061 | G7: =E7/E$5 -> 0.60606061
C8: Seguro tract. ( a 3os + Propios+seguro mercancias) | E8: 300 | F8: =E8/E$5 -> 0.045454545 | G8: =E8/E$5 -> 0.045454545
C9: Impto circulación Tract. | E9: 18 | F9: =E9/E$5 -> 0.0027272727 | G9: =E9/E$5 -> 0.0027272727
C10: Mantenimiento Tract. | E10: 400 | F10: =E10/E$5 -> 0.060606061 | G10: =E10/E$5 -> 0.060606061
C11: Reparación Tract.+ Equipo | E11: 100 | F11: =E11/E$5 -> 0.015151515 | G11: =E11/E$5 -> 0.015151515
C12: Equipo Tract. | E12: 50 | F12: =E12/E$5 -> 0.0075757576 | G12: =E12/E$5 -> 0.0075757576
C13: Siniestro Tract. | E13: 150 | F13: =E13/E$5 -> 0.022727273 | G13: =E13/E$5 -> 0.022727273
C14: Cuota PLATAFORMA Enganche | E14: ='DUOTRAILER GASOIL'!E14 -> 565 | F14: =E14/E$5 -> 0.085606061 | G14: =E14/E$5 -> 0.085606061
C15: Seguro Plat | E15: 25 | F15: =E15/E$5 -> 0.0037878788 | G15: =E15/E$5 -> 0.0037878788
C16: Impto circulación Plat | E16: 18 | F16: =E16/E$5 -> 0.0027272727 | G16: =E16/E$5 -> 0.0027272727
C17: Mantenimiento Plataforma + reparación | E17: 125 | F17: =E17/E$5 -> 0.018939394 | G17: =E17/E$5 -> 0.018939394
C18: CUOTA DOLLY | E18: ='DUOTRAILER GASOIL'!E18 -> 200 | F18: =E18/E$5 -> 0.03030303 | G18: =E18/E$5 -> 0.03030303
C19: Seguro Dolly | E19: 25 | F19: =E19/E$5 -> 0.0037878788 | G19: =E19/E$5 -> 0.0037878788
C20: Impuesto Dolly | E20: 18 | F20: =E20/E$5 -> 0.0027272727 | G20: =E20/E$5 -> 0.0027272727
C21: Mantenimiento | E21: 50 | F21: =E21/E$5 -> 0.0075757576 | G21: =E21/E$5 -> 0.0075757576
C22: Cuota PLATAFORMA 2 | E22: ='DUOTRAILER GASOIL'!E22 -> 450 | F22: =E22/E$5 -> 0.068181818 | G22: =E22/E$5 -> 0.068181818
C23: Seguro Plat | E23: 25 | F23: =E23/E$5 -> 0.0037878788 | G23: =E23/E$5 -> 0.0037878788
C24: Impto circulación Plat | E24: 18 | F24: =E24/E$5 -> 0.0027272727 | G24: =E24/E$5 -> 0.0027272727
C25: Mantenimiento Plataforma + reparación | E25: 125 | F25: =E25/E$5 -> 0.018939394 | G25: =E25/E$5 -> 0.018939394
C26: Siniestros | E26: 170 | F26: =E26/E$5 -> 0.025757576 | G26: =E26/E$5 -> 0.025757576
C27: Teléfono | E27: 15 | F27: =E27/E$5 -> 0.0022727273 | G27: =E27/E$5 -> 0.0022727273
C28: PARKING | F28: =E28/E$5 -> 0 | G28: =E28/E$5 -> 0
C29: Reg. Cierre | F29: =E29/E$5 -> 0 | G29: =E29/E$5 -> 0
C30: GASTOS VARIABLES | E30: =SUM(E31:E37) -> 5514.238 | F30: =E30/E5 -> 0.83549061 | G30: =SUM(G31:G37) -> 0.83549061
C31: GASTO PERSONAL | D31: =(2000+85+22*36.06+20+150)*'CALCULADORA COSTES'!B16 -> 3048.32 | E31: ='H2'!E31 -> 3200.4 | F31: =E31/E5 -> 0.48490909 | G31: =E31/E5 -> 0.48490909
F32: =E32/E5 -> 0 | G32: =E32/E5 -> 0
C33: GASOIL (0,8 €/L) | D33: ='CALCULADORA COSTES'!D12 -> 0.29463 | E33: =+D33*E5 -> 1944.558 | F33: =E33/E5 -> 0.29463 | G33: =E33/E5 -> 0.29463
C34: AUTOPISTA | E34: ='CALCULADORA COSTES'!F24*'CALCULADORA COSTES'!F25 -> 0 | F34: =E34/E5 -> 0 | G34: =E34/E5 -> 0
C35: NEUMÁTICOS TRACT.(0,0105€/km) | D35: 0.0102 | E35: =+D35*E5*2 -> 134.64 | F35: =E35/E5 -> 0.0204 | G35: =E35/E5 -> 0.0204
C36: NEUMÁTICOS PLAT. (0,0105€/km) | D36: 0.0102 | E36: =+D36*E5*2 -> 134.64 | F36: =E36/E5 -> 0.0204 | G36: =E36/E5 -> 0.0204
C37: OTROS GASTOS | E37: 100 | F37: =E37/E5 -> 0.015151515 | G37: =E37/E5 -> 0.015151515
C40: COSTE TOTAL | E40: =E30+E6 -> 12361.238 | F40: 1 | G40: =SUM(G30+G6) -> 1.8729148
F41: 0 | G41: 0
C42: Planificación Flota | E42: 275 | F42: =E42/E5 -> 0.041666667 | G42: =E42/E5 -> 0.041666667
C43: margen | D43: 0.04 | E43: =+E40*0.04 -> 494.44952 | F43: =E43/E5 -> 0.074916594 | G43: =E43/E5 -> 0.074916594
C44: Estructura Indirecta | F44: 0 | G44: 0
C45: Estructura General | F45: 0 | G45: 0
C46: COSTE PRODUCTIVO | E46: =E40+SUM(E42:E45) -> 13130.688 | F46: 1 | G46: =SUM(G40:G45) -> 1.9894981
C47: PRECIO INTRAGRUPO TOTAL
C48: PRECIO COSTE €/KM | E48: =G46+E47 -> 1.9894981

Sheet DUOTRAILER BIOMETANO
E2: € | F2: % | G2: €/KM
C3: KMS DIARIOS
C4: KMS ANUALES
C5: KMS mensuales | E5: ='CALCULADORA COSTES'!B14*'CALCULADORA COSTES'!B15 -> 6600
C6: GASTOS FIJOS | E6: =SUM(E7:E29) -> 5247 | F6: =E6/E$5 -> 0.795 | G6: =E6/E$5 -> 0.795
C7: Cuota TRACTORA | E7: ='CALCULADORA COSTES'!E10 -> 2400 | F7: =E7/E$5 -> 0.36363636 | G7: =E7/E$5 -> 0.36363636
C8: Seguro tract. ( a 3os + Propios+seguro mercancias) | E8: 300 | F8: =E8/E$5 -> 0.045454545 | G8: =E8/E$5 -> 0.045454545
C9: Impto circulación Tract. | E9: 18 | F9: =E9/E$5 -> 0.0027272727 | G9: =E9/E$5 -> 0.0027272727
C10: Mantenimiento Tract. | E10: 400 | F10: =E10/E$5 -> 0.060606061 | G10: =E10/E$5 -> 0.060606061
C11: Reparación Tract.+ Equipo | E11: 100 | F11: =E11/E$5 -> 0.015151515 | G11: =E11/E$5 -> 0.015151515
C12: Equipo Tract. | E12: 50 | F12: =E12/E$5 -> 0.0075757576 | G12: =E12/E$5 -> 0.0075757576
C13: Siniestro Tract. | E13: 150 | F13: =E13/E$5 -> 0.022727273 | G13: =E13/E$5 -> 0.022727273
C14: Cuota PLATAFORMA Enganche | E14: ='DUOTRAILER GASOIL'!E14 -> 565 | F14: =E14/E$5 -> 0.085606061 | G14: =E14/E$5 -> 0.085606061
C15: Seguro Plat | E15: 25 | F15: =E15/E$5 -> 0.0037878788 | G15: =E15/E$5 -> 0.0037878788
C16: Impto circulación Plat | E16: 18 | F16: =E16/E$5 -> 0.0027272727 | G16: =E16/E$5 -> 0.0027272727
C17: Mantenimiento Plataforma + reparación | E17: 125 | F17: =E17/E$5 -> 0.018939394 | G17: =E17/E$5 -> 0.018939394
C18: CUOTA DOLLY | E18: ='DUOTRAILER GASOIL'!E18 -> 200 | F18: =E18/E$5 -> 0.03030303 | G18: =E18/E$5 -> 0.03030303
C19: Seguro Dolly | E19: 25 | F19: =E19/E$5 -> 0.0037878788 | G19: =E19/E$5 -> 0.0037878788
C20: Impuesto Dolly | E20: 18 | F20: =E20/E$5 -> 0.0027272727 | G20: =E20/E$5 -> 0.0027272727
C21: Mantenimiento | E21: 50 | F21: =E21/E$5 -> 0.0075757576 | G21: =E21/E$5 -> 0.0075757576
C22: Cuota PLATAFORMA 2 | E22: ='DUOTRAILER GASOIL'!E22 -> 450 | F22: =E22/E$5 -> 0.068181818 | G22: =E22/E$5 -> 0.068181818
C23: Seguro Plat | E23: 25 | F23: =E23/E$5 -> 0.0037878788 | G23: =E23/E$5 -> 0.0037878788
C24: Impto circulación Plat | E24: 18 | F24: =E24/E$5 -> 0.0027272727 | G24: =E24/E$5 -> 0.0027272727
C25: Mantenimiento Plataforma + reparación | E25: 125 | F25: =E25/E$5 -> 0.018939394 | G25: =E25/E$5 -> 0.018939394
C26: Siniestros | E26: 170 | F26: =E26/E$5 -> 0.025757576 | G26: =E26/E$5 -> 0.025757576
C27: Teléfono | E27: 15 | F27: =E27/E$5 -> 0.0022727273 | G27: =E27/E$5 -> 0.0022727273
C28: PARKING | F28: =E28/E$5 -> 0 | G28: =E28/E$5 -> 0
C29: Reg. Cierre | F29: =E29/E$5 -> 0 | G29: =E29/E$5 -> 0
C30: GASTOS VARIABLES | E30: =SUM(E31:E37) -> 7960.528 | F30: =E30/E5 -> 1.2061406 | G30: =SUM(G31:G37) -> 1.2061406
C31: GASTO PERSONAL | D31: =(2000+85+22*36.06+20+150)*'CALCULADORA COSTES'!B16 -> 3048.32 | E31: ='H2'!E31 -> 3200.4 | F31: =E31/E5 -> 0.48490909 | G31: =E31/E5 -> 0.48490909
F32: =E32/E5 -> 0 | G32: =E32/E5 -> 0
C33: Biometano | D33: 1.05 | E33: ='CALCULADORA COSTES'!D10*E5 -> 4390.848 | F33: =E33/E5 -> 0.66528 | G33: =E33/E5 -> 0.66528
C34: AUTOPISTA | E34: ='CALCULADORA COSTES'!F24*'CALCULADORA COSTES'!F25 -> 0 | F34: =E34/E5 -> 0 | G34: =E34/E5 -> 0
C35: NEUMÁTICOS TRACT.(0,0105€/km) | D35: 0.0102 | E35: =+D35*E5*2 -> 134.64 | F35: =E35/E5 -> 0.0204 | G35: =E35/E5 -> 0.0204
C36: NEUMÁTICOS PLAT. (0,0105€/km) | D36: 0.0102 | E36: =+D36*E5*2 -> 134.64 | F36: =E36/E5 -> 0.0204 | G36: =E36/E5 -> 0.0204
C37: OTROS GASTOS | E37: 100 | F37: =E37/E5 -> 0.015151515 | G37: =E37/E5 -> 0.015151515
C40: COSTE TOTAL | E40: =E30+E6 -> 13207.528 | F40: 1 | G40: =SUM(G30+G6) -> 2.0011406
F41: 0 | G41: 0
C42: Planificación Flota | E42: 275 | F42: =E42/E5 -> 0.041666667 | G42: =E42/E5 -> 0.041666667
C43: margen | D43: 0.04 | E43: =+E40*0.04 -> 528.30112 | F43: =E43/E5 -> 0.080045624 | G43: =E43/E5 -> 0.080045624
C44: Estructura Indirecta | F44: 0 | G44: 0
C45: Estructura General | F45: 0 | G45: 0
C46: COSTE PRODUCTIVO | E46: =E40+SUM(E42:E45) -> 14010.829 | F46: 1 | G46: =SUM(G40:G45) -> 2.1228529
C47: PRECIO INTRAGRUPO TOTAL
C48: PRECIO COSTE €/KM | E48: =G46+E47 -> 2.1228529

Sheet GRAFICO
A1: €kg H2 | B1: 1 € | C1: 2 € | D1: 3 € | E1: 4 € | F1: 5 € | G1: 6 € | H1: 7 € | I1: 8 € | J1: 9 € | K1: 10 €
A2: H2 | B2: 0.08 | C2: =$C$2*C1 -> 0.16 | D2: =$C$2*D1 -> 0.24 | E2: =$C$2*E1 -> 0.32 | F2: =$C$2*F1 -> 0.4 | G2: =$C$2*G1 -> 0.48 | H2: =$C$2*H1 -> 0.56 | I2: =$C$2*I1 -> 0.64 | J2: =$C$2*J1 -> 0.72 | K2: =$C$2*K1 -> 0.8
A3: GASOIL 1€ | B3: 0.315 | C3: 0.315 | D3: 0.315 | E3: 0.315 | F3: 0.315 | G3: 0.315 | H3: 0.315 | I3: 0.315 | J3: 0.315 | K3: 0.315
A4: GASOIL 0,9 € | B4: 0.284 | C4: 0.284 | D4: 0.284 | E4: 0.284 | F4: 0.284 | G4: 0.284 | H4: 0.284 | I4: 0.284 | J4: 0.284 | K4: 0.284
A5: Gasoil 0,8 € | B5: 0.252 | C5: 0.252 | D5: 0.252 | E5: 0.252 | F5: 0.252 | G5: 0.252 | H5: 0.252 | I5: 0.252 | J5: 0.252 | K5: 0.252
A6: Biometano | B6: ='CALCULADORA COSTES'!$D$5 -> 0.4752 | C6: ='CALCULADORA COSTES'!$D$5 -> 0.4752 | D6: ='CALCULADORA COSTES'!$D$5 -> 0.4752 | E6: ='CALCULADORA COSTES'!$D$5 -> 0.4752 | F6: ='CALCULADORA COSTES'!$D$5 -> 0.4752 | G6: ='CALCULADORA COSTES'!$D$5 -> 0.4752 | H6: ='CALCULADORA COSTES'!$D$5 -> 0.4752 | I6: ='CALCULADORA COSTES'!$D$5 -> 0.4752 | ... K6: ='CALCULADORA COSTES'!$D$5 -> 0.4752
A7: Gas Natural | B7: ='CALCULADORA COSTES'!$D$3 -> 0.4488 | C7: ='CALCULADORA COSTES'!$D$3 -> 0.4488 | D7: ='CALCULADORA COSTES'!$D$3 -> 0.4488 | E7: ='CALCULADORA COSTES'!$D$3 -> 0.4488 | F7: ='CALCULADORA COSTES'!$D$3 -> 0.4488 | G7: ='CALCULADORA COSTES'!$D$3 -> 0.4488 | H7: ='CALCULADORA COSTES'!$D$3 -> 0.4488 | I7: ='CALCULADORA COSTES'!$D$3 -> 0.4488 | ... K7: ='CALCULADORA COSTES'!$D$3 -> 0.4488
A8: Eléctrico | B8: ='CALCULADORA COSTES'!$D$6 -> 0.4209 | C8: ='CALCULADORA COSTES'!$D$6 -> 0.4209 | D8: ='CALCULADORA COSTES'!$D$6 -> 0.4209 | E8: ='CALCULADORA COSTES'!$D$6 -> 0.4209 | F8: ='CALCULADORA COSTES'!$D$6 -> 0.4209 | G8: ='CALCULADORA COSTES'!$D$6 -> 0.4209 | H8: ='CALCULADORA COSTES'!$D$6 -> 0.4209 | I8: ='CALCULADORA COSTES'!$D$6 -> 0.4209 | ... K8: ='CALCULADORA COSTES'!$D$6 -> 0.4209

Sheet Hoja3
B3: 22 DIAS - 5.000 € | C3: 100 kms/dia | D3: 200 kms/dia | E3: 300 kms/dia | F3: 400 kms/dia | G3: 500 kms/dia | H3: 600 kms/dia | I3: 700 kms/dia | J3: 800 kms/dia | K3: 900 kms/dia | L3: 1000 kms/dia | M3: 1100 kms/dia | N3: 1200 kms/dia | O3: 1300 kms/dia | P3: 1400 kms/dia | R3: 22 DIAS - 7.000 € | S3: 100 kms/day | T3: 200 kms/day | U3: 300 kms/day | V3: 400 kms/day | W3: 500 kms/day | X3: 600 kms/day | Y3: 700 kms/day | Z3: 800 kms/day | AA3: 900 kms/day | AB3: 1000 kms/day | AC3: 1100 kms/day | AD3: 1200 kms/day | AE3: 1300 kms/day | AF3: 1400 kms/day
B4: H2 (10€) | C4: 5.76 | D4: 3.3 | E4: 2.49 | F4: 2.08 | G4: 1.83 | H4: 1.67 | I4: 1.55 | J4: 1.66 | K4: 1.57 | L4: 1.5 | M4: 1.44 | N4: 1.39 | O4: 1.35 | P4: 1.32 | R4: DUO H2 (10€) | S4: 3.85 | T4: 2.26 | U4: 1.73 | V4: 1.46 | W4: 1.3 | X4: 1.2 | Y4: 1.12 | Z4: 1.16 | AA4: 1.11 | AB4: 1.06 | AC4: 1.03 | AD4: 1 | AE4: 0.97 | AF4: 0.95
B5: H2 (9€) | C5: 5.67 | D5: 3.22 | E5: 2.4 | F5: 2 | G5: 1.75 | H5: 1.59 | I5: 1.47 | J5: 1.58 | K5: 1.49 | L5: 1.42 | M5: 1.36 | N5: 1.31 | O5: 1.27 | P5: 1.23 | R5: DUO H2 (9€) | S5: 3.78 | T5: 2.19 | U5: 1.66 | V5: 1.4 | W5: 1.24 | X5: 1.13 | Y5: 1.06 | Z5: 1.1 | AA5: 1.04 | AB5: 1 | AC5: 0.96 | AD5: 0.93 | AE5: 0.91 | AF5: 0.89
B6: H2 (8€) | C6: 5.59 | D6: 3.14 | E6: 2.32 | F6: 1.91 | G6: 1.67 | H6: 1.5 | I6: 1.39 | J6: 1.5 | K6: 1.41 | L6: 1.34 | M6: 1.28 | N6: 1.23 | O6: 1.19 | P6: 1.15 | R6: DUO H2 (8€) | S6: 3.72 | T6: 2.13 | U6: 1.6 | V6: 1.33 | W6: 1.17 | X6: 1.07 | Y6: 0.99 | Z6: 1.07 | AA6: 0.99 | AB6: 0.93 | AC6: 0.9 | AD6: 0.87 | AE6: 0.84 | AF6: 0.82
B7: H2 (7€) | C7: 5.51 | D7: 3.05 | E7: 2.24 | F7: 1.83 | G7: 1.58 | H7: 1.42 | I7: 1.3 | J7: 1.41 | K7: 1.32 | L7: 1.25 | M7: 1.19 | N7: 1.14 | O7: 1.1 | P7: 1.07 | R7: DUO H2 (7€) | S7: 3.66 | T7: 2.06 | U7: 1.53 | V7: 1.27 | W7: 1.11 | X7: 1 | Y7: 0.93 | Z7: 0.97 | AA7: 0.91 | AB7: 0.87 | AC7: 0.83 | AD7: 0.8 | AE7: 0.78 | AF7: 0.76
B8: H2 (6€) | C8: 5.42 | D8: 2.97 | E8: 2.15 | F8: 1.75 | G8: 1.5 | H8: 1.34 | I8: 1.22 | J8: 1.33 | K8: 1.24 | L8: 1.17 | M8: 1.11 | N8: 1.06 | O8: 1.02 | P8: 0.98 | R8: DUO H2 (6€) | S8: 3.59 | T8: 2 | U8: 1.47 | V8: 1.2 | W8: 1.04 | X8: 0.94 | Y8: 0.86 | Z8: 0.9 | AA8: 0.85 | AB8: 0.81 | AC8: 0.77 | AD8: 0.74 | AE8: 0.71 | AF8: 0.69
B9: H2 (5€) | C9: 5.34 | D9: 2.89 | E9: 2.07 | F9: 1.66 | G9: 1.42 | H9: 1.25 | I9: 1.14 | J9: 1.25 | K9: 1.16 | L9: 1.09 | M9: 1.03 | N9: 0.98 | O9: 0.94 | P9: 0.9 | R9: DUO H2 (5€) | S9: 3.53 | T9: 1.93 | U9: 1.4 | V9: 1.14 | W9: 0.98 | X9: 0.87 | Y9: 0.8 | Z9: 0.84 | AA9: 0.79 | AB9: 0.74 | AC9: 0.7 | AD9: 0.67 | AE9: 0.65 | AF9: 0.63
B10: H2 (4€) | C10: 5.26 | D10: 2.81 | E10: 1.99 | F10: 1.58 | G10: 1.33 | H10: 1.17 | I10: 1.05 | J10: 1.16 | K10: 1.07 | L10: 1 | M10: 0.94 | N10: 0.89 | O10: 0.85 | P10: 0.82 | R10: DUO H2 (4€) | S10: 3.46 | T10: 1.87 | U10: 1.34 | V10: 1.07 | W10: 0.92 | X10: 0.81 | Y10: 0.73 | Z10: 0.78 | AA10: 0.72 | AB10: 0.68 | AC10: 0.64 | AD10: 0.61 | AE10: 0.58 | AF10: 0.56
B11: H2 (3€) | C11: 5.17 | D11: 2.72 | E11: 1.9 | F11: 1.5 | G11: 1.25 | H11: 1.09 | I11: 0.97 | J11: 1.08 | K11: 0.99 | L11: 0.92 | M11: 0.86 | N11: 0.81 | O11: 0.77 | P11: 0.73 | R11: DUO H2 (3€) | S11: 3.4 | T11: 1.81 | U11: 1.28 | V11: 1.01 | W11: 0.85 | X11: 0.75 | Y11: 0.67 | Z11: 0.71 | AA11: 0.66 | AB11: 0.61 | AC11: 0.58 | AD11: 0.55 | AE11: 0.52 | AF11: 0.5
B12: H2 (2€) | C12: 5.09 | D12: 2.64 | E12: 1.82 | F12: 1.41 | G12: 1.17 | H12: 1 | I12: 0.89 | J12: 1 | K12: 0.91 | L12: 0.84 | M12: 0.78 | N12: 0.73 | O12: 0.69 | P12: 0.65 | R12: DUO H2 (2€) | S12: 3.33 | T12: 1.74 | U12: 1.21 | V12: 0.95 | W12: 0.79 | X12: 0.68 | Y12: 0.6 | Z12: 0.65 | AA12: 0.59 | AB12: 0.55 | AC12: 0.51 | AD12: 0.48 | AE12: 0.46 | AF12: 0.43
B13: H2 (1€) | C13: 5.01 | D13: 2.56 | E13: 1.74 | F13: 1.33 | G13: 1.08 | H13: 0.92 | I13: 0.8 | J13: 0.92 | K13: 0.82 | L13: 0.75 | M13: 0.69 | N13: 0.64 | O13: 0.6 | P13: 0.57 | R13: DUO H2 (1€) | S13: 3.27 | T13: 1.68 | U13: 1.15 | V13: 0.88 | W13: 0.72 | X13: 0.62 | Y13: 0.54 | Z13: 0.58 | AA13: 0.53 | AB13: 0.48 | AC13: 0.45 | AD13: 0.42 | AE13: 0.39 | AF13: 0.37
B14: GAS NATURAL (0,6 €) | C14: 3.6 | D14: 1.89 | E14: 1.32 | F14: 1.04 | G14: 0.87 | H14: 0.75 | I14: 0.67 | J14: 0.81 | K14: 0.74 | L14: 0.69 | M14: 0.64 | N14: 0.6 | O14: 0.57 | P14: 0.54 | R14: GAS NATURAL (0,6 €) | S14: 3.6 | T14: 1.89 | U14: 1.32 | V14: 1.04 | W14: 0.87 | X14: 0.75 | Y14: 0.67 | Z14: 0.81 | AA14: 0.74 | AB14: 0.69 | AC14: 0.64 | AD14: 0.6 | AE14: 0.57 | AF14: 0.54
B15: GASOIL (1 €) | C15: 3.19 | D15: 1.77 | E15: 1.29 | F15: 1.06 | G15: 0.92 | H15: 0.82 | I15: 0.75 | J15: 0.88 | K15: 0.82 | L15: 0.78 | M15: 0.94 | N15: 0.89 | O15: 0.85 | P15: 0.82 | R15: GASOIL (1 €) | S15: 3.19 | T15: 1.77 | U15: 1.29 | V15: 1.06 | W15: 0.92 | X15: 0.82 | Y15: 0.75 | Z15: 0.88 | AA15: 0.82 | AB15: 0.78 | AC15: 0.94 | AD15: 0.89 | AE15: 0.85 | AF15: 0.82
... B18: BIOMETANO | C18: 3.72 | D18: 2.01 | E18: 1.45 | F18: 1.16 | G18: 0.99 | H18: 0.88 | I18: 0.8 | J18: 0.93 | K18: 0.86 | L18: 0.81 | M18: 0.76 | N18: 0.73 | O18: 0.69 | P18: 0.67 | R18: BIOMETANO | S18: 3.72 | T18: 2.01 | U18: 1.45 | V18: 1.16 | W18: 0.99 | X18: 0.88 | Y18: 0.8 | Z18: 0.93 | AA18: 0.86 | AB18: 0.81 | AC18: 0.76 | AD18: 0.73 | AE18: 0.69 | AF18: 0.67
R19: DUO GASOIL | S19: 2.1 | T19: 1.16 | U19: 0.85 | V19: 0.69 | W19: 0.59 | X19: 0.53 | Y19: 0.49 | Z19: 0.55 | AA19: 0.52 | AB19: 0.49 | AC19: 0.46 | AD19: 0.44 | AE19: 0.42 | AF19: 0.41
B21: 22 D - 5.000 € (G.0,8) | C21: 100 kms/day | D21: 200 kms/day | E21: 300 kms/day | F21: 400 kms/day | G21: 500 kms/day | H21: 600 kms/day | I21: 700 kms/day | J21: 800 kms/day | K21: 900 kms/day | L21: 1000 kms/day | M21: 1100 kms/day | N21: 1200 kms/day | O21: 1300 kms/day | P21: 1400 kms/day | R21: 22 D - 7.000 € (G.0,8) | S21: 100 kms/day | T21: 200 kms/day | U21: 300 kms/day | V21: 400 kms/day | W21: 500 kms/day | X21: 600 kms/day | Y21: 700 kms/day | Z21: 800 kms/day | AA21: 900 kms/day | AB21: 1000 kms/day | AC21: 1100 kms/day | AD21: 1200 kms/day | AE21: 1300 kms/day | AF21: 1400 kms/day
B22: H2 (10€) | C22: 0.84 | D22: 0.94 | E22: 1.02 | F22: 1.09 | G22: 1.16 | H22: 1.21 | I22: 1.26 | J22: 1.03 | K22: 1.07 | L22: 1.11 | M22: 1.15 | N22: 1.18 | O22: 1.21 | P22: 1.24 | R22: DUO H2 (10€) | S22: =S4/S$17-1 -> 0.23397436 | T22: =T4/T$17-1 -> 0.32941176 | U22: =U4/U$17-1 -> 0.40650407 | V22: =V4/V$17-1 -> 0.47474747 | W22: =W4/W$17-1 -> 0.52941176 | X22: =X4/X$17-1 -> 0.57894737 | Y22: =Y4/Y$17-1 -> 0.62318841 | Z22: =Z4/Z$17-1 -> 0.41463415 | ... AF22: =AF4/AF$17-1 -> 0.61016949
B23: H2 (9€) | C23: 0.82 | D23: 0.89 | E23: 0.96 | F23: 1.01 | G23: 1.06 | H23: 1.1 | I23: 1.14 | J23: 0.93 | K23: 0.96 | L23: 0.99 | M23: 1.02 | N23: 1.05 | O23: 1.07 | P23: 1.09 | R23: DUO H2 (9€) | S23: =S5/S$17-1 -> 0.21153846 | T23: =T5/T$17-1 -> 0.28823529 | U23: =U5/U$17-1 -> 0.3495935 | V23: =V5/V$17-1 -> 0.41414141 | W23: =W5/W$17-1 -> 0.45882353 | X23: =X5/X$17-1 -> 0.48684211 | Y23: =Y5/Y$17-1 -> 0.53623188 | Z23: =Z5/Z$17-1 -> 0.34146341 | ... AF23: =AF5/AF$17-1 -> 0.50847458
B24: H2 (8€) | C24: 0.79 | D24: 0.84 | E24: 0.89 | F24: 0.93 | G24: 0.96 | H24: 0.99 | I24: 1.01 | J24: 0.83 | K24: 0.86 | L24: 0.88 | M24: 0.9 | N24: 0.92 | O24: 0.94 | P24: 0.95 | R24: DUO H2 (8€) | S24: =S6/S$17-1 -> 0.19230769 | T24: =T6/T$17-1 -> 0.25294118 | U24: =U6/U$17-1 -> 0.30081301 | V24: =V6/V$17-1 -> 0.34343434 | W24: =W6/W$17-1 -> 0.37647059 | X24: =X6/X$17-1 -> 0.40789474 | Y24: =Y6/Y$17-1 -> 0.43478261 | Z24: =Z6/Z$17-1 -> 0.30487805 | ... AF24: =AF6/AF$17-1 -> 0.38983051
B25: H2 (7€) | C25: 0.76 | D25: 0.8 | E25: 0.82 | F25: 0.84 | G25: 0.86 | H25: 0.88 | I25: 0.89 | J25: 0.73 | K25: 0.75 | L25: 0.76 | M25: 0.77 | N25: 0.79 | O25: 0.8 | P25: 0.81 | R25: DUO H2 (7€) | S25: =S7/S$17-1 -> 0.17307692 | T25: =T7/T$17-1 -> 0.21176471 | U25: =U7/U$17-1 -> 0.24390244 | V25: =V7/V$17-1 -> 0.28282828 | W25: =W7/W$17-1 -> 0.30588235 | X25: =X7/X$17-1 -> 0.31578947 | Y25: =Y7/Y$17-1 -> 0.34782609 | Z25: =Z7/Z$17-1 -> 0.18292683 | ... AF25: =AF7/AF$17-1 -> 0.28813559
B26: H2 (6€) | C26: 0.74 | D26: 0.75 | E26: 0.75 | F26: 0.76 | G26: 0.76 | H26: 0.77 | I26: 0.77 | J26: 0.63 | K26: 0.64 | L26: 0.64 | M26: 0.65 | N26: 0.66 | O26: 0.66 | P26: 0.67 | R26: DUO H2 (6€) | S26: =S8/S$17-1 -> 0.15064103 | T26: =T8/T$17-1 -> 0.17647059 | U26: =U8/U$17-1 -> 0.19512195 | V26: =V8/V$17-1 -> 0.21212121 | W26: =W8/W$17-1 -> 0.22352941 | X26: =X8/X$17-1 -> 0.23684211 | Y26: =Y8/Y$17-1 -> 0.24637681 | Z26: =Z8/Z$17-1 -> 0.097560976 | ... AF26: =AF8/AF$17-1 -> 0.16949153
B27: H2 (5€) | C27: 0.71 | D27: 0.7 | E27: 0.69 | F27: 0.68 | G27: 0.67 | H27: 0.66 | I27: 0.65 | J27: 0.53 | K27: 0.53 | L27: 0.53 | M27: 0.53 | N27: 0.53 | O27: 0.53 | P27: 0.53 | R27: DUO H2 (5€) | S27: =S9/S$17-1 -> 0.13141026 | T27: =T9/T$17-1 -> 0.13529412 | U27: =U9/U$17-1 -> 0.13821138 | V27: =V9/V$17-1 -> 0.15151515 | W27: =W9/W$17-1 -> 0.15294118 | X27: =X9/X$17-1 -> 0.14473684 | Y27: =Y9/Y$17-1 -> 0.15942029 | Z27: =Z9/Z$17-1 -> 0.024390244 | ... AF27: =AF9/AF$17-1 -> 0.06779661
B28: H2 (4€) | C28: 0.68 | D28: 0.65 | E28: 0.62 | F28: 0.59 | G28: 0.57 | H28: 0.55 | I28: 0.53 | J28: 0.42 | K28: 0.42 | L28: 0.41 | M28: 0.4 | N28: 0.4 | O28: 0.39 | P28: 0.39 | R28: DUO H2 (4€) | S28: =S10/S$17-1 -> 0.10897436 | T28: =T10/T$17-1 -> 0.1 | U28: =U10/U$17-1 -> 0.089430894 | V28: =V10/V$17-1 -> 0.080808081 | W28: =W10/W$17-1 -> 0.082352941 | X28: =X10/X$17-1 -> 0.065789474 | Y28: =Y10/Y$17-1 -> 0.057971014 | Z28: =Z10/Z$17-1 -> -0.048780488 | ... AF28: =AF10/AF$17-1 -> -0.050847458
B29: H2 (3€) | C29: 0.66 | D29: 0.6 | E29: 0.55 | F29: 0.51 | G29: 0.47 | H29: 0.44 | I29: 0.41 | J29: 0.32 | K29: 0.31 | L29: 0.29 | M29: 0.28 | N29: 0.27 | O29: 0.26 | P29: 0.25 | R29: DUO H2 (3€) | S29: =S11/S$17-1 -> 0.08974359 | T29: =T11/T$17-1 -> 0.064705882 | U29: =U11/U$17-1 -> 0.040650407 | V29: =V11/V$17-1 -> 0.02020202 | W29: =W11/W$17-1 -> 0 | X29: =X11/X$17-1 -> -0.013157895 | Y29: =Y11/Y$17-1 -> -0.028985507 | Z29: =Z11/Z$17-1 -> -0.13414634 | ... AF29: =AF11/AF$17-1 -> -0.15254237
B30: H2 (2€) | C30: 0.63 | D30: 0.55 | E30: 0.42 | F30: 0.42 | G30: 0.37 | H30: 0.33 | I30: 0.29 | J30: 0.22 | K30: 0.2 | L30: 0.18 | M30: 0.16 | N30: 0.14 | O30: 0.12 | P30: 0.1 | R30: DUO H2 (2€) | S30: =S12/S$17-1 -> 0.067307692 | T30: =T12/T$17-1 -> 0.023529412 | U30: =U12/U$17-1 -> -0.016260163 | V30: =V12/V$17-1 -> -0.04040404 | W30: =W12/W$17-1 -> -0.070588235 | X30: =X12/X$17-1 -> -0.10526316 | Y30: =Y12/Y$17-1 -> -0.13043478 | Z30: =Z12/Z$17-1 -> -0.20731707 | ... AF30: =AF12/AF$17-1 -> -0.27118644
B31: H2 (1€) | C31: 0.6 | D31: 0.5 | E31: 0.41 | F31: 0.34 | G31: 0.28 | H31: 0.22 | I31: 0.17 | J31: 0.12 | K31: 0.09 | L31: 0.06 | M31: 0.03 | N31: 0.01 | O31: -0.02 | P31: -0.04 | R31: DUO H2 (1€) | S31: =S13/S$17-1 -> 0.048076923 | T31: =T13/T$17-1 -> -0.011764706 | U31: =U13/U$17-1 -> -0.06504065 | V31: =V13/V$17-1 -> -0.11111111 | W31: =W13/W$17-1 -> -0.15294118 | X31: =X13/X$17-1 -> -0.18421053 | Y31: =Y13/Y$17-1 -> -0.2173913 | Z31: =Z13/Z$17-1 -> -0.29268293 | ... AF31: =AF13/AF$17-1 -> -0.37288136
B32: GAS NATURAL (0,6 €) | C32: 0.15 | D32: 0.11 | E32: 0.08 | F32: 0.05 | G32: 0.02 | H32: 0 | I32: -0.02 | J32: -0.01 | K32: -0.02 | L32: -0.04 | M32: -0.05 | N32: -0.06 | O32: -0.07 | P32: -0.08 | R32: GAS NATURAL (0,6 €) | S32: 0.15 | T32: 0.11 | U32: 0.08 | V32: 0.05 | W32: 0.02 | X32: 0 | Y32: -0.02 | Z32: -0.01 | AA32: -0.02 | AB32: -0.04 | AC32: -0.05 | AD32: -0.06 | AE32: -0.07 | AF32: -0.08
B33: GASOIL (0,8 €) | C33: 0 | D33: 0 | E33: 0 | F33: 0 | G33: 0 | H33: 0 | I33: 0 | J33: 0 | K33: 0 | L33: 0 | M33: 0 | N33: 0 | O33: 0 | P33: 0 | R33: GASOIL (0,8 €) | S33: 0 | T33: 0 | U33: 0 | V33: 0 | W33: 0 | X33: 0 | Y33: 0 | Z33: 0 | AA33: 0 | AB33: 0 | AC33: 0 | AD33: 0 | AE33: 0 | AF33: 0
B34: BIOMETANO | C34: =C18/C17-1 -> 0.19230769 | D34: =D18/D17-1 -> 0.18235294 | E34: =E18/E17-1 -> 0.17886179 | F34: =F18/F17-1 -> 0.17171717 | G34: =G18/G17-1 -> 0.16470588 | H34: =H18/H17-1 -> 0.15789474 | I34: =I18/I17-1 -> 0.15942029 | J34: 0.19 | K34: 0.19 | L34: =L18/L17-1 -> 0.14084507 | M34: 0.2 | N34: =N18/N17-1 -> 0.140625 | O34: =O18/O17-1 -> 0.13114754 | P34: =P18/P17-1 -> 0.13559322 | R34: BIOMETANO | S34: =S18/S17-1 -> 0.19230769 | T34: =T18/T17-1 -> 0.18235294 | U34: =U18/U17-1 -> 0.17886179 | V34: =V18/V17-1 -> 0.17171717 | W34: =W18/W17-1 -> 0.16470588 | X34: =X18/X17-1 -> 0.15789474 | Y34: =Y18/Y17-1 -> 0.15942029 | Z34: 0.19 | AA34: 0.19 | AB34: =AB18/AB17-1 -> 0.14084507 | AC34: 0.2 | AD34: =AD18/AD17-1 -> 0.140625 | AE34: =AE18/AE17-1 -> 0.13114754 | AF34: =AF18/AF17-1 -> 0.13559322
R35: DUO GASOIL | S35: =S19/S15-1 -> -0.34169279 | T35: =T19/T17-1 -> -0.31764706 | U35: =U19/U17-1 -> -0.30894309 | V35: =V19/V17-1 -> -0.3030303 | W35: =W19/W17-1 -> -0.30588235 | X35: =X19/X17-1 -> -0.30263158 | Y35: =Y19/Y17-1 -> -0.28985507 | Z35: =Z19/Z17-1 -> -0.32926829 | AA35: =AA19/AA17-1 -> -0.31578947 | ... AF35: =AF19/AF17-1 -> -0.30508475
B37: 22 D - 5.000 € (G.0,9) | C37: 100 kms/dia | D37: 200 kms/dia | E37: 300 kms/dia | F37: 400 kms/dia | G37: 500 kms/dia | H37: 600 kms/dia | I37: 700 kms/dia | J37: 800 kms/dia | K37: 900 kms/dia | L37: 1000 kms/dia | M37: 1100 kms/dia | N37: 1200 kms/dia | O37: 1300 kms/dia | P37: 1400 kms/dia | R37: 22 DIAS - 5.000 € | S37: 100 kms/dia | T37: 200 kms/dia | U37: 300 kms/dia | V37: 400 kms/dia | W37: 500 kms/dia | X37: 600 kms/dia | Y37: 700 kms/dia | Z37: 800 kms/dia | AA37: 900 kms/dia | AB37: 1000 kms/dia | AC37: 1100 kms/dia | AD37: 1200 kms/dia | AE37: 1300 kms/dia | AF37: 1400 kms/dia
B38: H2 (10€) | C38: =C4/C$16-1 -> 0.82857143 | D38: =D4/D$16-1 -> 0.90751445 | E38: =E4/E$16-1 -> 0.97619048 | F38: =F4/F$16-1 -> 1.0194175 | G38: =G4/G$16-1 -> 1.0795455 | H38: =H4/H$16-1 -> 1.1139241 | I38: =I4/I$16-1 -> 1.1527778 | J38: =J4/J$16-1 -> 0.95294118 | ... P38: =P4/P$16-1 -> 1.1290323 | R38: DUO H2 (10€) | S38: 3.38 | T38: 2.02 | U38: 1.57 | V38: 1.34 | W38: 1.21 | X38: 1.12 | Y38: 1.05 | Z38: 1.1 | AA38: 1.06 | AB38: 1.02 | AC38: 0.98 | AD38: 0.96 | AE38: 0.94 | AF38: 0.92
B39: H2 (9€) | C39: =C5/C$16-1 -> 0.8 | D39: =D5/D$16-1 -> 0.86127168 | E39: =E5/E$16-1 -> 0.9047619 | F39: =F5/F$16-1 -> 0.94174757 | G39: =G5/G$16-1 -> 0.98863636 | H39: =H5/H$16-1 -> 1.0126582 | I39: =I5/I$16-1 -> 1.0416667 | J39: =J5/J$16-1 -> 0.85882353 | ... P39: =P5/P$16-1 -> 0.98387097 | R39: DUO H2 (9€) | S39: 3.31 | T39: 1.96 | U39: 1.5 | V39: 1.28 | W39: 1.14 | X39: 1.05 | Y39: 0.99 | Z39: 1.04 | AA39: 0.99 | AB39: 0.95 | AC39: 0.92 | AD39: 0.89 | AE39: 0.87 | AF39: 0.85
B40: H2 (8€) | C40: =C6/C$16-1 -> 0.77460317 | D40: =D6/D$16-1 -> 0.8150289 | E40: =E6/E$16-1 -> 0.84126984 | F40: =F6/F$16-1 -> 0.85436893 | G40: =G6/G$16-1 -> 0.89772727 | H40: =H6/H$16-1 -> 0.89873418 | I40: =I6/I$16-1 -> 0.93055556 | J40: =J6/J$16-1 -> 0.76470588 | ... P40: =P6/P$16-1 -> 0.85483871 | R40: DUO H2 (8€) | S40: 3.25 | T40: 1.89 | U40: 1.44 | V40: 1.21 | W40: 1.08 | X40: 0.99 | Y40: 0.92 | Z40: 0.97 | AA40: 0.93 | AB40: 0.89 | AC40: 0.86 | AD40: 0.83 | AE40: 0.81 | AF40: 0.79
B41: H2 (7€) | C41: =C7/C$16-1 -> 0.74920635 | D41: =D7/D$16-1 -> 0.76300578 | E41: =E7/E$16-1 -> 0.77777778 | F41: =F7/F$16-1 -> 0.77669903 | G41: =G7/G$16-1 -> 0.79545455 | H41: =H7/H$16-1 -> 0.79746835 | I41: =I7/I$16-1 -> 0.80555556 | J41: =J7/J$16-1 -> 0.65882353 | ... P41: =P7/P$16-1 -> 0.72580645 | R41: DUO H2 (7€) | S41: 3.18 | T41: 1.83 | U41: 1.38 | V41: 1.15 | W41: 1.01 | X41: 0.92 | Y41: 0.86 | Z41: 0.91 | AA41: 0.86 | AB41: 0.82 | AC41: 0.79 | AD41: 0.76 | AE41: 0.74 | AF41: 0.72
B42: H2 (6€) | C42: =C8/C$16-1 -> 0.72063492 | D42: =D8/D$16-1 -> 0.71676301 | E42: =E8/E$16-1 -> 0.70634921 | F42: =F8/F$16-1 -> 0.69902913 | G42: =G8/G$16-1 -> 0.70454545 | H42: =H8/H$16-1 -> 0.69620253 | I42: =I8/I$16-1 -> 0.69444444 | J42: =J8/J$16-1 -> 0.56470588 | ... P42: =P8/P$16-1 -> 0.58064516 | R42: DUO H2 (6€) | S42: 3.12 | T42: 1.76 | U42: 1.31 | V42: 1.09 | W42: 0.95 | X42: 0.86 | Y42: 0.8 | Z42: 0.85 | AA42: 0.8 | AB42: 0.76 | AC42: 0.73 | AD42: 0.7 | AE42: 0.68 | AF42: 0.66
B43: H2 (5€) | C43: =C9/C$16-1 -> 0.6952381 | D43: =D9/D$16-1 -> 0.67052023 | E43: =E9/E$16-1 -> 0.64285714 | F43: =F9/F$16-1 -> 0.61165049 | G43: =G9/G$16-1 -> 0.61363636 | H43: =H9/H$16-1 -> 0.58227848 | I43: =I9/I$16-1 -> 0.58333333 | J43: =J9/J$16-1 -> 0.47058824 | ... P43: =P9/P$16-1 -> 0.4516129 | R43: DUO H2 (5€) | S43: 3.05 | T43: 1.7 | U43: 1.25 | V43: 1.02 | W43: 0.89 | X43: 0.8 | Y43: 0.73 | Z43: 0.78 | AA43: 0.73 | AB43: 0.69 | AC43: 0.66 | AD43: 0.64 | AE43: 0.61 | AF43: 0.59
B44: H2 (4€) | C44: =C10/C$16-1 -> 0.66984127 | D44: =D10/D$16-1 -> 0.62427746 | E44: =E10/E$16-1 -> 0.57936508 | F44: =F10/F$16-1 -> 0.53398058 | G44: =G10/G$16-1 -> 0.51136364 | H44: =H10/H$16-1 -> 0.48101266 | I44: =I10/I$16-1 -> 0.45833333 | J44: =J10/J$16-1 -> 0.36470588 | ... P44: =P10/P$16-1 -> 0.32258065 | R44: DUO H2 (4€) | S44: 2.99 | T44: 1.63 | U44: 1.18 | V44: 0.96 | W44: 0.82 | X44: 0.73 | Y44: 0.67 | Z44: 0.72 | AA44: 0.67 | AB44: 0.63 | AC44: 0.6 | AD44: 0.57 | AE44: 0.55 | AF44: 0.53
B45: H2 (3€) | C45: =C11/C$16-1 -> 0.64126984 | D45: =D11/D$16-1 -> 0.57225434 | E45: =E11/E$16-1 -> 0.50793651 | F45: =F11/F$16-1 -> 0.45631068 | G45: =G11/G$16-1 -> 0.42045455 | H45: =H11/H$16-1 -> 0.37974684 | I45: =I11/I$16-1 -> 0.34722222 | J45: =J11/J$16-1 -> 0.27058824 | ... P45: =P11/P$16-1 -> 0.17741935 | R45: DUO H2 (3€) | S45: 2.92 | T45: 1.57 | U45: 1.12 | V45: 0.89 | W45: 0.76 | X45: 0.67 | Y45: 0.6 | Z45: 0.65 | AA45: 0.6 | AB45: 0.56 | AC45: 0.53 | AD45: 0.51 | AE45: 0.48 | AF45: 0.46
B46: H2 (2€) | C46: =C12/C$16-1 -> 0.61587302 | D46: =D12/D$16-1 -> 0.52601156 | E46: =E12/E$16-1 -> 0.44444444 | F46: =F12/F$16-1 -> 0.36893204 | G46: =G12/G$16-1 -> 0.32954545 | H46: =H12/H$16-1 -> 0.26582278 | I46: =I12/I$16-1 -> 0.23611111 | J46: =J12/J$16-1 -> 0.17647059 | ... P46: =P12/P$16-1 -> 0.048387097 | R46: DUO H2 (2€) | S46: 2.86 | T46: 1.51 | U46: 1.05 | V46: 0.83 | W46: 0.69 | X46: 0.6 | Y46: 0.54 | Z46: 0.59 | AA46: 0.54 | AB46: 0.5 | AC46: 0.47 | AD46: 0.44 | AE46: 0.42 | AF46: 0.4
B47: H2 (1€) | C47: =C13/C$16-1 -> 0.59047619 | D47: =D13/D$16-1 -> 0.47976879 | E47: =E13/E$16-1 -> 0.38095238 | F47: =F13/F$16-1 -> 0.29126214 | G47: =G13/G$16-1 -> 0.22727273 | H47: =H13/H$16-1 -> 0.16455696 | I47: =I13/I$16-1 -> 0.11111111 | J47: =J13/J$16-1 -> 0.082352941 | ... P47: =P13/P$16-1 -> -0.080645161 | R47: DUO H2 (1€) | S47: 2.8 | T47: 1.44 | U47: 0.99 | V47: 0.76 | W47: 0.63 | X47: 0.54 | Y47: 0.47 | Z47: 0.52 | AA47: 0.47 | AB47: 0.44 | AC47: 0.4 | AD47: 0.38 | AE47: 0.36 | AF47: 0.34
B48: GAS NATURAL (0,6 €) | C48: =C14/C$16-1 -> 0.14285714 | D48: =D14/D$16-1 -> 0.092485549 | E48: =E14/E$16-1 -> 0.047619048 | F48: =F14/F$16-1 -> 0.0097087379 | G48: =G14/G$16-1 -> -0.011363636 | H48: =H14/H$16-1 -> -0.050632911 | I48: =I14/I$16-1 -> -0.069444444 | J48: =J14/J$16-1 -> -0.047058824 | ... P48: =P14/P$16-1 -> -0.12903226 | R48: GAS NATURAL (0,6 €) | S48: 3.6 | T48: 1.89 | U48: 1.32 | V48: 1.04 | W48: 0.87 | X48: 0.75 | Y48: 0.67 | Z48: 0.81 | AA48: 0.74 | AB48: 0.69 | AC48: 0.64 | AD48: 0.6 | AE48: 0.57 | AF48: 0.54
B49: GASOIL (0,9 €) | C49: =C17/C$17-1 -> 0 | D49: =D17/D$17-1 -> 0 | E49: =E17/E$17-1 -> 0 | F49: =F17/F$17-1 -> 0 | G49: =G17/G$17-1 -> 0 | H49: =H17/H$17-1 -> 0 | I49: =I17/I$17-1 -> 0 | J49: =J17/J$17-1 -> 0 | ... P49: =P17/P$17-1 -> 0 | R49: GASOIL (0,8 €) | S49: 3.12 | T49: 1.7 | U49: 1.23 | V49: 0.99 | W49: 0.85 | X49: 0.76 | Y49: 0.69 | Z49: 0.82 | AA49: 0.76 | AB49: 0.71 | AC49: 0.67 | AD49: 0.64 | AE49: 0.61 | AF49: 0.59
B50: BIOMETANO | C50: =C18/C$17-1 -> 0.19230769 | D50: =D18/D$17-1 -> 0.18235294 | E50: =E18/E$17-1 -> 0.17886179 | F50: =F18/F$17-1 -> 0.17171717 | G50: =G18/G$17-1 -> 0.16470588 | H50: =H18/H$17-1 -> 0.15789474 | I50: =I18/I$17-1 -> 0.15942029 | J50: =J18/J$17-1 -> 0.13414634 | ... P50: =P18/P$17-1 -> 0.13559322 | R50: BIOMETANO | S50: 3.72 | T50: 2.01 | U50: 1.45 | V50: 1.16 | W50: 0.99 | X50: 0.88 | Y50: 0.8 | Z50: 0.93 | AA50: 0.86 | AB50: 0.81 | AC50: 0.76 | AD50: 0.73 | AE50: 0.69 | AF50: 0.67
B53: 22 D - 5.000 € (G.1) | C53: 100 kms/dia | D53: 200 kms/dia | E53: 300 kms/dia | F53: 400 kms/dia | G53: 500 kms/dia | H53: 600 kms/dia | I53: 700 kms/dia | J53: 800 kms/dia | K53: 900 kms/dia | L53: 1000 kms/dia | M53: 1100 kms/dia | N53: 1200 kms/dia | O53: 1300 kms/dia | P53: 1400 kms/dia | R53: 22 D - 5.000 € (G.0,8) | S53: 100 kms/dia | T53: 200 kms/dia | U53: 300 kms/dia | V53: 400 kms/dia | W53: 500 kms/dia | X53: 600 kms/dia | Y53: 700 kms/dia | Z53: 800 kms/dia | AA53: 900 kms/dia | AB53: 1000 kms/dia | AC53: 1100 kms/dia | AD53: 1200 kms/dia | AE53: 1300 kms/dia | AF53: 1400 kms/dia
B54: H2 (10€) | C54: =C4/C$15-1 -> 0.80564263 | D54: =D4/D$15-1 -> 0.86440678 | E54: =E4/E$15-1 -> 0.93023256 | F54: =F4/F$15-1 -> 0.96226415 | G54: =G4/G$15-1 -> 0.98913043 | H54: =H4/H$15-1 -> 1.0365854 | I54: =I4/I$15-1 -> 1.0666667 | J54: =J4/J$15-1 -> 0.88636364 | ... P54: =P4/P$15-1 -> 0.6097561 | R54: H2 (10€) | S54: =S38/S$17-1 -> 0.083333333 | T54: =T38/T$17-1 -> 0.18823529 | U54: =U38/U$17-1 -> 0.27642276 | V54: =V38/V$17-1 -> 0.35353535 | W54: =W38/W$17-1 -> 0.42352941 | X54: =X38/X$17-1 -> 0.47368421 | Y54: =Y38/Y$17-1 -> 0.52173913 | Z54: =Z38/Z$17-1 -> 0.34146341 | ... AF54: =AF38/AF$17-1 -> 0.55932203
B55: H2 (9€) | C55: =C5/C$15-1 -> 0.77742947 | D55: =D5/D$15-1 -> 0.81920904 | E55: =E5/E$15-1 -> 0.86046512 | F55: =F5/F$15-1 -> 0.88679245 | G55: =G5/G$15-1 -> 0.90217391 | H55: =H5/H$15-1 -> 0.93902439 | I55: =I5/I$15-1 -> 0.96 | J55: =J5/J$15-1 -> 0.79545455 | ... P55: =P5/P$15-1 -> 0.5 | R55: H2 (9€) | S55: =S39/S$17-1 -> 0.060897436 | T55: =T39/T$17-1 -> 0.15294118 | U55: =U39/U$17-1 -> 0.2195122 | V55: =V39/V$17-1 -> 0.29292929 | W55: =W39/W$17-1 -> 0.34117647 | X55: =X39/X$17-1 -> 0.38157895 | Y55: =Y39/Y$17-1 -> 0.43478261 | Z55: =Z39/Z$17-1 -> 0.26829268 | ... AF55: =AF39/AF$17-1 -> 0.44067797
B56: H2 (8€) | C56: =C6/C$15-1 -> 0.7523511 | D56: =D6/D$15-1 -> 0.7740113 | E56: =E6/E$15-1 -> 0.79844961 | F56: =F6/F$15-1 -> 0.80188679 | G56: =G6/G$15-1 -> 0.81521739 | H56: =H6/H$15-1 -> 0.82926829 | I56: =I6/I$15-1 -> 0.85333333 | J56: =J6/J$15-1 -> 0.70454545 | ... P56: =P6/P$15-1 -> 0.40243902 | R56: H2 (8€) | S56: =S40/S$17-1 -> 0.041666667 | T56: =T40/T$17-1 -> 0.11176471 | U56: =U40/U$17-1 -> 0.17073171 | V56: =V40/V$17-1 -> 0.22222222 | W56: =W40/W$17-1 -> 0.27058824 | X56: =X40/X$17-1 -> 0.30263158 | Y56: =Y40/Y$17-1 -> 0.33333333 | Z56: =Z40/Z$17-1 -> 0.18292683 | ... AF56: =AF40/AF$17-1 -> 0.33898305
B57: H2 (7€) | C57: =C7/C$15-1 -> 0.72727273 | D57: =D7/D$15-1 -> 0.72316384 | E57: =E7/E$15-1 -> 0.73643411 | F57: =F7/F$15-1 -> 0.72641509 | G57: =G7/G$15-1 -> 0.7173913 | H57: =H7/H$15-1 -> 0.73170732 | I57: =I7/I$15-1 -> 0.73333333 | J57: =J7/J$15-1 -> 0.60227273 | ... P57: =P7/P$15-1 -> 0.30487805 | R57: H2 (7€) | S57: =S41/S$17-1 -> 0.019230769 | T57: =T41/T$17-1 -> 0.076470588 | U57: =U41/U$17-1 -> 0.12195122 | V57: =V41/V$17-1 -> 0.16161616 | W57: =W41/W$17-1 -> 0.18823529 | X57: =X41/X$17-1 -> 0.21052632 | Y57: =Y41/Y$17-1 -> 0.24637681 | Z57: =Z41/Z$17-1 -> 0.1097561 | ... AF57: =AF41/AF$17-1 -> 0.22033898
B58: H2 (6€) | C58: =C8/C$15-1 -> 0.69905956 | D58: =D8/D$15-1 -> 0.6779661 | E58: =E8/E$15-1 -> 0.66666667 | F58: =F8/F$15-1 -> 0.6509434 | G58: =G8/G$15-1 -> 0.63043478 | H58: =H8/H$15-1 -> 0.63414634 | I58: =I8/I$15-1 -> 0.62666667 | J58: =J8/J$15-1 -> 0.51136364 | ... P58: =P8/P$15-1 -> 0.19512195 | R58: H2 (6€) | S58: =S42/S$17-1 -> 0 | T58: =T42/T$17-1 -> 0.035294118 | U58: =U42/U$17-1 -> 0.06504065 | V58: =V42/V$17-1 -> 0.1010101 | W58: =W42/W$17-1 -> 0.11764706 | X58: =X42/X$17-1 -> 0.13157895 | Y58: =Y42/Y$17-1 -> 0.15942029 | Z58: =Z42/Z$17-1 -> 0.036585366 | ... AF58: =AF42/AF$17-1 -> 0.11864407
B59: H2 (5€) | C59: =C9/C$15-1 -> 0.67398119 | D59: =D9/D$15-1 -> 0.63276836 | E59: =E9/E$15-1 -> 0.60465116 | F59: =F9/F$15-1 -> 0.56603774 | G59: =G9/G$15-1 -> 0.54347826 | H59: =H9/H$15-1 -> 0.52439024 | I59: =I9/I$15-1 -> 0.52 | J59: =J9/J$15-1 -> 0.42045455 | ... P59: =P9/P$15-1 -> 0.097560976 | R59: H2 (5€) | S59: =S43/S$17-1 -> -0.022435897 | T59: =T43/T$17-1 -> 0 | U59: =U43/U$17-1 -> 0.016260163 | V59: =V43/V$17-1 -> 0.03030303 | W59: =W43/W$17-1 -> 0.047058824 | X59: =X43/X$17-1 -> 0.052631579 | Y59: =Y43/Y$17-1 -> 0.057971014 | Z59: =Z43/Z$17-1 -> -0.048780488 | ... AF59: =AF43/AF$17-1 -> 0
B60: H2 (4€) | C60: =C10/C$15-1 -> 0.64890282 | D60: =D10/D$15-1 -> 0.58757062 | E60: =E10/E$15-1 -> 0.54263566 | F60: =F10/F$15-1 -> 0.49056604 | G60: =G10/G$15-1 -> 0.44565217 | H60: =H10/H$15-1 -> 0.42682927 | I60: =I10/I$15-1 -> 0.4 | J60: =J10/J$15-1 -> 0.31818182 | ... P60: =P10/P$15-1 -> 0 | R60: H2 (4€) | S60: =S44/S$17-1 -> -0.041666667 | T60: =T44/T$17-1 -> -0.041176471 | U60: =U44/U$17-1 -> -0.040650407 | V60: =V44/V$17-1 -> -0.03030303 | W60: =W44/W$17-1 -> -0.035294118 | X60: =X44/X$17-1 -> -0.039473684 | Y60: =Y44/Y$17-1 -> -0.028985507 | Z60: =Z44/Z$17-1 -> -0.12195122 | ... AF60: =AF44/AF$17-1 -> -0.10169492
B61: H2 (3€) | C61: =C11/C$15-1 -> 0.62068966 | D61: =D11/D$15-1 -> 0.53672316 | E61: =E11/E$15-1 -> 0.47286822 | F61: =F11/F$15-1 -> 0.41509434 | G61: =G11/G$15-1 -> 0.35869565 | H61: =H11/H$15-1 -> 0.32926829 | I61: =I11/I$15-1 -> 0.29333333 | J61: =J11/J$15-1 -> 0.22727273 | ... P61: =P11/P$15-1 -> -0.1097561 | R61: H2 (3€) | S61: =S45/S$17-1 -> -0.064102564 | T61: =T45/T$17-1 -> -0.076470588 | U61: =U45/U$17-1 -> -0.089430894 | V61: =V45/V$17-1 -> -0.1010101 | W61: =W45/W$17-1 -> -0.10588235 | X61: =X45/X$17-1 -> -0.11842105 | Y61: =Y45/Y$17-1 -> -0.13043478 | Z61: =Z45/Z$17-1 -> -0.20731707 | ... AF61: =AF45/AF$17-1 -> -0.22033898
B62: H2 (2€) | C62: =C12/C$15-1 -> 0.59561129 | D62: =D12/D$15-1 -> 0.49152542 | E62: =E12/E$15-1 -> 0.41085271 | F62: =F12/F$15-1 -> 0.33018868 | G62: =G12/G$15-1 -> 0.27173913 | H62: =H12/H$15-1 -> 0.2195122 | I62: =I12/I$15-1 -> 0.18666667 | J62: =J12/J$15-1 -> 0.13636364 | ... P62: =P12/P$15-1 -> -0.20731707 | R62: H2 (2€) | S62: =S46/S$17-1 -> -0.083333333 | T62: =T46/T$17-1 -> -0.11176471 | U62: =U46/U$17-1 -> -0.14634146 | V62: =V46/V$17-1 -> -0.16161616 | W62: =W46/W$17-1 -> -0.18823529 | X62: =X46/X$17-1 -> -0.21052632 | Y62: =Y46/Y$17-1 -> -0.2173913 | Z62: =Z46/Z$17-1 -> -0.2804878 | ... AF62: =AF46/AF$17-1 -> -0.3220339
B63: H2 (1€) | C63: =C13/C$15-1 -> 0.57053292 | D63: =D13/D$15-1 -> 0.44632768 | E63: =E13/E$15-1 -> 0.34883721 | F63: =F13/F$15-1 -> 0.25471698 | G63: =G13/G$15-1 -> 0.17391304 | H63: =H13/H$15-1 -> 0.12195122 | I63: =I13/I$15-1 -> 0.066666667 | J63: =J13/J$15-1 -> 0.045454545 | ... P63: =P13/P$15-1 -> -0.30487805 | R63: H2 (1€) | S63: =S47/S$17-1 -> -0.1025641 | T63: =T47/T$17-1 -> -0.15294118 | U63: =U47/U$17-1 -> -0.19512195 | V63: =V47/V$17-1 -> -0.23232323 | W63: =W47/W$17-1 -> -0.25882353 | X63: =X47/X$17-1 -> -0.28947368 | Y63: =Y47/Y$17-1 -> -0.31884058 | Z63: =Z47/Z$17-1 -> -0.36585366 | ... AF63: =AF47/AF$17-1 -> -0.42372881
B64: GAS NATURAL (0,6 €) | C64: =C14/C$15-1 -> 0.12852665 | D64: =D14/D$15-1 -> 0.06779661 | E64: =E14/E$15-1 -> 0.023255814 | F64: =F14/F$15-1 -> -0.018867925 | G64: =G14/G$15-1 -> -0.054347826 | H64: =H14/H$15-1 -> -0.085365854 | I64: =I14/I$15-1 -> -0.10666667 | J64: =J14/J$15-1 -> -0.079545455 | ... P64: =P14/P$15-1 -> -0.34146341 | R64: GAS NATURAL (0,6 €) | S64: 0.15 | T64: 0.11 | U64: 0.08 | V64: 0.05 | W64: 0.02 | X64: 0 | Y64: -0.02 | Z64: -0.01 | AA64: -0.02 | AB64: -0.04 | AC64: -0.05 | AD64: -0.06 | AE64: -0.07 | AF64: -0.08
B65: GASOIL (1 €) | C65: =C15/C$15-1 -> 0 | D65: =D15/D$15-1 -> 0 | E65: =E15/E$15-1 -> 0 | F65: =F15/F$15-1 -> 0 | G65: =G15/G$15-1 -> 0 | H65: =H15/H$15-1 -> 0 | I65: =I15/I$15-1 -> 0 | J65: =J15/J$15-1 -> 0 | ... P65: =P15/P$15-1 -> 0 | R65: GASOIL (0,8 €) | S65: 0 | T65: 0 | U65: 0 | V65: 0 | W65: 0 | X65: 0 | Y65: 0 | Z65: 0 | AA65: 0 | AB65: 0 | AC65: 0 | AD65: 0 | AE65: 0 | AF65: 0
B66: BIOMETANO | C66: =C16/C$15-1 -> -0.012539185 | D66: =D18/D$15-1 -> 0.13559322 | E66: =E18/E$15-1 -> 0.12403101 | F66: =F16/F$15-1 -> -0.028301887 | G66: =G18/G$15-1 -> 0.076086957 | H66: =H18/H$15-1 -> 0.073170732 | I66: =I18/I$15-1 -> 0.066666667 | J66: =J18/J$15-1 -> 0.056818182 | K66: =K18/K$15-1 -> 0.048780488 | L66: =L18/L$15-1 -> 0.038461538 | M66: =M18/M$15-1 -> -0.19148936 | N66: =N18/N$15-1 -> -0.17977528 | ... P66: =P18/P$15-1 -> -0.18292683 | R66: BIOMETANO | S66: =S50/S49-1 -> 0.19230769 | T66: =T50/T49-1 -> 0.18235294 | U66: =U50/U49-1 -> 0.17886179 | V66: =V50/V49-1 -> 0.17171717 | W66: =W50/W49-1 -> 0.16470588 | X66: =X50/X49-1 -> 0.15789474 | Y66: =Y50/Y49-1 -> 0.15942029 | Z66: 0.19 | AA66: 0.19 | AB66: =AB50/AB49-1 -> 0.14084507 | AC66: 0.2 | AD66: =AD50/AD49-1 -> 0.140625 | AE66: =AE50/AE49-1 -> 0.13114754 | AF66: =AF50/AF49-1 -> 0.13559322
B68: 22 DIAS - 3.500 € | C68: 100 kms/dia | D68: 200 kms/dia | E68: 300 kms/dia | F68: 400 kms/dia | G68: 500 kms/dia | H68: 600 kms/dia | I68: 700 kms/dia | J68: 800 kms/dia | K68: 900 kms/dia | L68: 1000 kms/dia | M68: 1100 kms/dia | N68: 1200 kms/dia | O68: 1300 kms/dia | P68: 1400 kms/dia
B69: H2 (10€) | C69: 5.05 | D69: 2.95 | E69: 2.25 | F69: 1.9 | G69: 1.69 | H69: 1.55 | I69: 1.45 | J69: 1.58 | K69: 1.49 | L69: 1.43 | M69: 1.38 | N69: 1.33 | O69: 1.3 | P69: 1.27
B70: H2 (9€) | C70: 4.96 | D70: 2.87 | E70: 2.17 | F70: 1.82 | G70: 1.61 | H70: 1.47 | I70: 1.37 | J70: 1.49 | K70: 1.41 | L70: 1.35 | M70: 1.3 | N70: 1.25 | O70: 1.21 | P70: 1.18
B71: H2 (8€) | C71: 4.88 | D71: 2.78 | E71: 2.08 | F71: 1.73 | G71: 1.53 | H71: 1.39 | I71: 1.29 | J71: 1.41 | K71: 1.33 | L71: 1.26 | M71: 1.21 | N71: 1.17 | O71: 1.13 | P71: 1.1
B72: H2 (7€) | C72: 4.8 | D72: 2.7 | E72: 2 | F72: 1.65 | G72: 1.44 | H72: 1.3 | I72: 1.2 | J72: 1.25 | K72: 1.05 | L72: 1.18 | M72: 1.13 | N72: 1.08 | O72: 1.05 | P72: 1.02
B73: H2 (6€) | C73: 4.71 | D73: 2.62 | E73: 1.92 | F73: 1.57 | G73: 1.36 | H73: 1.22 | I73: 1.12 | J73: 1.24 | K73: 1.16 | L73: 1.1 | M73: 1.05 | N73: 1 | O73: 0.96 | P73: 0.93
B74: H2 (5€) | C74: 4.63 | D74: 2.53 | E74: 1.83 | F74: 1.49 | G74: 1.28 | H74: 1.14 | I74: 1.04 | J74: 1.16 | K74: 1.08 | L74: 1.01 | M74: 0.96 | N74: 0.92 | O74: 0.88 | P74: 0.85
B75: H2 (4€) | C75: 4.55 | D75: 2.45 | E75: 1.75 | F75: 1.4 | G75: 1.19 | H75: 1.05 | I75: 0.95 | J75: 1.08 | K75: 1 | L75: 0.93 | M75: 0.88 | N75: 0.84 | O75: 0.8 | P75: 0.77
B76: H2 (3€) | C76: 4.46 | D76: 2.37 | E76: 1.67 | F76: 1.32 | G76: 1.11 | H76: 0.97 | I76: 0.87 | J76: 0.99 | K76: 0.91 | L76: 0.85 | M76: 0.8 | N76: 0.75 | O76: 0.71 | P76: 0.68
B77: H2 (2€) | C77: 4.38 | D77: 2.28 | E77: 1.59 | F77: 1.24 | G77: 1.03 | H77: 0.89 | I77: 0.79 | J77: 0.91 | K77: 0.83 | L77: 0.77 | M77: 0.71 | N77: 0.67 | O77: 0.63 | P77: 0.6
B78: H2 (1€) | C78: 4.3 | D78: 2.2 | E78: 1.5 | F78: 1.15 | G78: 0.94 | H78: 0.8 | I78: 0.7 | J78: 0.83 | K78: 0.75 | L78: 0.68 | M78: 0.63 | N78: 0.59 | O78: 0.55 | P78: 0.52
B79: GAS NATURAL (0,6 €) | C79: 3.6 | D79: 1.89 | E79: 1.32 | F79: 1.04 | G79: 0.87 | H79: 0.75 | I79: 0.67 | J79: 0.81 | K79: 0.74 | L79: 0.69 | M79: 0.64 | N79: 0.6 | O79: 0.57 | P79: 0.54
B80: GASOIL (1 €) | C80: 3.19 | D80: 1.77 | E80: 1.29 | F80: 1.06 | G80: 0.92 | H80: 0.82 | I80: 0.75 | J80: 0.88 | K80: 0.82 | L80: 0.78 | M80: 0.94 | N80: 0.89 | O80: 0.85 | P80: 0.82
... B82: GASOIL (0,8 €) | C82: 3.12 | D82: 1.7 | E82: 1.23 | F82: 0.99 | G82: 0.85 | H82: 0.76 | I82: 0.69 | J82: 0.82 | K82: 0.76 | L82: 0.71 | M82: 0.67 | N82: 0.64 | O82: 0.61 | P82: 0.59
B86: 22 D - 3.500 € (G.0,8) | C86: 100 kms/dia | D86: 200 kms/dia | E86: 300 kms/dia | F86: 400 kms/dia | G86: 500 kms/dia | H86: 600 kms/dia | I86: 700 kms/dia | J86: 800 kms/dia | K86: 900 kms/dia | L86: 1000 kms/dia | M86: 1100 kms/dia | N86: 1200 kms/dia | O86: 1300 kms/dia | P86: 1400 kms/dia
B87: H2 (10€) | C87: =C69/C$82-1 -> 0.61858974 | D87: =D69/D$82-1 -> 0.73529412 | E87: =E69/E$82-1 -> 0.82926829 | F87: =F69/F$82-1 -> 0.91919192 | G87: =G69/G$82-1 -> 0.98823529 | H87: =H69/H$82-1 -> 1.0394737 | I87: =I69/I$82-1 -> 1.1014493 | J87: =J69/J$82-1 -> 0.92682927 | ... P87: =P69/P$82-1 -> 1.1525424
B88: H2 (9€) | C88: =C70/C$82-1 -> 0.58974359 | D88: =D70/D$82-1 -> 0.68823529 | E88: =E70/E$82-1 -> 0.76422764 | F88: =F70/F$82-1 -> 0.83838384 | G88: =G70/G$82-1 -> 0.89411765 | H88: =H70/H$82-1 -> 0.93421053 | I88: =I70/I$82-1 -> 0.98550725 | J88: =J70/J$82-1 -> 0.81707317 | ... P88: =P70/P$82-1 -> 1
B89: H2 (8€) | C89: =C71/C$82-1 -> 0.56410256 | D89: =D71/D$82-1 -> 0.63529412 | E89: =E71/E$82-1 -> 0.69105691 | F89: =F71/F$82-1 -> 0.74747475 | G89: =G71/G$82-1 -> 0.8 | H89: =H71/H$82-1 -> 0.82894737 | I89: =I71/I$82-1 -> 0.86956522 | J89: =J71/J$82-1 -> 0.7195122 | ... P89: =P71/P$82-1 -> 0.86440678
B90: H2 (7€) | C90: =C72/C$82-1 -> 0.53846154 | D90: =D72/D$82-1 -> 0.58823529 | E90: =E72/E$82-1 -> 0.62601626 | F90: =F72/F$82-1 -> 0.66666667 | G90: =G72/G$82-1 -> 0.69411765 | H90: =H72/H$82-1 -> 0.71052632 | I90: =I72/I$82-1 -> 0.73913043 | J90: =J72/J$82-1 -> 0.52439024 | ... P90: =P72/P$82-1 -> 0.72881356
B91: H2 (6€) | C91: =C73/C$82-1 -> 0.50961538 | D91: =D73/D$82-1 -> 0.54117647 | E91: =E73/E$82-1 -> 0.56097561 | F91: =F73/F$82-1 -> 0.58585859 | G91: =G73/G$82-1 -> 0.6 | H91: =H73/H$82-1 -> 0.60526316 | I91: =I73/I$82-1 -> 0.62318841 | J91: =J73/J$82-1 -> 0.51219512 | ... P91: =P73/P$82-1 -> 0.57627119
B92: H2 (5€) | C92: =C74/C$82-1 -> 0.48397436 | D92: =D74/D$82-1 -> 0.48823529 | E92: =E74/E$82-1 -> 0.48780488 | F92: =F74/F$82-1 -> 0.50505051 | G92: =G74/G$82-1 -> 0.50588235 | H92: =H74/H$82-1 -> 0.5 | I92: =I74/I$82-1 -> 0.50724638 | J92: =J74/J$82-1 -> 0.41463415 | ... P92: =P74/P$82-1 -> 0.44067797
B93: H2 (4€) | C93: =C75/C$82-1 -> 0.45833333 | D93: =D75/D$82-1 -> 0.44117647 | E93: =E75/E$82-1 -> 0.42276423 | F93: =F75/F$82-1 -> 0.41414141 | G93: =G75/G$82-1 -> 0.4 | H93: =H75/H$82-1 -> 0.38157895 | I93: =I75/I$82-1 -> 0.37681159 | J93: =J75/J$82-1 -> 0.31707317 | ... P93: =P75/P$82-1 -> 0.30508475
B94: H2 (3€) | C94: =C76/C$82-1 -> 0.42948718 | D94: =D76/D$82-1 -> 0.39411765 | E94: =E76/E$82-1 -> 0.35772358 | F94: =F76/F$82-1 -> 0.33333333 | G94: =G76/G$82-1 -> 0.30588235 | H94: =H76/H$82-1 -> 0.27631579 | I94: =I76/I$82-1 -> 0.26086957 | J94: =J76/J$82-1 -> 0.20731707 | ... P94: =P76/P$82-1 -> 0.15254237
B95: H2 (2€) | C95: =C77/C$82-1 -> 0.40384615 | D95: =D77/D$82-1 -> 0.34117647 | E95: =E77/E$82-1 -> 0.29268293 | F95: =F77/F$82-1 -> 0.25252525 | G95: =G77/G$82-1 -> 0.21176471 | H95: =H77/H$82-1 -> 0.17105263 | I95: =I77/I$82-1 -> 0.14492754 | J95: =J77/J$82-1 -> 0.1097561 | ... P95: =P77/P$82-1 -> 0.016949153
B96: H2 (1€) | C96: =C78/C$82-1 -> 0.37820513 | D96: =D78/D$82-1 -> 0.29411765 | E96: =E78/E$82-1 -> 0.2195122 | F96: =F78/F$82-1 -> 0.16161616 | G96: =G78/G$82-1 -> 0.10588235 | H96: =H78/H$82-1 -> 0.052631579 | I96: =I78/I$82-1 -> 0.014492754 | J96: =J78/J$82-1 -> 0.012195122 | ... P96: =P78/P$82-1 -> -0.11864407
B97: GAS NATURAL (0,6 €) | C97: =C79/C$82-1 -> 0.15384615 | D97: =D79/D$82-1 -> 0.11176471 | E97: =E79/E$82-1 -> 0.073170732 | F97: =F79/F$82-1 -> 0.050505051 | G97: =G79/G$82-1 -> 0.023529412 | H97: =H79/H$82-1 -> -0.013157895 | I97: =I79/I$82-1 -> -0.028985507 | J97: =J79/J$82-1 -> -0.012195122 | ... P97: =P79/P$82-1 -> -0.084745763
B98: GASOIL (0,8 €) | C98: 0 | D98: 0 | E98: 0 | F98: 0 | G98: 0 | H98: 0 | I98: 0 | J98: 0 | K98: 0 | L98: 0 | M98: 0 | N98: 0 | O98: 0 | P98: 0
B102: 22 D - 3500 € (G.0,9) | C102: 100 kms/dia | D102: 200 kms/dia | E102: 300 kms/dia | F102: 400 kms/dia | G102: 500 kms/dia | H102: 600 kms/dia | I102: 700 kms/dia | J102: 800 kms/dia | K102: 900 kms/dia | L102: 1000 kms/dia | M102: 1100 kms/dia | N102: 1200 kms/dia | O102: 1300 kms/dia | P102: 1400 kms/dia
B103: H2 (10€) | C103: =C69/C$16-1 -> 0.6031746 | D103: =D69/D$16-1 -> 0.70520231 | E103: =E69/E$16-1 -> 0.78571429 | F103: =F69/F$16-1 -> 0.84466019 | G103: =G69/G$16-1 -> 0.92045455 | H103: =H69/H$16-1 -> 0.96202532 | I103: =I69/I$16-1 -> 1.0138889 | J103: =J69/J$16-1 -> 0.85882353 | ... P103: =P69/P$16-1 -> 1.0483871
B104: H2 (9€) | C104: =C70/C$16-1 -> 0.57460317 | D104: =D70/D$16-1 -> 0.65895954 | E104: =E70/E$16-1 -> 0.72222222 | F104: =F70/F$16-1 -> 0.76699029 | G104: =G70/G$16-1 -> 0.82954545 | H104: =H70/H$16-1 -> 0.86075949 | I104: =I70/I$16-1 -> 0.90277778 | J104: =J70/J$16-1 -> 0.75294118 | ... P104: =P70/P$16-1 -> 0.90322581
B105: H2 (8€) | C105: =C71/C$16-1 -> 0.54920635 | D105: =D71/D$16-1 -> 0.60693642 | E105: =E71/E$16-1 -> 0.65079365 | F105: =F71/F$16-1 -> 0.67961165 | G105: =G71/G$16-1 -> 0.73863636 | H105: =H71/H$16-1 -> 0.75949367 | I105: =I71/I$16-1 -> 0.79166667 | J105: =J71/J$16-1 -> 0.65882353 | ... P105: =P71/P$16-1 -> 0.77419355
B106: H2 (7€) | C106: =C72/C$16-1 -> 0.52380952 | D106: =D72/D$16-1 -> 0.56069364 | E106: =E72/E$16-1 -> 0.58730159 | F106: =F72/F$16-1 -> 0.60194175 | G106: =G72/G$16-1 -> 0.63636364 | H106: =H72/H$16-1 -> 0.64556962 | I106: =I72/I$16-1 -> 0.66666667 | J106: =J72/J$16-1 -> 0.47058824 | ... P106: =P72/P$16-1 -> 0.64516129
B107: H2 (6€) | C107: =C73/C$16-1 -> 0.4952381 | D107: =D73/D$16-1 -> 0.51445087 | E107: =E73/E$16-1 -> 0.52380952 | F107: =F73/F$16-1 -> 0.52427184 | G107: =G73/G$16-1 -> 0.54545455 | H107: =H73/H$16-1 -> 0.5443038 | I107: =I73/I$16-1 -> 0.55555556 | J107: =J73/J$16-1 -> 0.45882353 | ... P107: =P73/P$16-1 -> 0.5
B108: H2 (5€) | C108: =C74/C$16-1 -> 0.46984127 | D108: =D74/D$16-1 -> 0.46242775 | E108: =E74/E$16-1 -> 0.45238095 | F108: =F74/F$16-1 -> 0.44660194 | G108: =G74/G$16-1 -> 0.45454545 | H108: =H74/H$16-1 -> 0.44303797 | I108: =I74/I$16-1 -> 0.44444444 | J108: =J74/J$16-1 -> 0.36470588 | ... P108: =P74/P$16-1 -> 0.37096774
B109: H2 (4€) | C109: =C75/C$16-1 -> 0.44444444 | D109: =D75/D$16-1 -> 0.41618497 | E109: =E75/E$16-1 -> 0.38888889 | F109: =F75/F$16-1 -> 0.3592233 | G109: =G75/G$16-1 -> 0.35227273 | H109: =H75/H$16-1 -> 0.32911392 | I109: =I75/I$16-1 -> 0.31944444 | J109: =J75/J$16-1 -> 0.27058824 | ... P109: =P75/P$16-1 -> 0.24193548
B110: H2 (3€) | C110: =C76/C$16-1 -> 0.41587302 | D110: =D76/D$16-1 -> 0.3699422 | E110: =E76/E$16-1 -> 0.32539683 | F110: =F76/F$16-1 -> 0.2815534 | G110: =G76/G$16-1 -> 0.26136364 | H110: =H76/H$16-1 -> 0.2278481 | I110: =I76/I$16-1 -> 0.20833333 | J110: =J76/J$16-1 -> 0.16470588 | ... P110: =P76/P$16-1 -> 0.096774194
B111: H2 (2€) | C111: =C77/C$16-1 -> 0.39047619 | D111: =D77/D$16-1 -> 0.31791908 | E111: =E77/E$16-1 -> 0.26190476 | F111: =F77/F$16-1 -> 0.2038835 | G111: =G77/G$16-1 -> 0.17045455 | H111: =H77/H$16-1 -> 0.12658228 | I111: =I77/I$16-1 -> 0.097222222 | J111: =J77/J$16-1 -> 0.070588235 | ... P111: =P77/P$16-1 -> -0.032258065
B112: H2 (1€) | C112: =C78/C$16-1 -> 0.36507937 | D112: =D78/D$16-1 -> 0.2716763 | E112: =E78/E$16-1 -> 0.19047619 | F112: =F78/F$16-1 -> 0.11650485 | G112: =G78/G$16-1 -> 0.068181818 | H112: =H78/H$16-1 -> 0.012658228 | I112: =I78/I$16-1 -> -0.027777778 | J112: =J78/J$16-1 -> -0.023529412 | ... P112: =P78/P$16-1 -> -0.16129032
B113: GAS NATURAL (0,6 €) | C113: =C79/C$16-1 -> 0.14285714 | D113: =D79/D$16-1 -> 0.092485549 | E113: =E79/E$16-1 -> 0.047619048 | F113: =F79/F$16-1 -> 0.0097087379 | G113: =G79/G$16-1 -> -0.011363636 | H113: =H79/H$16-1 -> -0.050632911 | I113: =I79/I$16-1 -> -0.069444444 | J113: =J79/J$16-1 -> -0.047058824 | ... P113: =P79/P$16-1 -> -0.12903226
B114: GASOIL (0,9 €) | C114: =C82/C$17-1 -> 0 | D114: =D82/D$17-1 -> 0 | E114: =E82/E$17-1 -> 0 | F114: =F82/F$17-1 -> 0 | G114: =G82/G$17-1 -> 0 | H114: =H82/H$17-1 -> 0 | I114: =I82/I$17-1 -> 0 | J114: =J82/J$17-1 -> 0 | ... P114: =P82/P$17-1 -> 0
B118: 22 D - 3.5000 € (G.1) | C118: 100 kms/dia | D118: 200 kms/dia | E118: 300 kms/dia | F118: 400 kms/dia | G118: 500 kms/dia | H118: 600 kms/dia | I118: 700 kms/dia | J118: 800 kms/dia | K118: 900 kms/dia | L118: 1000 kms/dia | M118: 1100 kms/dia | N118: 1200 kms/dia | O118: 1300 kms/dia | P118: 1400 kms/dia
B119: H2 (10€) | C119: =C69/C$15-1 -> 0.5830721 | D119: =D69/D$15-1 -> 0.66666667 | E119: =E69/E$15-1 -> 0.74418605 | F119: =F69/F$15-1 -> 0.79245283 | G119: =G69/G$15-1 -> 0.83695652 | H119: =H69/H$15-1 -> 0.8902439 | I119: =I69/I$15-1 -> 0.93333333 | J119: =J69/J$15-1 -> 0.79545455 | ... P119: =P69/P$15-1 -> 0.54878049
...

Sheet Hoja1
B3: Datos mayo 2021 | C3: Kg CO2 | D3: % Evitadas/ Emitidas
B4: EMISIONES TOTALES | C4: 333805 | D4: -
B5: EMISIOSES TOTALES EVITADAS | C5: 55006 | D5: =C5/C4 -> 0.16478483
B6: Optimización rutas (Kms vacio) | C6: 23549 | D6: =C6/C4 -> 0.070547176
B7: Intermodalidad | C7: 16273 | D7: =C7/C4 -> 0.048750019
B8: Medidas eficiencia (Reducción consumo) | C8: 14441 | D8: =C8/C4 -> 0.043261785
B9: Desarrolllo provedores (Veh Sostenibles) | C9: 744 | D9: =C9/C4 -> 0.0022288462

Sheet GRAFICOS
S63: VEH/KMS | T63: 100 KMS | U63: 200 KMS | V63: 300 KMS | W63: 400 KMS | X63: 500 KMS | Y63: 600 KMS | Z63: 700 KMS
S64: DIESEL | T64: 3.1527709 | U64: 1.7344135 | V64: 1.2616276 | W64: 1.0252347 | X64: 0.88339898 | Y64: 0.78884182 | Z64: 0.72130099
S65: GAS NATURAL | T65: 3.5780988 | U65: 1.8818174 | V65: 1.3163903 | W65: 1.0336767 | X65: 0.86404855 | Y65: 0.75096313 | Z65: 0.67018782
S66: H2 | T66: 4.3134355 | U66: 2.3335177 | V66: 1.6735452 | W66: 1.3435589 | X66: 1.1455671 | Y66: 1.0135726 | Z66: 0.91929078
S67: BIOMETANO | T67: 3.7016508 | U67: 2.0053694 | V67: 1.4399423 | W67: 1.1572287 | X67: 0.98760055 | Y67: 0.87451513 | Z67: 0.79373982
S68: ELECTRICO | T68: 4.2361446 | U68: 2.2571723 | V68: 1.5975149 | W68: 1.2676861 | X68: 1.0697889 | Y68: 0.93785743 | Z68: 0.84362065
S69: HVO | T69: 3.5131309 | U69: 2.0947735 | V69: 1.6219876 | W69: 1.3855947 | X69: 1.243759 | Y69: 1.1492018 | Z69: 1.081661
S70: DUO H2 | T70: 2.4912574 | U70: 1.3727167 | V70: 0.99986979 | W70: 0.81344635 | X70: 0.70159228 | Y70: 0.6270229 | Z70: 0.57375905
S71: DUO GASOIL | T71: 2.1101399 | U71: 1.168872 | V71: 0.85511598 | W71: 0.69823798 | X71: 0.60411119 | Y71: 0.54135999 | Z71: 0.4965377
S72: DUO BIOMETANO | T72: 2.2237353 | U72: 1.2233765 | V72: 0.88992352 | W72: 0.72319704 | X72: 0.62316115 | Y72: 0.55647056 | Z72: 0.50883442
S73: DUO HVO | T73: 2.3623919 | U73: 1.421124 | V73: 1.107368 | W73: 0.95048998 | X73: 0.85636319 | Y73: 0.79361199 | Z73: 0.7487897
S74: DUO ELECTRICO | T74: 2.4384774 | U74: 1.3199367 | V74: 0.94708979 | W74: 0.76066635 | X74: 0.64881228 | Y74: 0.5742429 | Z74: 0.52097905
S75: SECTOR | T75: 2 | U75: 1.5 | V75: 1 | W75: =#REF! -> #REF! | X75: =W75 -> #REF! | Y75: =W75 -> #REF! | Z75: =W75 -> #REF!
